Workbook

Sheet Обложка
B2: Мандат — финансовая модель
B3: Версия 1.0 от 27.10.2026. Трек ВТБ «Финтех без границ», «Академия Финтеха 2026». Деньги — млн ₽ без НДС; цены 2027 года, дальше индексация
B5: Главное
B6: Показатель | C6: Консервативный | D6: Базовый | E6: Оптимистичный
B7: Высвобождается ставок в ВТБ | C7: =Сводка!D6 -> 33 | D7: =Сводка!E6 -> 75 | E7: =Сводка!F6 -> 167
B8: Предотвращённый ущерб клиентов ВТБ, млн ₽ в год | C8: =Сводка!D7 -> 34 | D8: =Сводка!E7 -> 115 | E8: =Сводка!F7 -> 229
B9: Окупаемость для ВТБ (деньги), месяцев | C9: =Сводка!D11 -> 33.074022 | D9: =Сводка!E11 -> 8.0099861 | E9: =Сводка!F11 -> 1.5072704
B10: SAM: банки уровней 1 и 2, одна операция, млн ₽ в год | C10: =Сводка!D15 -> 101.1 | D10: =Сводка!E15 -> 186.75 | E10: =Сводка!F15 -> 251.85
B11: Выручка 2031 года, млн ₽ | C11: =Сводка!D21 -> 11.947181 | D11: =Сводка!E21 -> 67.776952 | E11: =Сводка!F21 -> 141.84839
B12: Потребность в финансировании, млн ₽ | C12: =Сводка!D26 -> 78.123714 | D12: =Сводка!E26 -> 33.332275 | E12: =Сводка!F26 -> 39.390185
B13: Год выхода на операционную прибыль | C13: =Сводка!D27 -> после 2031 | D13: =Сводка!E27 -> 2029 | E13: =Сводка!F27 -> 2030
B14: NPV с остаточной стоимостью, млн ₽ | C14: =Сводка!D30 -> -31.664046 | D14: =Сводка!E30 -> -0.14959473 | E14: =Сводка!F30 -> 41.570143
B16: Статус проверок | C16: =Проверки!$F$50 -> ОК | D16: ="Ошибок: "&Проверки!$E$48&", предупреждений: "&Проверки!$E$49 -> Ошибок: 0, предупреждений: 0
B18: Что внутри
B19: Сводка | C19: главные результаты трёх сценариев и графики
B20: Допущения | C20: все параметры по сценариям с типом, источником и способом проверки на пилоте
B21: План | C21: договоры с банками и команда по годам
B22: Эффект для банка | C22: ставки и ущерб как в презентации, деньги для ВТБ, окупаемость, «купить или сделать»
B23: Рынок | C23: TAM, SAM, SOM снизу вверх и сверху вниз
B24: Консервативный, Базовый, Оптимистичный | C24: полный расчёт сценария: выручка, затраты, отчёт, деньги, NPV
B25: Чувствительность | C25: NPV базового сценария при ±20 % по каждому допущению
B26: Проверки | C26: целостность модели и рамки допущений
B27: Источники | C27: откуда взяты факты
B29: Как пользоваться
B30: • Меняйте только синие ячейки на листах «Допущения» и «План»: каждый сценарий — свой столбец. Всё остальное — формулы.
B31: • Жёлтая заливка — допущения, которые банк заменит своими данными на пилоте (клиенты, события, минуты, оклады, цена).
B32: • Зелёный — ссылка на другой лист, чёрный — формула на этом листе.
B33: • После правки посмотрите лист «Проверки»: итог должен быть «ОК».
B34: • Пересобрать с нуля: python submission/analytics/build_model.py (нужен LibreOffice для пересчёта).
B36: Легенда
C37: 12,3 | D37: введено руками (допущение)
C38: 12,3 | D38: ключевое допущение
C39: 12,3 | D39: ссылка на другой лист
C40: 12,3 | D40: формула

Sheet Сводка
A1: Сводка по сценариям
A2: Все числа — ссылки на листы сценариев; млн ₽ без НДС
A4: № | B4: Показатель | C4: Единица | D4: Консервативный | E4: Базовый | F4: Оптимистичный
A5: Эффект для ВТБ
A6: 1 | B6: Высвобождается ставок | C6: ставок | D6: ='Эффект для банка'!$D$36 -> 33 | E6: ='Эффект для банка'!$E$36 -> 75 | F6: ='Эффект для банка'!$F$36 -> 167
A7: 2 | B7: Предотвращённый ущерб клиентов | C7: млн ₽ в год | D7: ='Эффект для банка'!$D$44 -> 34 | E7: ='Эффект для банка'!$E$44 -> 115 | F7: ='Эффект для банка'!$F$44 -> 229
A8: 3 | B8: Прямой эффект банка: ёмкость | C8: млн ₽ в год | D8: ='Эффект для банка'!$D$47 -> 56.5596 | E8: ='Эффект для банка'!$E$47 -> 164.6964 | F8: ='Эффект для банка'!$F$47 -> 463.524
A9: 4 | B9: Прямой эффект банка: деньги | C9: млн ₽ в год | D9: ='Эффект для банка'!$D$48 -> 19.37448 | E9: ='Эффект для банка'!$E$48 -> 91.4589 | F9: ='Эффект для банка'!$F$48 -> 341.6568
A10: 5 | B10: Подписка для ВТБ (цены 2027) | C10: млн ₽ в год | D10: ='Эффект для банка'!$D$51 -> 6.6 | E10: ='Эффект для банка'!$E$51 -> 15 | F10: ='Эффект для банка'!$F$51 -> 20.6
A11: 6 | B11: Окупаемость для ВТБ: деньги | C11: месяцев | D11: ='Эффект для банка'!$D$60 -> 33.074022 | E11: ='Эффект для банка'!$E$60 -> 8.0099861 | F11: ='Эффект для банка'!$F$60 -> 1.5072704
A12: 7 | B12: Отдача за 3 года на вложенный рубль: деньги | C12: раз | D12: ='Эффект для банка'!$D$59 -> 0.055945062 | E12: ='Эффект для банка'!$E$59 -> 2.2313065 | F12: ='Эффект для банка'!$F$59 -> 9.1022117
A13: Рынок
A14: 8 | B14: TAM: все банки России | C14: млн ₽ в год | D14: =Рынок!$D$36 -> 173.4 | E14: =Рынок!$E$36 -> 307.25 | F14: =Рынок!$F$36 -> 420.55
A15: 9 | B15: SAM: банки уровней 1 и 2, одна операция | C15: млн ₽ в год | D15: =Рынок!$D$37 -> 101.1 | E15: =Рынок!$E$37 -> 186.75 | F15: =Рынок!$F$37 -> 251.85
A16: 10 | B16: SAM при полном охвате операций | C16: млн ₽ в год | D16: =Рынок!$D$40 -> 101.1 | E16: =Рынок!$E$40 -> 326.62692 | F16: =Рынок!$F$40 -> 614.86816
A17: 11 | B17: SOM: подписка на конец 2031 (цены 2027) | C17: млн ₽ в год | D17: =Рынок!$D$44 -> 9.76875 | E17: =Рынок!$E$44 -> 61.400727 | F17: =Рынок!$F$44 -> 134.74225
A18: 12 | B18: SOM в доле SAM при полном охвате | C18: доля | D18: =Рынок!$D$45 -> 0.096624629 | E18: =Рынок!$E$45 -> 0.18798428 | F18: =Рынок!$F$45 -> 0.21914007
A19: Проект
A20: 13 | B20: Выручка 2027–2031 | C20: млн ₽ | D20: =Консервативный!$D$126 -> 37.247677 | E20: =Базовый!$D$126 -> 171.04852 | F20: =Оптимистичный!$D$126 -> 322.68477
A21: 14 | B21: Выручка 2031 | C21: млн ₽ | D21: =Консервативный!$D$127 -> 11.947181 | E21: =Базовый!$D$127 -> 67.776952 | F21: =Оптимистичный!$D$127 -> 141.84839
A22: 15 | B22: ARR на конец 2031 | C22: млн ₽ | D22: =Консервативный!$D$128 -> 11.428056 | E22: =Базовый!$D$128 -> 74.632967 | F22: =Оптимистичный!$D$128 -> 170.10899
A23: 16 | B23: Операционная прибыль 2031 | C23: млн ₽ | D23: =Консервативный!$D$129 -> -11.838856 | E23: =Базовый!$D$129 -> 20.079808 | F23: =Оптимистичный!$D$129 -> 53.050325
A24: 17 | B24: Банков с договором к концу 2031 | C24: банков | D24: =Консервативный!$D$130 -> 4 | E24: =Базовый!$D$130 -> 11 | F24: =Оптимистичный!$D$130 -> 18
A25: 18 | B25: Команда к концу 2031 | C25: ставок | D25: =Консервативный!$D$131 -> 4 | E25: =Базовый!$D$131 -> 8 | F25: =Оптимистичный!$D$131 -> 15
A26: 19 | B26: Потребность в финансировании с запасом | C26: млн ₽ | D26: =Консервативный!$D$133 -> 78.123714 | E26: =Базовый!$D$133 -> 33.332275 | F26: =Оптимистичный!$D$133 -> 39.390185
A27: 20 | B27: Год выхода на операционную прибыль | C27: год | D27: =Консервативный!$D$138 -> после 2031 | E27: =Базовый!$D$138 -> 2029 | F27: =Оптимистичный!$D$138 -> 2030
A28: 21 | B28: Год окупаемости вложений | C28: год | D28: =Консервативный!$D$139 -> после 2031 | E28: =Базовый!$D$139 -> после 2031 | F28: =Оптимистичный!$D$139 -> 2031
A29: 22 | B29: NPV без остаточной стоимости | C29: млн ₽ | D29: =Консервативный!$D$135 -> -31.664046 | E29: =Базовый!$D$135 -> -14.756216 | F29: =Оптимистичный!$D$135 -> -4.248058
A30: 23 | B30: NPV с остаточной стоимостью | C30: млн ₽ | D30: =Консервативный!$D$136 -> -31.664046 | E30: =Базовый!$D$136 -> -0.14959473 | F30: =Оптимистичный!$D$136 -> 41.570143
A31: 24 | B31: IRR с остаточной стоимостью | C31: доля | D31: =Консервативный!$D$137 -> н/д | E31: =Базовый!$D$137 -> 0.29711998 | F31: =Оптимистичный!$D$137 -> 0.78510393
A33: № | B33: Показатель по годам | C33: Сценарий | D33: 2027 | E33: 2028 | F33: 2029 | G33: 2030 | H33: 2031
B34: Выручка | C34: Консервативный | D34: =Консервативный!F74 -> 0 | E34: =Консервативный!G74 -> 6.24 | F34: =Консервативный!H74 -> 8.76096 | G34: =Консервативный!I74 -> 10.299536 | H34: =Консервативный!J74 -> 11.947181
B35: Выручка | C35: Базовый | D35: =Базовый!F74 -> 8 | E35: =Базовый!G74 -> 17.85 | F35: =Базовый!H74 -> 34.056914 | G35: =Базовый!I74 -> 43.364649 | H35: =Базовый!J74 -> 67.776952
B36: Выручка | C36: Оптимистичный | D36: =Оптимистичный!F74 -> 10 | E36: =Оптимистичный!G74 -> 27.136 | F36: =Оптимистичный!H74 -> 53.532517 | G36: =Оптимистичный!I74 -> 90.167863 | H36: =Оптимистичный!J74 -> 141.84839
B37: Операционная прибыль | C37: Консервативный | D37: =Консервативный!F105 -> -11.048796 | E37: =Консервативный!G105 -> -13.904266 | F37: =Консервативный!H105 -> -12.353668 | G37: =Консервативный!I105 -> -12.029669 | H37: =Консервативный!J105 -> -11.838856
B38: Операционная прибыль | C38: Базовый | D38: =Базовый!F105 -> -14.07621 | E38: =Базовый!G105 -> -7.10975 | F38: =Базовый!H105 -> 1.8529838 | G38: =Базовый!I105 -> 4.0472884 | H38: =Базовый!J105 -> 20.079808
B39: Операционная прибыль | C39: Оптимистичный | D39: =Оптимистичный!F105 -> -13.50621 | E39: =Оптимистичный!G105 -> -9.8447412 | F39: =Оптимистичный!H105 -> -0.67433728 | G39: =Оптимистичный!I105 -> 22.948053 | H39: =Оптимистичный!J105 -> 53.050325
B40: Накопленный денежный поток | C40: Консервативный | D40: =Консервативный!F117 -> -11.048796 | E40: =Консервативный!G117 -> -27.004569 | F40: =Консервативный!H117 -> -40.187046 | G40: =Консервативный!I117 -> -52.722548 | H40: =Консервативный!J117 -> -65.103095
B41: Накопленный денежный поток | C41: Базовый | D41: =Базовый!F117 -> -16.048813 | E41: =Базовый!G117 -> -25.58733 | F41: =Базовый!H117 -> -27.776896 | G41: =Базовый!I117 -> -26.125848 | H41: =Базовый!J117 -> -12.567507
B42: Накопленный денежный поток | C42: Оптимистичный | D42: =Оптимистичный!F117 -> -15.150045 | E42: =Оптимистичный!G117 -> -27.811663 | F42: =Оптимистичный!H117 -> -32.825154 | G42: =Оптимистичный!I117 -> -16.473051 | H42: =Оптимистичный!J117 -> 26.056892
B43: Банков с договором | C43: Консервативный | D43: =Консервативный!F66 -> 0 | E43: =Консервативный!G66 -> 1 | F43: =Консервативный!H66 -> 2 | G43: =Консервативный!I66 -> 3 | H43: =Консервативный!J66 -> 4
B44: Банков с договором | C44: Базовый | D44: =Базовый!F66 -> 1 | E44: =Базовый!G66 -> 2 | F44: =Базовый!H66 -> 5 | G44: =Базовый!I66 -> 7 | H44: =Базовый!J66 -> 11
B45: Банков с договором | C45: Оптимистичный | D45: =Оптимистичный!F66 -> 1 | E45: =Оптимистичный!G66 -> 3 | F45: =Оптимистичный!H66 -> 7 | G45: =Оптимистичный!I66 -> 12 | H45: =Оптимистичный!J66 -> 18
B46: Команда, ставок | C46: Консервативный | D46: =Консервативный!F77 -> 2.5 | E46: =Консервативный!G77 -> 3.5 | F46: =Консервативный!H77 -> 4 | G46: =Консервативный!I77 -> 4 | H46: =Консервативный!J77 -> 4
B47: Команда, ставок | C47: Базовый | D47: =Базовый!F77 -> 4 | E47: =Базовый!G77 -> 5 | F47: =Базовый!H77 -> 6 | G47: =Базовый!I77 -> 7 | H47: =Базовый!J77 -> 8
B48: Команда, ставок | C48: Оптимистичный | D48: =Оптимистичный!F77 -> 4 | E48: =Оптимистичный!G77 -> 7 | F48: =Оптимистичный!H77 -> 10 | G48: =Оптимистичный!I77 -> 12 | H48: =Оптимистичный!J77 -> 15

Sheet Допущения
A1: Допущения
A2: Синий — введено руками, жёлтая заливка — ключевые допущения, которые банк заменит своими данными
A3: Год начала модели (исходные остатки) | D3: 2026
A5: № | B5: Параметр | C5: Единица | D5: Консервативный | E5: Базовый | F5: Оптимистичный | G5: Тип | H5: Источник или обоснование | I5: Как проверить на пилоте
A6: П. Эффект для ВТБ: параметры презентации (effect_scenarios.json)
A7: П1 | B7: Клиенты ВТБ — предприятия и предприниматели | C7: млн | D7: 1.8 | E7: 1.8 | F7: 1.8 | G7: вторичный | H7: Пресс-релиз ВТБ к МСФО за I полугодие 2026 в пересказе altapress.ru и kp.ru (M-09, S05) | I7: внутренняя цифра банка
A8: П2 | B8: Доля клиентов со сменой или добавлением подписанта в год | C8: доля | D8: 0.1 | E8: 0.15 | F8: 0.25 | G8: допущение | H8: Допущение команды (C-15); публичных данных нет | I8: число событий за год в журнале банка
A9: П3 | B9: Минут на кейс вручную, вместе с разбором | C9: минут | D9: 20 | E9: 30 | F9: 40 | G9: допущение | H9: Допущение команды (C-15); замер — в пилоте | I9: хронометраж в пилоте
A10: П4 | B10: Рабочих часов на ставку в год | C10: часов | D10: 1800 | E10: 1800 | F10: 1800 | G10: допущение | H10: Около 1 970 часов по производственному календарю минус отпуск | I10: норма банка
A11: П5 | B11: Операций без согласия у юрлиц за квартал | C11: операций | D11: 818 | E11: 818 | F11: 818 | G11: факт | H11: Банк России, I кв. 2026 (M-07, S03) | I11: —
A12: П6 | B12: Объём таких операций за квартал | C12: млн ₽ | D12: 573 | E12: 573 | F12: 573 | G12: факт | H12: Банк России, I кв. 2026 (M-07, S03) | I12: —
A13: П7 | B13: Доля ВТБ в таких инцидентах | C13: доля | D13: 0.15 | E13: 0.2 | F13: 0.25 | G13: допущение | H13: Допущение команды (C-16) | I13: данные антифрода банка
A14: П8 | B14: Доля инцидентов, связанных с полномочиями | C14: доля | D14: 0.1 | E14: 0.25 | F14: 0.4 | G14: допущение | H14: Допущение команды (C-16) | I14: разметка инцидентов банка
A15: Э. Эффект для ВТБ: стоимость времени и доля ущерба
A16: Э1 | B16: Оклад сотрудника, проверяющего документы | C16: тыс. ₽ в месяц | D16: 85 | E16: 100 | F16: 120 | G16: допущение | H16: Вакансии операционистов по работе с юрлицами — от 60–100 тыс. ₽ до вычета налогов (hh.ru, октябрь 2026, S14); средняя по финансовой отрасли — 314 тыс. ₽ (Росстат, март 2026, S13) — верхний ориентир | I16: фонд оплаты труда подразделения по данным банка
A17: Э2 | B17: Страховые взносы банка | C17: доля | D17: 0.302 | E17: 0.302 | F17: 0.302 | G17: факт | H17: Общий тариф 30 % в пределах базы и взнос на травматизм от 0,2 % (НК РФ, гл. 34; 125-ФЗ) | I17: тариф банка на травматизм
A18: Э3 | B18: Накладные на рабочее место (помещение, ИТ, управление) | C18: доля к ФОТ с взносами | D18: 0.2 | E18: 0.25 | F18: 0.3 | G18: допущение | H18: Оценка команды для бэк-офиса крупного банка | I18: методика внутреннего учёта затрат банка
A19: Э4 | B19: Доля высвобожденного времени, которая становится экономией | C19: доля | D19: 0.3 | E19: 0.5 | F19: 0.7 | G19: допущение | H19: Высвобожденное время становится деньгами, только если банк перераспределяет людей или не нанимает новых; остальное — ёмкость под рост потока | I19: план банка по численности подразделения
A20: Э5 | B20: Доля предотвращённого ущерба клиентов, которую несёт банк | C20: доля | D20: 0.1 | E20: 0.159 | F20: 0.25 | G20: допущение | H20: Ориентир — доля возмещённого юрлицам по счетам в I кв. 2026: 15,9 % (Банк России, M-07, S03) | I20: данные банка о возмещениях и претензиях клиентов
A21: Э6 | B21: Эффект в первый год работы (раскачка) | C21: доля | D21: 0.5 | E21: 0.5 | F21: 0.5 | G21: допущение | H21: Первый год — одна операция и постепенный перевод потока | I21: план тиражирования после пилота
A22: Б. Затраты ВТБ на внедрение и сравнение с собственной разработкой
A23: Б1 | B23: Полная стоимость ИТ-специалиста банка | C23: млн ₽ в год | D23: 4.5 | E23: 4.5 | F23: 4.5 | G23: допущение | H23: Оклад около 250 тыс. ₽ × 12 × 1,302 взносов × 1,15 накладных; вилки вакансий разработчиков 180–400 тыс. ₽ (S14) | I23: ставка внутреннего ИТ банка
A24: Б2 | B24: Интеграция силами банка (ДБО, источники, ИБ) | C24: человеко-лет | D24: 2 | E24: 1.5 | F24: 1 | G24: допущение | H24: Порты к источникам и OpenAPI готовы; банк подключает ДБО, реестр МЧД, ЕГРЮЛ и СКЗИ | I24: оценка ИТ-архитектора банка после пилота
A25: Б3 | B25: Инфраструктура в контуре банка, разово | C25: млн ₽ | D25: 2 | E25: 1.5 | F25: 1 | G25: допущение | H25: Два узла и резерв; ядро не требует GPU, модель для устава необязательна | I25: требования ИБ и эксплуатации банка
A26: Б4 | B26: Оценка ИБ силами банка, разово | C26: млн ₽ | D26: 1 | E26: 1 | F26: 1 | G26: допущение | H26: Внутренняя проверка документов ИБ, модели угроз и результатов анализа уязвимостей | I26: регламент ИБ банка
A27: Б5 | B27: Сопровождение силами банка | C27: человеко-лет в год | D27: 0.5 | E27: 0.5 | F27: 0.3 | G27: допущение | H27: Администрирование, обновления, разбор обращений; правила сопровождает поставщик | I27: регламент эксплуатации
A28: Б6 | B28: НДС на услуги внедрения (банк не принимает к вычету) | C28: доля | D28: 0.22 | E28: 0.22 | F28: 0.22 | G28: факт | H28: Ставка НДС 22 % с 01.01.2026; лицензия на ПО из реестра российского ПО освобождена (пп. 26 п. 2 ст. 149 НК РФ) — по обзорам (M-24, S12) | I28: налоговая политика банка
A29: Б7 | B29: Собственная разработка банка: создание | C29: человеко-лет | D29: 10 | E29: 10 | F29: 10 | G29: допущение | H29: Ядро правил, адаптеры, журнал, удостоверения, корпус тестов и юридическая разметка правил | I29: оценка ИТ банка
A30: Б8 | B30: Собственная разработка банка: сопровождение правил и кода | C30: человек | D30: 4 | E30: 4 | F30: 4 | G30: допущение | H30: Разработчик, юрист, аналитик, инженер качества | I30: оценка ИТ банка
A31: Б9 | B31: Горизонт сравнения «купить или сделать» | C31: лет | D31: 5 | E31: 5 | F31: 5 | G31: допущение | H31: Срок, на котором банк сравнивает варианты | I31: —
A32: Р. Рынок
A33: Р1 | B33: Действующих банков в России | C33: банков | D33: 301 | E33: 301 | F33: 301 | G33: вторичный | H33: 301 банк на 01.07.2026 без НКО (brobank.ru по данным Банка России, M-22, S10) | I33: таблица Банка России «Количественные характеристики банковского сектора»
A34: Р2 | B34: Уровень 1: системно значимые банки | C34: банков | D34: 12 | E34: 12 | F34: 12 | G34: вторичный | H34: Перечень СЗКО на 2026 год — 12 банков, около 80 % активов сектора (Moscow Times 07.10.2026, vbr.ru, M-21, S09) | I34: перечень на сайте Банка России
A35: Р3 | B35: Уровень 2: крупные и средние банки с корпоративным ДБО | C35: банков | D35: 48 | E35: 48 | F35: 48 | G35: допущение | H35: Банки с 13-го по 60-е место по активам; дальше — банки с малой базой бизнеса | I35: рэнкинг по активам и интервью с банками
A36: Р4 | B36: Доля ВТБ в отношениях «банк — клиент-бизнес» | C36: доля | D36: 0.2 | E36: 0.2 | F36: 0.2 | G36: допущение | H36: ВТБ называет клиентом «каждый третий реально действующий бизнес» (M-28, S15); у бизнеса бывает несколько банков, поэтому доля в отношениях ниже | I36: данные Банка России о счетах юрлиц и ИП
A37: Р5 | B37: Доля уровня 1 в отношениях с бизнесом | C37: доля | D37: 0.8 | E37: 0.8 | F37: 0.8 | G37: допущение | H37: Ориентир — доля СЗКО в активах сектора около 80 % (M-21) | I37: статистика Банка России по счетам
A38: Р6 | B38: Доля уровня 2 в отношениях с бизнесом | C38: доля | D38: 0.15 | E38: 0.15 | F38: 0.15 | G38: допущение | H38: Остаток после уровня 1; на уровень 3 приходится 5 % | I38: статистика Банка России по счетам
A39: Р7 | B39: Цена для банка уровня 3 через партнёра (всё включено) | C39: млн ₽ в год | D39: 0.3 | E39: 0.5 | F39: 0.7 | G39: гипотеза | H39: Небольшим банкам — через поставщиков ДБО; в SAM и SOM не входит | I39: переговоры с поставщиками ДБО
A40: Р8 | B40: Доля ценности задачи, которую забирает поставщик | C40: доля | D40: 0.1 | E40: 0.15 | F40: 0.2 | G40: допущение | H40: Обычная для корпоративного ПО доля 10–20 % измеренного эффекта клиента | I40: переговоры о цене после пилота
A41: Ц. Цена и продажи
A42: Ц1 | B42: Подписка банка уровня 1: постоянная часть | C42: млн ₽ в год | D42: 3 | E42: 6 | F42: 8 | G42: гипотеза | H42: Сопровождение пакета правил юристом, обновления при смене норм и формата МЧД, поддержка; ниже затрат банка на сопровождение своими силами | I42: переговоры о цене после пилота
A43: Ц2 | B43: Подписка: плата за активного клиента-бизнес | C43: ₽ в год | D43: 2 | E43: 5 | F43: 7 | G43: гипотеза | H43: Для ВТБ в базовом сценарии подписка — около 9 % прямого эффекта (лист «Эффект для банка») | I43: измеренный эффект пилота
A44: Ц3 | B44: Подписка банка уровня 2: постоянная часть | C44: млн ₽ в год | D44: 1 | E44: 1.5 | F44: 2 | G44: гипотеза | H44: Те же правила и обновления; меньше интеграций и поддержки | I44: интервью с банками уровня 2
A45: Ц4 | B45: Внедрение в банке уровня 1, разово | C45: млн ₽ | D45: 6 | E45: 8 | F45: 10 | G45: гипотеза | H45: Адаптеры к источникам банка, интеграция с ДБО, документы ИБ, обучение; около 3 инженеров на 3–4 месяца | I45: фактические трудозатраты внедрения в ВТБ
A46: Ц5 | B46: Внедрение в банке уровня 2, разово | C46: млн ₽ | D46: 1.5 | E46: 2 | F46: 2.5 | G46: гипотеза | H46: Типовые адаптеры, меньше интеграций | I46: фактические трудозатраты
A47: Ц6 | B47: Индексация цен | C47: доля в год | D47: 0.04 | E47: 0.05 | F47: 0.06 | G47: допущение | H47: Цель Банка России по инфляции — 4 % | I47: условия договора
A48: Ц7 | B48: Рост подписки банка за счёт новых операций | C48: доля в год | D48: 0 | E48: 0.15 | F48: 0.25 | G48: гипотеза | H48: Пилот — одна операция; дальше открытие счёта, кредиты, гарантии, смена пользователей ДБО | I48: план тиражирования в ВТБ
A49: Ц8 | B49: Год договора с ВТБ (подписка — со следующего года) | C49: год | D49: 2028 | E49: 2027 | F49: 2027 | G49: гипотеза | H49: Теневой пилот — I полугодие 2027 года, затем закупка и внедрение | I49: решение по итогам пилота
A50: К. Команда
A51: К1 | B51: Рост окладов | C51: доля в год | D51: 0.07 | E51: 0.07 | F51: 0.07 | G51: допущение | H51: Ориентир — рост зарплат в ИТ в 2025–2026 годах | I51: —
A52: К2 | B52: Взносы ИТ-компании в пределах базы | C52: доля | D52: 0.15 | E52: 0.15 | F52: 0.15 | G52: вторичный | H52: Льготный тариф аккредитованной ИТ-компании с 2025 года — 15 % (M-24, S12) | I52: НК РФ, ст. 427
A53: К3 | B53: Взносы ИТ-компании сверх базы | C53: доля | D53: 0.076 | E53: 0.076 | F53: 0.076 | G53: вторичный | H53: 7,6 % сверх единой предельной базы (M-24, S12) | I53: НК РФ, ст. 427
A54: К4 | B54: Взнос на травматизм | C54: доля | D54: 0.002 | E54: 0.002 | F54: 0.002 | G54: факт | H54: Минимальный тариф по 125-ФЗ | I54: —
A55: К5 | B55: Единая предельная база взносов в 2026 году | C55: млн ₽ в год | D55: 2.979 | E55: 2.979 | F55: 2.979 | G55: вторичный | H55: 2 979 000 ₽ на 2026 год (M-24, S12) | I55: постановление Правительства о базе на год
A56: К6 | B56: Рост предельной базы | C56: доля в год | D56: 0.08 | E56: 0.08 | F56: 0.08 | G56: допущение | H56: База индексируется вслед за средней зарплатой | I56: —
A57: З. Прочие затраты проекта
A58: З1 | B58: Анализ уязвимостей по ОУД4 в лаборатории — первый | C58: млн ₽ | D58: 3 | E58: 2.5 | F58: 2.5 | G58: допущение | H58: Банк России требует для ПО переводов сертификацию ФСТЭК или анализ уязвимостей по ОУД4 (M-31, S25); публичных цен нет — запросим предложения у 2–3 лицензиатов | I58: коммерческие предложения лабораторий
A59: З2 | B59: Повторная оценка релизов | C59: млн ₽ в год | D59: 1.2 | E59: 1 | F59: 1 | G59: допущение | H59: Оценка изменений в новых версиях | I59: коммерческие предложения лабораторий
A60: З3 | B60: Внешняя юридическая экспертиза правил | C60: млн ₽ в год | D60: 0.4 | E60: 0.6 | F60: 0.8 | G60: допущение | H60: Вторая подпись под правилами при изменении норм | I60: —
A61: З4 | B61: Инфраструктура и инструменты на сотрудника | C61: млн ₽ в год | D61: 0.12 | E61: 0.15 | F61: 0.18 | G61: допущение | H61: Тестовые стенды, CI, лицензии СКЗИ для разработки, данные для тестов (тарифы API данных — от 96 тыс. ₽ в год, M-32) | I61: —
A62: З5 | B62: Продажи и маркетинг: постоянная часть | C62: млн ₽ в год | D62: 0.6 | E62: 1 | F62: 1.5 | G62: допущение | H62: Отраслевые конференции, демо-стенды, материалы | I62: —
A63: З6 | B63: Продажи: на новый договор | C63: млн ₽ | D63: 0.3 | E63: 0.4 | F63: 0.5 | G63: допущение | H63: Командировки, пилот, юридическое сопровождение договора | I63: —
A64: З7 | B64: Административные: постоянная часть | C64: млн ₽ в год | D64: 1 | E64: 1.2 | F64: 1.5 | G64: допущение | H64: Бухгалтерия, юрист компании, офис или коворкинг, страхование | I64: —
A65: З8 | B65: Административные: на сотрудника | C65: млн ₽ в год | D65: 0.08 | E65: 0.1 | F65: 0.12 | G65: допущение | H65: Рабочее место, связь, обучение | I65: —
A66: З9 | B66: Оборудование на нового сотрудника | C66: млн ₽ | D66: 0.25 | E66: 0.25 | F66: 0.25 | G66: допущение | H66: Ноутбук и лицензии; относится на расходы года | I66: —
A67: З10 | B67: Регистрация, аккредитация ИТ, реестр российского ПО (2027) | C67: млн ₽ | D67: 0.3 | E67: 0.3 | F67: 0.3 | G67: допущение | H67: Госпошлины, юридическое сопровождение, подготовка документов | I67: —
A68: З11 | B68: Рост прочих затрат | C68: доля в год | D68: 0.05 | E68: 0.05 | F68: 0.05 | G68: допущение | H68: Инфляция затрат | I68: —
A69: З12 | B69: Резерв на непредвиденное | C69: доля затрат | D69: 0.1 | E69: 0.1 | F69: 0.1 | G69: допущение | H69: Обычный резерв ранней стадии | I69: —
A70: Н. Налоги и деньги
A71: Н1 | B71: Налог на прибыль аккредитованной ИТ-компании | C71: доля | D71: 0.05 | E71: 0.05 | F71: 0.05 | G71: вторичный | H71: 5 % в 2025–2030 годах (M-24, S12); в 2031 году оставлен тот же — допущение | I71: НК РФ, ст. 284
A72: Н2 | B72: Перенос убытка: не больше доли прибыли года | C72: доля | D72: 0.5 | E72: 0.5 | F72: 0.5 | G72: факт | H72: Ограничение переноса убытков 50 % налоговой базы (НК РФ, ст. 283) | I72: —
A73: Н3 | B73: Срок оплаты банками (дебиторская задолженность) | C73: дней выручки | D73: 120 | E73: 90 | F73: 60 | G73: допущение | H73: Закупка и приёмка в банке | I73: условия договора
A74: Н4 | B74: Ставка дисконтирования | C74: доля | D74: 0.3 | E74: 0.3 | F74: 0.3 | G74: допущение | H74: Ключевая ставка 14 % (23.10.2026, M-23) плюс премия за риск ранней стадии | I74: —
A75: Н5 | B75: Рост денежного потока после 2031 года | C75: доля в год | D75: 0.04 | E75: 0.04 | F75: 0.04 | G75: допущение | H75: На уровне цели по инфляции | I75: —
A76: Н6 | B76: Запас к потребности в финансировании | C76: доля | D76: 0.2 | E76: 0.2 | F76: 0.2 | G76: допущение | H76: Подушка на сдвиг сроков закупок | I76: —

Sheet План
A1: План продаж и команды
A2: Новые договоры и численность в ставках на конец года; 2026 — исходные значения
A4: № | B4: Показатель | C4: Единица | D4: Оклад 2027 | E4: 2026 | F4: 2027 | G4: 2028 | H4: 2029 | I4: 2030 | J4: 2031 | K4: Итого
A5: Консервативный
A6: КД1 | B6: Новые банки уровня 1 (кроме ВТБ) | C6: банков | E6: 0 | F6: 0 | G6: 0 | H6: 0 | I6: 0 | J6: 0 | K6: =SUM(F6:J6) -> 0
A7: КД2 | B7: Новые банки уровня 2 | C7: банков | E7: 0 | F7: 0 | G7: 0 | H7: 1 | I7: 1 | J7: 1 | K7: =SUM(F7:J7) -> 3
A8: КЧ1 | B8: Основатели: продукт и продажи, архитектура правил | C8: ставок | D8: 200 | E8: 2 | F8: 2 | G8: 2 | H8: 2 | I8: 2 | J8: 2
A9: КЧ2 | B9: Разработчики | C9: ставок | D9: 280 | E9: 0 | F9: 0 | G9: 1 | H9: 1 | I9: 1 | J9: 1
A10: КЧ3 | B10: Юрист-аналитик правил | C10: ставок | D10: 230 | E10: 0 | F10: 0.5 | G10: 0.5 | H10: 0.5 | I10: 0.5 | J10: 0.5
A11: КЧ4 | B11: Инженеры внедрения и поддержки | C11: ставок | D11: 220 | E11: 0 | F11: 0 | G11: 0 | H11: 0.5 | I11: 0.5 | J11: 0.5
A12: КЧ5 | B12: Инженер качества и ИБ | C12: ставок | D12: 250 | E12: 0 | F12: 0 | G12: 0 | H12: 0 | I12: 0 | J12: 0
A13: КЧ6 | B13: Менеджер по работе с банками | C13: ставок | D13: 220 | E13: 0 | F13: 0 | G13: 0 | H13: 0 | I13: 0 | J13: 0
A15: Базовый
A16: БД1 | B16: Новые банки уровня 1 (кроме ВТБ) | C16: банков | E16: 0 | F16: 0 | G16: 0 | H16: 1 | I16: 0 | J16: 1 | K16: =SUM(F16:J16) -> 2
A17: БД2 | B17: Новые банки уровня 2 | C17: банков | E17: 0 | F17: 0 | G17: 1 | H17: 2 | I17: 2 | J17: 3 | K17: =SUM(F17:J17) -> 8
A18: БЧ1 | B18: Основатели: продукт и продажи, архитектура правил | C18: ставок | D18: 200 | E18: 2 | F18: 2 | G18: 2 | H18: 2 | I18: 2 | J18: 2
A19: БЧ2 | B19: Разработчики | C19: ставок | D19: 280 | E19: 0 | F19: 1 | G19: 1 | H19: 1 | I19: 2 | J19: 2
A20: БЧ3 | B20: Юрист-аналитик правил | C20: ставок | D20: 230 | E20: 0 | F20: 1 | G20: 1 | H20: 1 | I20: 1 | J20: 1
A21: БЧ4 | B21: Инженеры внедрения и поддержки | C21: ставок | D21: 220 | E21: 0 | F21: 0 | G21: 1 | H21: 1 | I21: 1 | J21: 1
A22: БЧ5 | B22: Инженер качества и ИБ | C22: ставок | D22: 250 | E22: 0 | F22: 0 | G22: 0 | H22: 1 | I22: 1 | J22: 1
A23: БЧ6 | B23: Менеджер по работе с банками | C23: ставок | D23: 220 | E23: 0 | F23: 0 | G23: 0 | H23: 0 | I23: 0 | J23: 1
A25: Оптимистичный
A26: ОД1 | B26: Новые банки уровня 1 (кроме ВТБ) | C26: банков | E26: 0 | F26: 0 | G26: 0 | H26: 1 | I26: 1 | J26: 1 | K26: =SUM(F26:J26) -> 3
A27: ОД2 | B27: Новые банки уровня 2 | C27: банков | E27: 0 | F27: 0 | G27: 2 | H27: 3 | I27: 4 | J27: 5 | K27: =SUM(F27:J27) -> 14
A28: ОЧ1 | B28: Основатели: продукт и продажи, архитектура правил | C28: ставок | D28: 200 | E28: 2 | F28: 2 | G28: 2 | H28: 2 | I28: 2 | J28: 2
A29: ОЧ2 | B29: Разработчики | C29: ставок | D29: 280 | E29: 0 | F29: 1 | G29: 2 | H29: 3 | I29: 3 | J29: 4
A30: ОЧ3 | B30: Юрист-аналитик правил | C30: ставок | D30: 230 | E30: 0 | F30: 1 | G30: 1 | H30: 1 | I30: 2 | J30: 2
A31: ОЧ4 | B31: Инженеры внедрения и поддержки | C31: ставок | D31: 220 | E31: 0 | F31: 0 | G31: 1 | H31: 2 | I31: 3 | J31: 3
A32: ОЧ5 | B32: Инженер качества и ИБ | C32: ставок | D32: 250 | E32: 0 | F32: 0 | G32: 1 | H32: 1 | I32: 1 | J32: 2
A33: ОЧ6 | B33: Менеджер по работе с банками | C33: ставок | D33: 220 | E33: 0 | F33: 0 | G33: 0 | H33: 1 | I33: 1 | J33: 2
A35: Оклады 2027 года, тыс. ₽ в месяц до вычета налогов. Ориентиры: вакансии Python-разработчиков 180–300 тыс. ₽ (middle) и 300–400 тыс. ₽ (senior) на career.habr.com (S14); основатели — ниже рынка до выхода на прибыль.

Sheet Эффект для банка
A1: Эффект и окупаемость для ВТБ
A2: Ставки и ущерб повторяют расчёт презентации (C-15, C-16); деньги — млн ₽ в год без НДС, цены 2027 года
A4: № | B4: Показатель | C4: Единица | D4: Консервативный | E4: Базовый | F4: Оптимистичный | G4: Как считается
A5: Параметры (ссылки на «Допущения»)
A6: 1 | B6: Клиенты ВТБ — предприятия и предприниматели | C6: млн | D6: =Допущения!$D$7 -> 1.8 | E6: =Допущения!$E$7 -> 1.8 | F6: =Допущения!$F$7 -> 1.8 | G6: Допущения, строка П1
A7: 2 | B7: Доля клиентов со сменой или добавлением подписанта в год | C7: доля | D7: =Допущения!$D$8 -> 0.1 | E7: =Допущения!$E$8 -> 0.15 | F7: =Допущения!$F$8 -> 0.25 | G7: Допущения, строка П2
A8: 3 | B8: Минут на кейс вручную, вместе с разбором | C8: минут | D8: =Допущения!$D$9 -> 20 | E8: =Допущения!$E$9 -> 30 | F8: =Допущения!$F$9 -> 40 | G8: Допущения, строка П3
A9: 4 | B9: Рабочих часов на ставку в год | C9: часов | D9: =Допущения!$D$10 -> 1800 | E9: =Допущения!$E$10 -> 1800 | F9: =Допущения!$F$10 -> 1800 | G9: Допущения, строка П4
A10: 5 | B10: Операций без согласия у юрлиц за квартал | C10: операций | D10: =Допущения!$D$11 -> 818 | E10: =Допущения!$E$11 -> 818 | F10: =Допущения!$F$11 -> 818 | G10: Допущения, строка П5
A11: 6 | B11: Объём таких операций за квартал | C11: млн ₽ | D11: =Допущения!$D$12 -> 573 | E11: =Допущения!$E$12 -> 573 | F11: =Допущения!$F$12 -> 573 | G11: Допущения, строка П6
A12: 7 | B12: Доля ВТБ в таких инцидентах | C12: доля | D12: =Допущения!$D$13 -> 0.15 | E12: =Допущения!$E$13 -> 0.2 | F12: =Допущения!$F$13 -> 0.25 | G12: Допущения, строка П7
A13: 8 | B13: Доля инцидентов, связанных с полномочиями | C13: доля | D13: =Допущения!$D$14 -> 0.1 | E13: =Допущения!$E$14 -> 0.25 | F13: =Допущения!$F$14 -> 0.4 | G13: Допущения, строка П8
A14: 9 | B14: Оклад сотрудника, проверяющего документы | C14: тыс. ₽ в месяц | D14: =Допущения!$D$16 -> 85 | E14: =Допущения!$E$16 -> 100 | F14: =Допущения!$F$16 -> 120 | G14: Допущения, строка Э1
A15: 10 | B15: Страховые взносы банка | C15: доля | D15: =Допущения!$D$17 -> 0.302 | E15: =Допущения!$E$17 -> 0.302 | F15: =Допущения!$F$17 -> 0.302 | G15: Допущения, строка Э2
A16: 11 | B16: Накладные на рабочее место (помещение, ИТ, управление) | C16: доля к ФОТ с взносами | D16: =Допущения!$D$18 -> 0.2 | E16: =Допущения!$E$18 -> 0.25 | F16: =Допущения!$F$18 -> 0.3 | G16: Допущения, строка Э3
A17: 12 | B17: Доля высвобожденного времени, которая становится экономией | C17: доля | D17: =Допущения!$D$19 -> 0.3 | E17: =Допущения!$E$19 -> 0.5 | F17: =Допущения!$F$19 -> 0.7 | G17: Допущения, строка Э4
A18: 13 | B18: Доля предотвращённого ущерба клиентов, которую несёт банк | C18: доля | D18: =Допущения!$D$20 -> 0.1 | E18: =Допущения!$E$20 -> 0.159 | F18: =Допущения!$F$20 -> 0.25 | G18: Допущения, строка Э5
A19: 14 | B19: Эффект в первый год работы (раскачка) | C19: доля | D19: =Допущения!$D$21 -> 0.5 | E19: =Допущения!$E$21 -> 0.5 | F19: =Допущения!$F$21 -> 0.5 | G19: Допущения, строка Э6
A20: 15 | B20: Подписка банка уровня 1: постоянная часть | C20: млн ₽ в год | D20: =Допущения!$D$42 -> 3 | E20: =Допущения!$E$42 -> 6 | F20: =Допущения!$F$42 -> 8 | G20: Допущения, строка Ц1
A21: 16 | B21: Подписка: плата за активного клиента-бизнес | C21: ₽ в год | D21: =Допущения!$D$43 -> 2 | E21: =Допущения!$E$43 -> 5 | F21: =Допущения!$F$43 -> 7 | G21: Допущения, строка Ц2
A22: 17 | B22: Внедрение в банке уровня 1, разово | C22: млн ₽ | D22: =Допущения!$D$45 -> 6 | E22: =Допущения!$E$45 -> 8 | F22: =Допущения!$F$45 -> 10 | G22: Допущения, строка Ц4
A23: 18 | B23: НДС на услуги внедрения (банк не принимает к вычету) | C23: доля | D23: =Допущения!$D$28 -> 0.22 | E23: =Допущения!$E$28 -> 0.22 | F23: =Допущения!$F$28 -> 0.22 | G23: Допущения, строка Б6
A24: 19 | B24: Полная стоимость ИТ-специалиста банка | C24: млн ₽ в год | D24: =Допущения!$D$23 -> 4.5 | E24: =Допущения!$E$23 -> 4.5 | F24: =Допущения!$F$23 -> 4.5 | G24: Допущения, строка Б1
A25: 20 | B25: Интеграция силами банка (ДБО, источники, ИБ) | C25: человеко-лет | D25: =Допущения!$D$24 -> 2 | E25: =Допущения!$E$24 -> 1.5 | F25: =Допущения!$F$24 -> 1 | G25: Допущения, строка Б2
A26: 21 | B26: Инфраструктура в контуре банка, разово | C26: млн ₽ | D26: =Допущения!$D$25 -> 2 | E26: =Допущения!$E$25 -> 1.5 | F26: =Допущения!$F$25 -> 1 | G26: Допущения, строка Б3
A27: 22 | B27: Оценка ИБ силами банка, разово | C27: млн ₽ | D27: =Допущения!$D$26 -> 1 | E27: =Допущения!$E$26 -> 1 | F27: =Допущения!$F$26 -> 1 | G27: Допущения, строка Б4
A28: 23 | B28: Сопровождение силами банка | C28: человеко-лет в год | D28: =Допущения!$D$27 -> 0.5 | E28: =Допущения!$E$27 -> 0.5 | F28: =Допущения!$F$27 -> 0.3 | G28: Допущения, строка Б5
A29: 24 | B29: Собственная разработка банка: создание | C29: человеко-лет | D29: =Допущения!$D$29 -> 10 | E29: =Допущения!$E$29 -> 10 | F29: =Допущения!$F$29 -> 10 | G29: Допущения, строка Б7
A30: 25 | B30: Собственная разработка банка: сопровождение правил и кода | C30: человек | D30: =Допущения!$D$30 -> 4 | E30: =Допущения!$E$30 -> 4 | F30: =Допущения!$F$30 -> 4 | G30: Допущения, строка Б8
A31: 26 | B31: Горизонт сравнения «купить или сделать» | C31: лет | D31: =Допущения!$D$31 -> 5 | E31: =Допущения!$E$31 -> 5 | F31: =Допущения!$F$31 -> 5 | G31: Допущения, строка Б9
A32: 1. Высвобождение времени
A33: 27 | B33: Кейсов смены или добавления подписанта в год | C33: тыс. | D33: =D6*1000*D7 -> 180 | E33: =E6*1000*E7 -> 270 | F33: =F6*1000*F7 -> 450 | G33: клиенты × доля с событием
A34: 28 | B34: Часов ручной проверки в год | C34: тыс. часов | D34: =D33*D8/60 -> 60 | E34: =E33*E8/60 -> 135 | F34: =F33*F8/60 -> 300 | G34: кейсы × минуты / 60
A35: 29 | B35: Высвобождается ставок | C35: ставок | D35: =D34*1000/D9 -> 33.333333 | E35: =E34*1000/E9 -> 75 | F35: =F34*1000/F9 -> 166.66667 | G35: часы / часы на ставку
A36: 30 | B36: То же, округлено (как в презентации, C-15) | C36: ставок | D36: =ROUND(D35,0) -> 33 | E36: =ROUND(E35,0) -> 75 | F36: =ROUND(F35,0) -> 167 | G36: сверяется на листе «Проверки»
A37: 31 | B37: Полная стоимость ставки | C37: млн ₽ в год | D37: =D14*12*(1+D15)*(1+D16)/1000 -> 1.593648 | E37: =E14*12*(1+E15)*(1+E16)/1000 -> 1.953 | F37: =F14*12*(1+F15)*(1+F16)/1000 -> 2.437344 | G37: оклад × 12 × (1 + взносы) × (1 + накладные)
A38: 32 | B38: Стоимость высвобожденного времени (ёмкость) | C38: млн ₽ в год | D38: =D35*D37 -> 53.1216 | E38: =E35*E37 -> 146.475 | F38: =F35*F37 -> 406.224 | G38: ставки × стоимость ставки
A39: 33 | B39: Денежная экономия на времени | C39: млн ₽ в год | D39: =D38*D17 -> 15.93648 | E39: =E38*E17 -> 73.2375 | F39: =F38*F17 -> 284.3568 | G39: ёмкость × доля, которая становится экономией
A40: 2. Предотвращённый ущерб
A41: 34 | B41: Средняя операция без согласия у юрлица | C41: млн ₽ | D41: =D11/D10 -> 0.700489 | E41: =E11/E10 -> 0.700489 | F41: =F11/F10 -> 0.700489 | G41: объём за квартал / число операций
A42: 35 | B42: Таких операций в год по всем банкам | C42: операций | D42: =D10*4 -> 3272 | E42: =E10*4 -> 3272 | F42: =F10*4 -> 3272 | G42: квартал × 4
A43: 36 | B43: Предотвращённый ущерб клиентов ВТБ | C43: млн ₽ в год | D43: =D42*D12*D13*D41 -> 34.38 | E43: =E42*E12*E13*E41 -> 114.6 | F43: =F42*F12*F13*F41 -> 229.2 | G43: операции × доля ВТБ × доля с полномочиями × средняя операция
A44: 37 | B44: То же, округлено (как в презентации, C-16) | C44: млн ₽ в год | D44: =ROUND(D43,0) -> 34 | E44: =ROUND(E43,0) -> 115 | F44: =ROUND(F43,0) -> 229 | G44: сверяется на листе «Проверки»
A45: 38 | B45: Из него несёт банк | C45: млн ₽ в год | D45: =D43*D18 -> 3.438 | E45: =E43*E18 -> 18.2214 | F45: =F43*F18 -> 57.3 | G45: ущерб × доля банка
A46: 3. Эффект в год
A47: 39 | B47: Прямой эффект банка: ёмкость | C47: млн ₽ в год | D47: =D38+D45 -> 56.5596 | E47: =E38+E45 -> 164.6964 | F47: =F38+F45 -> 463.524 | G47: время целиком + ущерб, который несёт банк
A48: 40 | B48: Прямой эффект банка: деньги | C48: млн ₽ в год | D48: =D39+D45 -> 19.37448 | E48: =E39+E45 -> 91.4589 | F48: =F39+F45 -> 341.6568 | G48: денежная экономия + ущерб банка
A49: 41 | B49: Эффект с ущербом клиентов | C49: млн ₽ в год | D49: =D38+D43 -> 87.5016 | E49: =E38+E43 -> 261.075 | F49: =F38+F43 -> 635.424 | G49: время + весь предотвращённый ущерб
A50: 4. Затраты банка
A51: 42 | B51: Подписка «Мандата» для ВТБ | C51: млн ₽ в год | D51: =D20+D6*D21 -> 6.6 | E51: =E20+E6*E21 -> 15 | F51: =F20+F6*F21 -> 20.6 | G51: постоянная часть + клиенты × плата за клиента; лицензия из реестра ПО — без НДС
A52: 43 | B52: Внедрение с НДС | C52: млн ₽ | D52: =D22*(1+D23) -> 7.32 | E52: =E22*(1+E23) -> 9.76 | F52: =F22*(1+F23) -> 12.2 | G52: услуга облагается НДС, банк его не вычитает
A53: 44 | B53: Интеграция силами банка | C53: млн ₽ | D53: =D25*D24 -> 9 | E53: =E25*E24 -> 6.75 | F53: =F25*F24 -> 4.5 | G53: человеко-годы × стоимость
A54: 45 | B54: Разовые затраты банка | C54: млн ₽ | D54: =D52+D53+D26+D27 -> 19.32 | E54: =E52+E53+E26+E27 -> 19.01 | F54: =F52+F53+F26+F27 -> 18.7 | G54: внедрение + интеграция + инфраструктура + оценка ИБ
A55: 46 | B55: Ежегодные затраты банка | C55: млн ₽ в год | D55: =D51+D28*D24 -> 8.85 | E55: =E51+E28*E24 -> 17.25 | F55: =F51+F28*F24 -> 21.95 | G55: подписка + сопровождение силами банка
A56: 5. Окупаемость для банка: деньги
A57: 47 | B57: Чистый эффект первого года | C57: млн ₽ | D57: =D48*D19-D55 -> 0.83724 | E57: =E48*E19-E55 -> 28.47945 | F57: =F48*F19-F55 -> 148.8784 | G57: эффект × раскачка − ежегодные
A58: 48 | B58: Чистый эффект со второго года | C58: млн ₽ в год | D58: =D48-D55 -> 10.52448 | E58: =E48-E55 -> 74.2089 | F58: =F48-F55 -> 319.7068 | G58: эффект − ежегодные
A59: 49 | B59: Отдача за 3 года на вложенный рубль | C59: раз | D59: =(D57+2*D58-D54)/(D54+3*D55) -> 0.055945062 | E59: =(E57+2*E58-E54)/(E54+3*E55) -> 2.2313065 | F59: =(F57+2*F58-F54)/(F54+3*F55) -> 9.1022117 | G59: (чистый эффект 3 лет − разовые) / (разовые + ежегодные × 3)
A60: 50 | B60: Срок окупаемости разовых затрат | C60: месяцев | D60: =IF(D57>=D54,12*D54/D57,IF(D58<=0,"не окупается",12+12*(D54-D57)/D58)) -> 33.074022 | E60: =IF(E57>=E54,12*E54/E57,IF(E58<=0,"не окупается",12+12*(E54-E57)/E58)) -> 8.0099861 | F60: =IF(F57>=F54,12*F54/F57,IF(F58<=0,"не окупается",12+12*(F54-F57)/F58)) -> 1.5072704 | G60: месяцы до возврата разовых затрат с учётом раскачки
A61: 5. Окупаемость для банка: ёмкость
A62: 51 | B62: Чистый эффект первого года | C62: млн ₽ | D62: =D47*D19-D55 -> 19.4298 | E62: =E47*E19-E55 -> 65.0982 | F62: =F47*F19-F55 -> 209.812 | G62: эффект × раскачка − ежегодные
A63: 52 | B63: Чистый эффект со второго года | C63: млн ₽ в год | D63: =D47-D55 -> 47.7096 | E63: =E47-E55 -> 147.4464 | F63: =F47-F55 -> 441.574 | G63: эффект − ежегодные
A64: 53 | B64: Отдача за 3 года на вложенный рубль | C64: раз | D64: =(D62+2*D63-D54)/(D54+3*D55) -> 2.082603 | E64: =(E62+2*E63-E54)/(E54+3*E55) -> 4.8188383 | F64: =(F62+2*F63-F54)/(F54+3*F55) -> 12.705618 | G64: (чистый эффект 3 лет − разовые) / (разовые + ежегодные × 3)
A65: 54 | B65: Срок окупаемости разовых затрат | C65: месяцев | D65: =IF(D62>=D54,12*D54/D62,IF(D63<=0,"не окупается",12+12*(D54-D62)/D63)) -> 11.932187 | E65: =IF(E62>=E54,12*E54/E62,IF(E63<=0,"не окупается",12+12*(E54-E62)/E63)) -> 3.5042444 | F65: =IF(F62>=F54,12*F54/F62,IF(F63<=0,"не окупается",12+12*(F54-F62)/F63)) -> 1.0695289 | G65: месяцы до возврата разовых затрат с учётом раскачки
A66: 6. Цена и «купить или сделать»
A67: 55 | B67: Подписка в доле прямого эффекта (ёмкость) | C67: доля | D67: =D51/D47 -> 0.11669107 | E67: =E51/E47 -> 0.091076672 | F67: =F51/F47 -> 0.044442143 | G67: условие цены: не больше 15 %
A68: 56 | B68: Подписка в доле прямого эффекта (деньги) | C68: доля | D68: =D51/D48 -> 0.3406543 | E68: =E51/E48 -> 0.1640081 | F68: =F51/F48 -> 0.060294424 | G68: справочно
A69: 57 | B69: Купить: затраты в год за горизонт | C69: млн ₽ в год | D69: =D55+D54/D31 -> 12.714 | E69: =E55+E54/E31 -> 21.052 | F69: =F55+F54/F31 -> 25.69 | G69: ежегодные + разовые / горизонт
A70: 58 | B70: Сделать самим: затраты в год за горизонт | C70: млн ₽ в год | D70: =D29*D24/D31+D30*D24+D26/D31 -> 27.4 | E70: =E29*E24/E31+E30*E24+E26/E31 -> 27.3 | F70: =F29*F24/F31+F30*F24+F26/F31 -> 27.2 | G70: создание / горизонт + команда сопровождения + инфраструктура / горизонт
A71: 59 | B71: Купить в доле от «сделать самим» | C71: доля | D71: =D69/D70 -> 0.4640146 | E71: =E69/E70 -> 0.77113553 | F71: =F69/F70 -> 0.94448529 | G71: условие цены: меньше 100 %

Sheet Рынок
A1: Объём рынка: банки России
A2: Снизу вверх — банки по уровням × цена подписки; сверху вниз — ценность задачи × доля поставщика. Млн ₽ в год без НДС, цены 2027 года
A4: № | B4: Показатель | C4: Единица | D4: Консервативный | E4: Базовый | F4: Оптимистичный | G4: Как считается
A5: Параметры (ссылки на «Допущения» и «Эффект для банка»)
A6: 1 | B6: Действующих банков в России | C6: банков | D6: =Допущения!$D$33 -> 301 | E6: =Допущения!$E$33 -> 301 | F6: =Допущения!$F$33 -> 301 | G6: Допущения, строка Р1
A7: 2 | B7: Уровень 1: системно значимые банки | C7: банков | D7: =Допущения!$D$34 -> 12 | E7: =Допущения!$E$34 -> 12 | F7: =Допущения!$F$34 -> 12 | G7: Допущения, строка Р2
A8: 3 | B8: Уровень 2: крупные и средние банки с корпоративным ДБО | C8: банков | D8: =Допущения!$D$35 -> 48 | E8: =Допущения!$E$35 -> 48 | F8: =Допущения!$F$35 -> 48 | G8: Допущения, строка Р3
A9: 4 | B9: Доля ВТБ в отношениях «банк — клиент-бизнес» | C9: доля | D9: =Допущения!$D$36 -> 0.2 | E9: =Допущения!$E$36 -> 0.2 | F9: =Допущения!$F$36 -> 0.2 | G9: Допущения, строка Р4
A10: 5 | B10: Доля уровня 1 в отношениях с бизнесом | C10: доля | D10: =Допущения!$D$37 -> 0.8 | E10: =Допущения!$E$37 -> 0.8 | F10: =Допущения!$F$37 -> 0.8 | G10: Допущения, строка Р5
A11: 6 | B11: Доля уровня 2 в отношениях с бизнесом | C11: доля | D11: =Допущения!$D$38 -> 0.15 | E11: =Допущения!$E$38 -> 0.15 | F11: =Допущения!$F$38 -> 0.15 | G11: Допущения, строка Р6
A12: 7 | B12: Цена для банка уровня 3 через партнёра (всё включено) | C12: млн ₽ в год | D12: =Допущения!$D$39 -> 0.3 | E12: =Допущения!$E$39 -> 0.5 | F12: =Допущения!$F$39 -> 0.7 | G12: Допущения, строка Р7
A13: 8 | B13: Доля ценности задачи, которую забирает поставщик | C13: доля | D13: =Допущения!$D$40 -> 0.1 | E13: =Допущения!$E$40 -> 0.15 | F13: =Допущения!$F$40 -> 0.2 | G13: Допущения, строка Р8
A14: 9 | B14: Клиенты ВТБ — предприятия и предприниматели | C14: млн | D14: =Допущения!$D$7 -> 1.8 | E14: =Допущения!$E$7 -> 1.8 | F14: =Допущения!$F$7 -> 1.8 | G14: Допущения, строка П1
A15: 10 | B15: Подписка банка уровня 1: постоянная часть | C15: млн ₽ в год | D15: =Допущения!$D$42 -> 3 | E15: =Допущения!$E$42 -> 6 | F15: =Допущения!$F$42 -> 8 | G15: Допущения, строка Ц1
A16: 11 | B16: Подписка банка уровня 2: постоянная часть | C16: млн ₽ в год | D16: =Допущения!$D$44 -> 1 | E16: =Допущения!$E$44 -> 1.5 | F16: =Допущения!$F$44 -> 2 | G16: Допущения, строка Ц3
A17: 12 | B17: Подписка: плата за активного клиента-бизнес | C17: ₽ в год | D17: =Допущения!$D$43 -> 2 | E17: =Допущения!$E$43 -> 5 | F17: =Допущения!$F$43 -> 7 | G17: Допущения, строка Ц2
A18: 13 | B18: Рост подписки банка за счёт новых операций | C18: доля в год | D18: =Допущения!$D$48 -> 0 | E18: =Допущения!$E$48 -> 0.15 | F18: =Допущения!$F$48 -> 0.25 | G18: Допущения, строка Ц7
A19: 14 | B19: Операций без согласия у юрлиц за квартал | C19: операций | D19: =Допущения!$D$11 -> 818 | E19: =Допущения!$E$11 -> 818 | F19: =Допущения!$F$11 -> 818 | G19: Допущения, строка П5
A20: 15 | B20: Доля инцидентов, связанных с полномочиями | C20: доля | D20: =Допущения!$D$14 -> 0.1 | E20: =Допущения!$E$14 -> 0.25 | F20: =Допущения!$F$14 -> 0.4 | G20: Допущения, строка П8
A21: 16 | B21: Доля предотвращённого ущерба клиентов, которую несёт банк | C21: доля | D21: =Допущения!$D$20 -> 0.1 | E21: =Допущения!$E$20 -> 0.159 | F21: =Допущения!$F$20 -> 0.25 | G21: Допущения, строка Э5
A22: 17 | B22: Стоимость высвобожденного времени ВТБ | C22: млн ₽ в год | D22: ='Эффект для банка'!$D$38 -> 53.1216 | E22: ='Эффект для банка'!$E$38 -> 146.475 | F22: ='Эффект для банка'!$F$38 -> 406.224 | G22: лист «Эффект для банка»
A23: 18 | B23: Средняя операция без согласия | C23: млн ₽ | D23: ='Эффект для банка'!$D$41 -> 0.700489 | E23: ='Эффект для банка'!$E$41 -> 0.700489 | F23: ='Эффект для банка'!$F$41 -> 0.700489 | G23: лист «Эффект для банка»
A24: 1. Банки и клиенты-бизнесы
A25: 19 | B25: Уровень 3: остальные банки | C25: банков | D25: =D6-D7-D8 -> 241 | E25: =E6-E7-E8 -> 241 | F25: =F6-F7-F8 -> 241 | G25: всего − уровень 1 − уровень 2
A26: 20 | B26: Отношений «банк — клиент-бизнес» в России | C26: млн | D26: =D14/D9 -> 9 | E26: =E14/E9 -> 9 | F26: =F14/F9 -> 9 | G26: клиенты ВТБ / доля ВТБ
A27: 21 | B27: Из них в банках уровня 1 | C27: млн | D27: =D26*D10 -> 7.2 | E27: =E26*E10 -> 7.2 | F27: =F26*F10 -> 7.2 | G27: всего × доля уровня 1
A28: 22 | B28: В банках уровня 2 | C28: млн | D28: =D26*D11 -> 1.35 | E28: =E26*E11 -> 1.35 | F28: =F26*F11 -> 1.35 | G28: всего × доля уровня 2
A29: 23 | B29: В банках уровня 3 | C29: млн | D29: =D26-D27-D28 -> 0.45 | E29: =E26-E27-E28 -> 0.45 | F29: =F26-F27-F28 -> 0.45 | G29: остаток
A30: 24 | B30: Клиентов-бизнесов у банка уровня 1, кроме ВТБ, в среднем | C30: млн | D30: =(D27-D14)/(D7-1) -> 0.49090909 | E30: =(E27-E14)/(E7-1) -> 0.49090909 | F30: =(F27-F14)/(F7-1) -> 0.49090909 | G30: (уровень 1 − ВТБ) / (банков уровня 1 − 1); база для подписки других банков
A31: 25 | B31: Клиентов-бизнесов у банка уровня 2 в среднем | C31: млн | D31: =D28/D8 -> 0.028125 | E31: =E28/E8 -> 0.028125 | F31: =F28/F8 -> 0.028125 | G31: уровень 2 / банков уровня 2
A32: 2. Снизу вверх: все банки по прайсу
A33: 26 | B33: Уровень 1 | C33: млн ₽ в год | D33: =D7*D15+D27*D17 -> 50.4 | E33: =E7*E15+E27*E17 -> 108 | F33: =F7*F15+F27*F17 -> 146.4 | G33: банки × постоянная часть + клиенты × плата за клиента
A34: 27 | B34: Уровень 2 | C34: млн ₽ в год | D34: =D8*D16+D28*D17 -> 50.7 | E34: =E8*E16+E28*E17 -> 78.75 | F34: =F8*F16+F28*F17 -> 105.45 | G34: то же
A35: 28 | B35: Уровень 3 (через партнёров) | C35: млн ₽ в год | D35: =D25*D12 -> 72.3 | E35: =E25*E12 -> 120.5 | F35: =F25*F12 -> 168.7 | G35: банки × цена через партнёра
A36: 29 | B36: TAM: все банки России | C36: млн ₽ в год | D36: =D33+D34+D35 -> 173.4 | E36: =E33+E34+E35 -> 307.25 | F36: =F33+F34+F35 -> 420.55 | G36: сумма уровней
A37: 30 | B37: SAM: банки уровней 1 и 2 (установка в контуре) | C37: млн ₽ в год | D37: =D33+D34 -> 101.1 | E37: =E33+E34 -> 186.75 | F37: =F33+F34 -> 251.85 | G37: уровни, которые обслуживаем сами
A38: 31 | B38: Подписка при полном охвате операций, к одной операции | C38: раз | D38: =(1+D18)^4 -> 1 | E38: =(1+E18)^4 -> 1.7490063 | F38: =(1+F18)^4 -> 2.4414062 | G38: банк добавляет операции четыре года: (1 + рост подписки) ^ 4
A39: 32 | B39: TAM при полном охвате операций | C39: млн ₽ в год | D39: =D36*D38 -> 173.4 | E39: =E36*E38 -> 537.38217 | F39: =F36*F38 -> 1026.7334 | G39: TAM × множитель
A40: 33 | B40: SAM при полном охвате операций | C40: млн ₽ в год | D40: =D37*D38 -> 101.1 | E40: =E37*E38 -> 326.62692 | F40: =F37*F38 -> 614.86816 | G40: SAM × множитель
A41: 3. SOM: годовая подписка на конец 2031 года по плану продаж
A42: 34 | B42: Подписка на конец 2031 года (ARR), номинал | C42: млн ₽ в год | D42: =Консервативный!$J$75 -> 11.428056 | E42: =Базовый!$J$75 -> 74.632967 | F42: =Оптимистичный!$J$75 -> 170.10899 | G42: лист сценария, строка «Годовая подписка на конец года»
A43: 35 | B43: Индекс цен 2031 к 2027 | C43: раз | D43: =Консервативный!$J$57 -> 1.1698586 | E43: =Базовый!$J$57 -> 1.2155063 | F43: =Оптимистичный!$J$57 -> 1.262477 | G43: лист сценария
A44: 36 | B44: SOM в ценах 2027 года | C44: млн ₽ в год | D44: =D42/D43 -> 9.76875 | E44: =E42/E43 -> 61.400727 | F44: =F42/F43 -> 134.74225 | G44: номинал / индекс
A45: 37 | B45: SOM в доле SAM при полном охвате | C45: доля | D45: =D44/D40 -> 0.096624629 | E45: =E44/E40 -> 0.18798428 | F45: =F44/F40 -> 0.21914007 | G45: SOM включает рост подписки за счёт новых операций, поэтому сравнивается с SAM при полном охвате
A46: 4. Сверху вниз: ценность задачи для всех банков
A47: 38 | B47: Стоимость ручной проверки во всех банках | C47: млн ₽ в год | D47: =D22/D9 -> 265.608 | E47: =E22/E9 -> 732.375 | F47: =F22/F9 -> 2031.12 | G47: ёмкость ВТБ / доля ВТБ в отношениях
A48: 39 | B48: Ущерб клиентов из-за полномочий во всех банках | C48: млн ₽ в год | D48: =D19*4*D20*D23 -> 229.2 | E48: =E19*4*E20*E23 -> 573 | F48: =F19*4*F20*F23 -> 916.8 | G48: операции в год × доля с полномочиями × средняя операция
A49: 40 | B49: Ценность для банков: время + ущерб, который несут банки | C49: млн ₽ в год | D49: =D47+D48*D21 -> 288.528 | E49: =E47+E48*E21 -> 823.482 | F49: =F47+F48*F21 -> 2260.32
A50: 41 | B50: Ценность с ущербом клиентов | C50: млн ₽ в год | D50: =D47+D48 -> 494.808 | E50: =E47+E48 -> 1305.375 | F50: =F47+F48 -> 2947.92
A51: 42 | B51: Выручка поставщика сверху вниз | C51: млн ₽ в год | D51: =D49*D13 -> 28.8528 | E51: =E49*E13 -> 123.5223 | F51: =F49*F13 -> 452.064 | G51: ценность для банков × доля поставщика
A52: 43 | B52: TAM по прайсу в доле ценности для банков | C52: доля | D52: =D36/D49 -> 0.60098153 | E52: =E36/E49 -> 0.37311077 | F52: =F36/F49 -> 0.18605773 | G52: выше доли поставщика: постоянная часть подписки оплачивает сопровождение правил, а не только время

Sheet Консервативный
A1: Расчёт: консервативный сценарий
A2: Входы — зелёные ссылки на «Допущения», «План» и «Рынок»; в строке одна формула для всех лет; млн ₽ без НДС
A4: № | B4: Показатель | C4: Единица | D4: Константа | E4: 2026 | F4: 2027 | G4: 2028 | H4: 2029 | I4: 2030 | J4: 2031 | K4: Итого 2027–2031 | L4: Как считается
A5: Входные данные (ссылки на «Допущения», «План», «Рынок»)
A6: 1 | B6: Год договора с ВТБ | C6: год | D6: =Допущения!$D$49 -> 2028
A7: 2 | B7: Клиенты-бизнесы ВТБ | C7: млн | D7: =Допущения!$D$7 -> 1.8
A8: 3 | B8: Подписка уровня 1: постоянная часть | C8: млн ₽ в год | D8: =Допущения!$D$42 -> 3
A9: 4 | B9: Плата за активного клиента-бизнес | C9: ₽ в год | D9: =Допущения!$D$43 -> 2
A10: 5 | B10: Подписка уровня 2: постоянная часть | C10: млн ₽ в год | D10: =Допущения!$D$44 -> 1
A11: 6 | B11: Внедрение, уровень 1 | C11: млн ₽ | D11: =Допущения!$D$45 -> 6
A12: 7 | B12: Внедрение, уровень 2 | C12: млн ₽ | D12: =Допущения!$D$46 -> 1.5
A13: 8 | B13: Индексация цен | C13: доля в год | D13: =Допущения!$D$47 -> 0.04
A14: 9 | B14: Рост подписки за счёт новых операций | C14: доля в год | D14: =Допущения!$D$48 -> 0
A15: 10 | B15: Рост окладов | C15: доля в год | D15: =Допущения!$D$51 -> 0.07
A16: 11 | B16: Взносы в пределах базы | C16: доля | D16: =Допущения!$D$52 -> 0.15
A17: 12 | B17: Взносы сверх базы | C17: доля | D17: =Допущения!$D$53 -> 0.076
A18: 13 | B18: Взнос на травматизм | C18: доля | D18: =Допущения!$D$54 -> 0.002
A19: 14 | B19: Предельная база взносов 2026 | C19: млн ₽ в год | D19: =Допущения!$D$55 -> 2.979
A20: 15 | B20: Рост базы | C20: доля в год | D20: =Допущения!$D$56 -> 0.08
A21: 16 | B21: Анализ уязвимостей по ОУД4 — первый | C21: млн ₽ | D21: =Допущения!$D$58 -> 3
A22: 17 | B22: Повторная оценка релизов | C22: млн ₽ в год | D22: =Допущения!$D$59 -> 1.2
A23: 18 | B23: Внешняя юридическая экспертиза правил | C23: млн ₽ в год | D23: =Допущения!$D$60 -> 0.4
A24: 19 | B24: Инфраструктура на сотрудника | C24: млн ₽ в год | D24: =Допущения!$D$61 -> 0.12
A25: 20 | B25: Продажи: постоянная часть | C25: млн ₽ в год | D25: =Допущения!$D$62 -> 0.6
A26: 21 | B26: Продажи: на договор | C26: млн ₽ | D26: =Допущения!$D$63 -> 0.3
A27: 22 | B27: Административные: постоянная часть | C27: млн ₽ в год | D27: =Допущения!$D$64 -> 1
A28: 23 | B28: Административные: на сотрудника | C28: млн ₽ в год | D28: =Допущения!$D$65 -> 0.08
A29: 24 | B29: Оборудование на нового сотрудника | C29: млн ₽ | D29: =Допущения!$D$66 -> 0.25
A30: 25 | B30: Регистрация, аккредитация, реестр ПО | C30: млн ₽ | D30: =Допущения!$D$67 -> 0.3
A31: 26 | B31: Рост прочих затрат | C31: доля в год | D31: =Допущения!$D$68 -> 0.05
A32: 27 | B32: Резерв | C32: доля затрат | D32: =Допущения!$D$69 -> 0.1
A33: 28 | B33: Налог на прибыль | C33: доля | D33: =Допущения!$D$71 -> 0.05
A34: 29 | B34: Перенос убытка: доля прибыли | C34: доля | D34: =Допущения!$D$72 -> 0.5
A35: 30 | B35: Срок оплаты банками | C35: дней | D35: =Допущения!$D$73 -> 120
A36: 31 | B36: Ставка дисконтирования | C36: доля | D36: =Допущения!$D$74 -> 0.3
A37: 32 | B37: Рост после 2031 года | C37: доля в год | D37: =Допущения!$D$75 -> 0.04
A38: 33 | B38: Запас к финансированию | C38: доля | D38: =Допущения!$D$76 -> 0.2
A39: 34 | B39: Клиентов у банка уровня 1, кроме ВТБ | C39: млн | D39: =Рынок!$D$30 -> 0.49090909 | L39: лист «Рынок»
A40: 35 | B40: Клиентов у банка уровня 2 | C40: млн | D40: =Рынок!$D$31 -> 0.028125 | L40: лист «Рынок»
A41: 36 | B41: Оклад: Основатели: продукт и продажи, архитектура правил | C41: тыс. ₽ в месяц | D41: =План!$D$8 -> 200 | L41: лист «План»
A42: 37 | B42: Оклад: Разработчики | C42: тыс. ₽ в месяц | D42: =План!$D$9 -> 280 | L42: лист «План»
A43: 38 | B43: Оклад: Юрист-аналитик правил | C43: тыс. ₽ в месяц | D43: =План!$D$10 -> 230 | L43: лист «План»
A44: 39 | B44: Оклад: Инженеры внедрения и поддержки | C44: тыс. ₽ в месяц | D44: =План!$D$11 -> 220 | L44: лист «План»
A45: 40 | B45: Оклад: Инженер качества и ИБ | C45: тыс. ₽ в месяц | D45: =План!$D$12 -> 250 | L45: лист «План»
A46: 41 | B46: Оклад: Менеджер по работе с банками | C46: тыс. ₽ в месяц | D46: =План!$D$13 -> 220 | L46: лист «План»
A47: 42 | B47: Новые банки уровня 1 (кроме ВТБ) | C47: банков | E47: =План!E6 -> 0 | F47: =План!F6 -> 0 | G47: =План!G6 -> 0 | H47: =План!H6 -> 0 | I47: =План!I6 -> 0 | J47: =План!J6 -> 0 | K47: =SUM(F47:J47) -> 0 | L47: лист «План»
A48: 43 | B48: Новые банки уровня 2 | C48: банков | E48: =План!E7 -> 0 | F48: =План!F7 -> 0 | G48: =План!G7 -> 0 | H48: =План!H7 -> 1 | I48: =План!I7 -> 1 | J48: =План!J7 -> 1 | K48: =SUM(F48:J48) -> 3 | L48: лист «План»
A49: 44 | B49: Численность: Основатели: продукт и продажи, архитектура правил | C49: ставок | E49: =План!E8 -> 2 | F49: =План!F8 -> 2 | G49: =План!G8 -> 2 | H49: =План!H8 -> 2 | I49: =План!I8 -> 2 | J49: =План!J8 -> 2 | L49: лист «План»
A50: 45 | B50: Численность: Разработчики | C50: ставок | E50: =План!E9 -> 0 | F50: =План!F9 -> 0 | G50: =План!G9 -> 1 | H50: =План!H9 -> 1 | I50: =План!I9 -> 1 | J50: =План!J9 -> 1 | L50: лист «План»
A51: 46 | B51: Численность: Юрист-аналитик правил | C51: ставок | E51: =План!E10 -> 0 | F51: =План!F10 -> 0.5 | G51: =План!G10 -> 0.5 | H51: =План!H10 -> 0.5 | I51: =План!I10 -> 0.5 | J51: =План!J10 -> 0.5 | L51: лист «План»
A52: 47 | B52: Численность: Инженеры внедрения и поддержки | C52: ставок | E52: =План!E11 -> 0 | F52: =План!F11 -> 0 | G52: =План!G11 -> 0 | H52: =План!H11 -> 0.5 | I52: =План!I11 -> 0.5 | J52: =План!J11 -> 0.5 | L52: лист «План»
A53: 48 | B53: Численность: Инженер качества и ИБ | C53: ставок | E53: =План!E12 -> 0 | F53: =План!F12 -> 0 | G53: =План!G12 -> 0 | H53: =План!H12 -> 0 | I53: =План!I12 -> 0 | J53: =План!J12 -> 0 | L53: лист «План»
A54: 49 | B54: Численность: Менеджер по работе с банками | C54: ставок | E54: =План!E13 -> 0 | F54: =План!F13 -> 0 | G54: =План!G13 -> 0 | H54: =План!H13 -> 0 | I54: =План!I13 -> 0 | J54: =План!J13 -> 0 | L54: лист «План»
A55: 1. Время
A56: 50 | B56: Год | E56: =Допущения!$D$3 -> 2026 | F56: =E56+1 -> 2027 | G56: =F56+1 -> 2028 | H56: =G56+1 -> 2029 | I56: =H56+1 -> 2030 | J56: =I56+1 -> 2031 | L56: предыдущий + 1
A57: 51 | B57: Индекс цен к 2027 году | C57: раз | F57: =(1+$D$13)^(F$56-$E$56-1) -> 1 | G57: =(1+$D$13)^(G$56-$E$56-1) -> 1.04 | H57: =(1+$D$13)^(H$56-$E$56-1) -> 1.0816 | I57: =(1+$D$13)^(I$56-$E$56-1) -> 1.124864 | J57: =(1+$D$13)^(J$56-$E$56-1) -> 1.1698586 | L57: (1 + индексация) ^ (год − 2027)
A58: 52 | B58: Индекс прочих затрат к 2027 году | C58: раз | F58: =(1+$D$31)^(F$56-$E$56-1) -> 1 | G58: =(1+$D$31)^(G$56-$E$56-1) -> 1.05 | H58: =(1+$D$31)^(H$56-$E$56-1) -> 1.1025 | I58: =(1+$D$31)^(I$56-$E$56-1) -> 1.157625 | J58: =(1+$D$31)^(J$56-$E$56-1) -> 1.2155063 | L58: то же для затрат
A59: 53 | B59: Индекс окладов к 2027 году | C59: раз | F59: =(1+$D$15)^(F$56-$E$56-1) -> 1 | G59: =(1+$D$15)^(G$56-$E$56-1) -> 1.07 | H59: =(1+$D$15)^(H$56-$E$56-1) -> 1.1449 | I59: =(1+$D$15)^(I$56-$E$56-1) -> 1.225043 | J59: =(1+$D$15)^(J$56-$E$56-1) -> 1.310796 | L59: то же для окладов
A60: 54 | B60: Предельная база взносов | C60: млн ₽ в год | F60: =$D$19*(1+$D$20)^(F$56-$E$56) -> 3.21732 | G60: =$D$19*(1+$D$20)^(G$56-$E$56) -> 3.4747056 | H60: =$D$19*(1+$D$20)^(H$56-$E$56) -> 3.752682 | I60: =$D$19*(1+$D$20)^(I$56-$E$56) -> 4.0528966 | J60: =$D$19*(1+$D$20)^(J$56-$E$56) -> 4.3771283 | L60: база 2026 × (1 + рост) ^ (год − 2026)
A61: 2. Договоры
A62: 55 | B62: Договор с ВТБ (1 — в этом году) | C62: банков | F62: =IF(F$56=$D$6,1,0) -> 0 | G62: =IF(G$56=$D$6,1,0) -> 1 | H62: =IF(H$56=$D$6,1,0) -> 0 | I62: =IF(I$56=$D$6,1,0) -> 0 | J62: =IF(J$56=$D$6,1,0) -> 0 | L62: год договора с ВТБ
A63: 56 | B63: Новые банки уровня 1, с ВТБ | C63: банков | E63: =0 -> 0 | F63: =F62+F47 -> 0 | G63: =G62+G47 -> 1 | H63: =H62+H47 -> 0 | I63: =I62+I47 -> 0 | J63: =J62+J47 -> 0 | K63: =SUM(F63:J63) -> 1 | L63: ВТБ + другие
A64: 57 | B64: Банки уровня 1 с договором, на конец года | C64: банков | E64: =0 -> 0 | F64: =E64+F63 -> 0 | G64: =F64+G63 -> 1 | H64: =G64+H63 -> 1 | I64: =H64+I63 -> 1 | J64: =I64+J63 -> 1 | L64: накопленным итогом
A65: 58 | B65: Банки уровня 2 с договором, на конец года | C65: банков | E65: =0 -> 0 | F65: =E65+F48 -> 0 | G65: =F65+G48 -> 0 | H65: =G65+H48 -> 1 | I65: =H65+I48 -> 2 | J65: =I65+J48 -> 3 | L65: накопленным итогом
A66: 59 | B66: Банков с договором, на конец года | C66: банков | E66: =0 -> 0 | F66: =F64+F65 -> 0 | G66: =G64+G65 -> 1 | H66: =H64+H65 -> 2 | I66: =I64+I65 -> 3 | J66: =J64+J65 -> 4 | L66: уровень 1 + уровень 2
A67: 60 | B67: Новых договоров за год | C67: банков | F67: =F63+F48 -> 0 | G67: =G63+G48 -> 1 | H67: =H63+H48 -> 1 | I67: =I63+I48 -> 1 | J67: =J63+J48 -> 1 | K67: =SUM(F67:J67) -> 4
A68: 3. Выручка, млн ₽ без НДС
A69: 61 | B69: Подписка ВТБ | C69: млн ₽ | F69: =IF(F$56>$D$6,($D$8+$D$7*$D$9)*(1+$D$14)^(F$56-$D$6-1)*F57,0) -> 0 | G69: =IF(G$56>$D$6,($D$8+$D$7*$D$9)*(1+$D$14)^(G$56-$D$6-1)*G57,0) -> 0 | H69: =IF(H$56>$D$6,($D$8+$D$7*$D$9)*(1+$D$14)^(H$56-$D$6-1)*H57,0) -> 7.13856 | I69: =IF(I$56>$D$6,($D$8+$D$7*$D$9)*(1+$D$14)^(I$56-$D$6-1)*I57,0) -> 7.4241024 | J69: =IF(J$56>$D$6,($D$8+$D$7*$D$9)*(1+$D$14)^(J$56-$D$6-1)*J57,0) -> 7.7210665 | K69: =SUM(F69:J69) -> 22.283729 | L69: со следующего года после договора; растёт с новыми операциями; индексируется
A70: 62 | B70: Подписка других банков уровня 1 | C70: млн ₽ | F70: =($D$8+$D$39*$D$9)*F57*SUMPRODUCT($E$47:E$47,(1+$D$14)^(F$56-$E$56:E$56-1)) -> 0 | G70: =($D$8+$D$39*$D$9)*G57*SUMPRODUCT($E$47:F$47,(1+$D$14)^(G$56-$E$56:F$56-1)) -> 0 | H70: =($D$8+$D$39*$D$9)*H57*SUMPRODUCT($E$47:G$47,(1+$D$14)^(H$56-$E$56:G$56-1)) -> 0 | I70: =($D$8+$D$39*$D$9)*I57*SUMPRODUCT($E$47:H$47,(1+$D$14)^(I$56-$E$56:H$56-1)) -> 0 | J70: =($D$8+$D$39*$D$9)*J57*SUMPRODUCT($E$47:I$47,(1+$D$14)^(J$56-$E$56:I$56-1)) -> 0 | K70: =SUM(F70:J70) -> 0 | L70: по годам договоров: подписка × (1 + рост) ^ (лет после первого года) × индекс
A71: 63 | B71: Подписка банков уровня 2 | C71: млн ₽ | F71: =($D$10+$D$40*$D$9)*F57*SUMPRODUCT($E$48:E$48,(1+$D$14)^(F$56-$E$56:E$56-1)) -> 0 | G71: =($D$10+$D$40*$D$9)*G57*SUMPRODUCT($E$48:F$48,(1+$D$14)^(G$56-$E$56:F$56-1)) -> 0 | H71: =($D$10+$D$40*$D$9)*H57*SUMPRODUCT($E$48:G$48,(1+$D$14)^(H$56-$E$56:G$56-1)) -> 0 | I71: =($D$10+$D$40*$D$9)*I57*SUMPRODUCT($E$48:H$48,(1+$D$14)^(I$56-$E$56:H$56-1)) -> 1.1881376 | J71: =($D$10+$D$40*$D$9)*J57*SUMPRODUCT($E$48:I$48,(1+$D$14)^(J$56-$E$56:I$56-1)) -> 2.4713262 | K71: =SUM(F71:J71) -> 3.6594638 | L71: то же для уровня 2
A72: 64 | B72: Внедрение | C72: млн ₽ | F72: =(F63*$D$11+F48*$D$12)*F57 -> 0 | G72: =(G63*$D$11+G48*$D$12)*G57 -> 6.24 | H72: =(H63*$D$11+H48*$D$12)*H57 -> 1.6224 | I72: =(I63*$D$11+I48*$D$12)*I57 -> 1.687296 | J72: =(J63*$D$11+J48*$D$12)*J57 -> 1.7547878 | K72: =SUM(F72:J72) -> 11.304484 | L72: новые договоры × плата за внедрение × индекс
A73: 65 | B73: Подписка всего | C73: млн ₽ | F73: =F69+F70+F71 -> 0 | G73: =G69+G70+G71 -> 0 | H73: =H69+H70+H71 -> 7.13856 | I73: =I69+I70+I71 -> 8.61224 | J73: =J69+J70+J71 -> 10.192393 | K73: =SUM(F73:J73) -> 25.943193
A74: 66 | B74: Выручка | C74: млн ₽ | F74: =F73+F72 -> 0 | G74: =G73+G72 -> 6.24 | H74: =H73+H72 -> 8.76096 | I74: =I73+I72 -> 10.299536 | J74: =J73+J72 -> 11.947181 | K74: =SUM(F74:J74) -> 37.247677 | L74: подписка + внедрение
A75: 67 | B75: Годовая подписка на конец года (ARR) | C75: млн ₽ в год | F75: =IF(F$56>=$D$6,($D$8+$D$7*$D$9)*(1+$D$14)^(F$56-$D$6)*F57,0)+($D$8+$D$39*$D$9)*F57*SUMPRODUCT($E$47:F$47,(1+$D$14)^(F$56-$E$56:F$56))+($D$10+$D$40*$D$9)*F57*SUMPRODUCT($E$48:F$48,(1+$D$14)^(F$56-$E$56:F$56)) -> 0 | G75: =IF(G$56>=$D$6,($D$8+$D$7*$D$9)*(1+$D$14)^(G$56-$D$6)*G57,0)+($D$8+$D$39*$D$9)*G57*SUMPRODUCT($E$47:G$47,(1+$D$14)^(G$56-$E$56:G$56))+($D$10+$D$40*$D$9)*G57*SUMPRODUCT($E$48:G$48,(1+$D$14)^(G$56-$E$56:G$56)) -> 6.864 | H75: =IF(H$56>=$D$6,($D$8+$D$7*$D$9)*(1+$D$14)^(H$56-$D$6)*H57,0)+($D$8+$D$39*$D$9)*H57*SUMPRODUCT($E$47:H$47,(1+$D$14)^(H$56-$E$56:H$56))+($D$10+$D$40*$D$9)*H57*SUMPRODUCT($E$48:H$48,(1+$D$14)^(H$56-$E$56:H$56)) -> 8.281 | I75: =IF(I$56>=$D$6,($D$8+$D$7*$D$9)*(1+$D$14)^(I$56-$D$6)*I57,0)+($D$8+$D$39*$D$9)*I57*SUMPRODUCT($E$47:I$47,(1+$D$14)^(I$56-$E$56:I$56))+($D$10+$D$40*$D$9)*I57*SUMPRODUCT($E$48:I$48,(1+$D$14)^(I$56-$E$56:I$56)) -> 9.8003776 | J75: =IF(J$56>=$D$6,($D$8+$D$7*$D$9)*(1+$D$14)^(J$56-$D$6)*J57,0)+($D$8+$D$39*$D$9)*J57*SUMPRODUCT($E$47:J$47,(1+$D$14)^(J$56-$E$56:J$56))+($D$10+$D$40*$D$9)*J57*SUMPRODUCT($E$48:J$48,(1+$D$14)^(J$56-$E$56:J$56)) -> 11.428056 | L75: подписка всех банков с договором в ценах года
A76: 4. Затраты, млн ₽
A77: 68 | B77: Численность команды | C77: ставок | E77: =E49+E50+E51+E52+E53+E54 -> 2 | F77: =F49+F50+F51+F52+F53+F54 -> 2.5 | G77: =G49+G50+G51+G52+G53+G54 -> 3.5 | H77: =H49+H50+H51+H52+H53+H54 -> 4 | I77: =I49+I50+I51+I52+I53+I54 -> 4 | J77: =J49+J50+J51+J52+J53+J54 -> 4 | L77: сумма по ролям
A78: 69 | B78: Новые сотрудники | C78: ставок | F78: =MAX(0,F77-E77) -> 0.5 | G78: =MAX(0,G77-F77) -> 1 | H78: =MAX(0,H77-G77) -> 0.5 | I78: =MAX(0,I77-H77) -> 0 | J78: =MAX(0,J77-I77) -> 0 | L78: прирост численности
A79: 70 | B79: Годовой оклад на ставку: Основатели: продукт и продажи, архитектура правил | C79: млн ₽ | F79: =$D$41*12/1000*F59 -> 2.4 | G79: =$D$41*12/1000*G59 -> 2.568 | H79: =$D$41*12/1000*H59 -> 2.74776 | I79: =$D$41*12/1000*I59 -> 2.9401032 | J79: =$D$41*12/1000*J59 -> 3.1459104 | L79: оклад × 12 × индекс
A80: 71 | B80: Годовой оклад на ставку: Разработчики | C80: млн ₽ | F80: =$D$42*12/1000*F59 -> 3.36 | G80: =$D$42*12/1000*G59 -> 3.5952 | H80: =$D$42*12/1000*H59 -> 3.846864 | I80: =$D$42*12/1000*I59 -> 4.1161445 | J80: =$D$42*12/1000*J59 -> 4.4042746 | L80: оклад × 12 × индекс
A81: 72 | B81: Годовой оклад на ставку: Юрист-аналитик правил | C81: млн ₽ | F81: =$D$43*12/1000*F59 -> 2.76 | G81: =$D$43*12/1000*G59 -> 2.9532 | H81: =$D$43*12/1000*H59 -> 3.159924 | I81: =$D$43*12/1000*I59 -> 3.3811187 | J81: =$D$43*12/1000*J59 -> 3.617797 | L81: оклад × 12 × индекс
A82: 73 | B82: Годовой оклад на ставку: Инженеры внедрения и поддержки | C82: млн ₽ | F82: =$D$44*12/1000*F59 -> 2.64 | G82: =$D$44*12/1000*G59 -> 2.8248 | H82: =$D$44*12/1000*H59 -> 3.022536 | I82: =$D$44*12/1000*I59 -> 3.2341135 | J82: =$D$44*12/1000*J59 -> 3.4605015 | L82: оклад × 12 × индекс
A83: 74 | B83: Годовой оклад на ставку: Инженер качества и ИБ | C83: млн ₽ | F83: =$D$45*12/1000*F59 -> 3 | G83: =$D$45*12/1000*G59 -> 3.21 | H83: =$D$45*12/1000*H59 -> 3.4347 | I83: =$D$45*12/1000*I59 -> 3.675129 | J83: =$D$45*12/1000*J59 -> 3.932388 | L83: оклад × 12 × индекс
A84: 75 | B84: Годовой оклад на ставку: Менеджер по работе с банками | C84: млн ₽ | F84: =$D$46*12/1000*F59 -> 2.64 | G84: =$D$46*12/1000*G59 -> 2.8248 | H84: =$D$46*12/1000*H59 -> 3.022536 | I84: =$D$46*12/1000*I59 -> 3.2341135 | J84: =$D$46*12/1000*J59 -> 3.4605015 | L84: оклад × 12 × индекс
A85: 76 | B85: Фонд оплаты труда: Основатели: продукт и продажи, архитектура правил | C85: млн ₽ | F85: =F49*F79 -> 4.8 | G85: =G49*G79 -> 5.136 | H85: =H49*H79 -> 5.49552 | I85: =I49*I79 -> 5.8802064 | J85: =J49*J79 -> 6.2918208 | K85: =SUM(F85:J85) -> 27.603547 | L85: ставки × годовой оклад
A86: 77 | B86: Фонд оплаты труда: Разработчики | C86: млн ₽ | F86: =F50*F80 -> 0 | G86: =G50*G80 -> 3.5952 | H86: =H50*H80 -> 3.846864 | I86: =I50*I80 -> 4.1161445 | J86: =J50*J80 -> 4.4042746 | K86: =SUM(F86:J86) -> 15.962483 | L86: ставки × годовой оклад
A87: 78 | B87: Фонд оплаты труда: Юрист-аналитик правил | C87: млн ₽ | F87: =F51*F81 -> 1.38 | G87: =G51*G81 -> 1.4766 | H87: =H51*H81 -> 1.579962 | I87: =I51*I81 -> 1.6905593 | J87: =J51*J81 -> 1.8088985 | K87: =SUM(F87:J87) -> 7.9360198 | L87: ставки × годовой оклад
A88: 79 | B88: Фонд оплаты труда: Инженеры внедрения и поддержки | C88: млн ₽ | F88: =F52*F82 -> 0 | G88: =G52*G82 -> 0 | H88: =H52*H82 -> 1.511268 | I88: =I52*I82 -> 1.6170568 | J88: =J52*J82 -> 1.7302507 | K88: =SUM(F88:J88) -> 4.8585755 | L88: ставки × годовой оклад
A89: 80 | B89: Фонд оплаты труда: Инженер качества и ИБ | C89: млн ₽ | F89: =F53*F83 -> 0 | G89: =G53*G83 -> 0 | H89: =H53*H83 -> 0 | I89: =I53*I83 -> 0 | J89: =J53*J83 -> 0 | K89: =SUM(F89:J89) -> 0 | L89: ставки × годовой оклад
A90: 81 | B90: Фонд оплаты труда: Менеджер по работе с банками | C90: млн ₽ | F90: =F54*F84 -> 0 | G90: =G54*G84 -> 0 | H90: =H54*H84 -> 0 | I90: =I54*I84 -> 0 | J90: =J54*J84 -> 0 | K90: =SUM(F90:J90) -> 0 | L90: ставки × годовой оклад
A91: 82 | B91: Фонд оплаты труда | C91: млн ₽ | F91: =F85+F86+F87+F88+F89+F90 -> 6.18 | G91: =G85+G86+G87+G88+G89+G90 -> 10.2078 | H91: =H85+H86+H87+H88+H89+H90 -> 12.433614 | I91: =I85+I86+I87+I88+I89+I90 -> 13.303967 | J91: =J85+J86+J87+J88+J89+J90 -> 14.235245 | K91: =SUM(F91:J91) -> 56.360626
A92: 83 | B92: Страховые взносы | C92: млн ₽ | F92: =F49*(MIN(F79,F60)*$D$16+MAX(0,F79-F60)*$D$17+F79*$D$18)+F50*(MIN(F80,F60)*$D$16+MAX(0,F80-F60)*$D$17+F80*$D$18)+F51*(MIN(F81,F60)*$D$16+MAX(0,F81-F60)*$D$17+F81*$D$18)+F52*(MIN(F82,F60)*$D$16+MAX(0,F82-F60)*$D$17+F82*$D$18)+F53*(MIN(F83,F60)*$D$16+MAX(0,F83-F60)*$D$17+F83*$D$18)+F54*(MIN(F84,F60)*$D$16+MAX(0,F84-F60)*$D$17+F84*$D$18) -> 0.93936 | G92: =G49*(MIN(G79,G60)*$D$16+MAX(0,G79-G60)*$D$17+G79*$D$18)+G50*(MIN(G80,G60)*$D$16+MAX(0,G80-G60)*$D$17+G80*$D$18)+G51*(MIN(G81,G60)*$D$16+MAX(0,G81-G60)*$D$17+G81*$D$18)+G52*(MIN(G82,G60)*$D$16+MAX(0,G82-G60)*$D$17+G82*$D$18)+G53*(MIN(G83,G60)*$D$16+MAX(0,G83-G60)*$D$17+G83*$D$18)+G54*(MIN(G84,G60)*$D$16+MAX(0,G84-G60)*$D$17+G84*$D$18) -> 1.542669 | H92: =H49*(MIN(H79,H60)*$D$16+MAX(0,H79-H60)*$D$17+H79*$D$18)+H50*(MIN(H80,H60)*$D$16+MAX(0,H80-H60)*$D$17+H80*$D$18)+H51*(MIN(H81,H60)*$D$16+MAX(0,H81-H60)*$D$17+H81*$D$18)+H52*(MIN(H82,H60)*$D$16+MAX(0,H82-H60)*$D$17+H82*$D$18)+H53*(MIN(H83,H60)*$D$16+MAX(0,H83-H60)*$D$17+H83*$D$18)+H54*(MIN(H84,H60)*$D$16+MAX(0,H84-H60)*$D$17+H84*$D$18) -> 1.8829399 | I92: =I49*(MIN(I79,I60)*$D$16+MAX(0,I79-I60)*$D$17+I79*$D$18)+I50*(MIN(I80,I60)*$D$16+MAX(0,I80-I60)*$D$17+I80*$D$18)+I51*(MIN(I81,I60)*$D$16+MAX(0,I81-I60)*$D$17+I81*$D$18)+I52*(MIN(I82,I60)*$D$16+MAX(0,I82-I60)*$D$17+I82*$D$18)+I53*(MIN(I83,I60)*$D$16+MAX(0,I83-I60)*$D$17+I83*$D$18)+I54*(MIN(I84,I60)*$D$16+MAX(0,I84-I60)*$D$17+I84*$D$18) -> 2.0175226 | J92: =J49*(MIN(J79,J60)*$D$16+MAX(0,J79-J60)*$D$17+J79*$D$18)+J50*(MIN(J80,J60)*$D$16+MAX(0,J80-J60)*$D$17+J80*$D$18)+J51*(MIN(J81,J60)*$D$16+MAX(0,J81-J60)*$D$17+J81*$D$18)+J52*(MIN(J82,J60)*$D$16+MAX(0,J82-J60)*$D$17+J82*$D$18)+J53*(MIN(J83,J60)*$D$16+MAX(0,J83-J60)*$D$17+J83*$D$18)+J54*(MIN(J84,J60)*$D$16+MAX(0,J84-J60)*$D$17+J84*$D$18) -> 2.1617484 | K92: =SUM(F92:J92) -> 8.5442399 | L92: по каждой роли: в пределах базы × льготный тариф + сверх базы × 7,6 % + травматизм
A93: 84 | B93: Первый договор (1 — в этом году) | F93: =IF(AND(F66>0,E66=0),1,0) -> 0 | G93: =IF(AND(G66>0,F66=0),1,0) -> 1 | H93: =IF(AND(H66>0,G66=0),1,0) -> 0 | I93: =IF(AND(I66>0,H66=0),1,0) -> 0 | J93: =IF(AND(J66>0,I66=0),1,0) -> 0
A94: 85 | B94: Оценка ИБ (анализ уязвимостей) | C94: млн ₽ | F94: =(F93*$D$21+IF(E66>0,1,0)*$D$22)*F58 -> 0 | G94: =(G93*$D$21+IF(F66>0,1,0)*$D$22)*G58 -> 3.15 | H94: =(H93*$D$21+IF(G66>0,1,0)*$D$22)*H58 -> 1.323 | I94: =(I93*$D$21+IF(H66>0,1,0)*$D$22)*I58 -> 1.38915 | J94: =(J93*$D$21+IF(I66>0,1,0)*$D$22)*J58 -> 1.4586075 | K94: =SUM(F94:J94) -> 7.3207575 | L94: первая — в год первого договора, дальше — ежегодно
A95: 86 | B95: Внешняя юридическая экспертиза правил | C95: млн ₽ | F95: =$D$23*F58 -> 0.4 | G95: =$D$23*G58 -> 0.42 | H95: =$D$23*H58 -> 0.441 | I95: =$D$23*I58 -> 0.46305 | J95: =$D$23*J58 -> 0.4862025 | K95: =SUM(F95:J95) -> 2.2102525
A96: 87 | B96: Инфраструктура и инструменты | C96: млн ₽ | F96: =$D$24*F77*F58 -> 0.3 | G96: =$D$24*G77*G58 -> 0.441 | H96: =$D$24*H77*H58 -> 0.5292 | I96: =$D$24*I77*I58 -> 0.55566 | J96: =$D$24*J77*J58 -> 0.583443 | K96: =SUM(F96:J96) -> 2.409303 | L96: на сотрудника
A97: 88 | B97: Продажи и маркетинг | C97: млн ₽ | F97: =($D$25+$D$26*F67)*F58 -> 0.6 | G97: =($D$25+$D$26*G67)*G58 -> 0.945 | H97: =($D$25+$D$26*H67)*H58 -> 0.99225 | I97: =($D$25+$D$26*I67)*I58 -> 1.0418625 | J97: =($D$25+$D$26*J67)*J58 -> 1.0939556 | K97: =SUM(F97:J97) -> 4.6730681 | L97: постоянная часть + на договор
A98: 89 | B98: Административные | C98: млн ₽ | F98: =($D$27+$D$28*F77)*F58 -> 1.2 | G98: =($D$27+$D$28*G77)*G58 -> 1.344 | H98: =($D$27+$D$28*H77)*H58 -> 1.4553 | I98: =($D$27+$D$28*I77)*I58 -> 1.528065 | J98: =($D$27+$D$28*J77)*J58 -> 1.6044683 | K98: =SUM(F98:J98) -> 7.1318332 | L98: постоянная часть + на сотрудника
A99: 90 | B99: Оборудование | C99: млн ₽ | F99: =$D$29*F78*F58 -> 0.125 | G99: =$D$29*G78*G58 -> 0.2625 | H99: =$D$29*H78*H58 -> 0.1378125 | I99: =$D$29*I78*I58 -> 0 | J99: =$D$29*J78*J58 -> 0 | K99: =SUM(F99:J99) -> 0.5253125 | L99: на нового сотрудника
A100: 91 | B100: Регистрация, аккредитация, реестр ПО | C100: млн ₽ | F100: =IF(F$56=$F$56,$D$30,0) -> 0.3 | G100: =IF(G$56=$F$56,$D$30,0) -> 0 | H100: =IF(H$56=$F$56,$D$30,0) -> 0 | I100: =IF(I$56=$F$56,$D$30,0) -> 0 | J100: =IF(J$56=$F$56,$D$30,0) -> 0 | K100: =SUM(F100:J100) -> 0.3 | L100: только 2027 год
A101: 92 | B101: Затраты до резерва | C101: млн ₽ | F101: =F91+F92+F94+F95+F96+F97+F98+F99+F100 -> 10.04436 | G101: =G91+G92+G94+G95+G96+G97+G98+G99+G100 -> 18.312969 | H101: =H91+H92+H94+H95+H96+H97+H98+H99+H100 -> 19.195116 | I101: =I91+I92+I94+I95+I96+I97+I98+I99+I100 -> 20.299277 | J101: =J91+J92+J94+J95+J96+J97+J98+J99+J100 -> 21.62367 | K101: =SUM(F101:J101) -> 89.475392
...

Sheet Базовый
A1: Расчёт: базовый сценарий
A2: Входы — зелёные ссылки на «Допущения», «План» и «Рынок»; в строке одна формула для всех лет; млн ₽ без НДС
A4: № | B4: Показатель | C4: Единица | D4: Константа | E4: 2026 | F4: 2027 | G4: 2028 | H4: 2029 | I4: 2030 | J4: 2031 | K4: Итого 2027–2031 | L4: Как считается
A5: Входные данные (ссылки на «Допущения», «План», «Рынок»)
A6: 1 | B6: Год договора с ВТБ | C6: год | D6: =Допущения!$E$49 -> 2027
A7: 2 | B7: Клиенты-бизнесы ВТБ | C7: млн | D7: =Допущения!$E$7 -> 1.8
A8: 3 | B8: Подписка уровня 1: постоянная часть | C8: млн ₽ в год | D8: =Допущения!$E$42 -> 6
A9: 4 | B9: Плата за активного клиента-бизнес | C9: ₽ в год | D9: =Допущения!$E$43 -> 5
A10: 5 | B10: Подписка уровня 2: постоянная часть | C10: млн ₽ в год | D10: =Допущения!$E$44 -> 1.5
A11: 6 | B11: Внедрение, уровень 1 | C11: млн ₽ | D11: =Допущения!$E$45 -> 8
A12: 7 | B12: Внедрение, уровень 2 | C12: млн ₽ | D12: =Допущения!$E$46 -> 2
A13: 8 | B13: Индексация цен | C13: доля в год | D13: =Допущения!$E$47 -> 0.05
A14: 9 | B14: Рост подписки за счёт новых операций | C14: доля в год | D14: =Допущения!$E$48 -> 0.15
A15: 10 | B15: Рост окладов | C15: доля в год | D15: =Допущения!$E$51 -> 0.07
A16: 11 | B16: Взносы в пределах базы | C16: доля | D16: =Допущения!$E$52 -> 0.15
A17: 12 | B17: Взносы сверх базы | C17: доля | D17: =Допущения!$E$53 -> 0.076
A18: 13 | B18: Взнос на травматизм | C18: доля | D18: =Допущения!$E$54 -> 0.002
A19: 14 | B19: Предельная база взносов 2026 | C19: млн ₽ в год | D19: =Допущения!$E$55 -> 2.979
A20: 15 | B20: Рост базы | C20: доля в год | D20: =Допущения!$E$56 -> 0.08
A21: 16 | B21: Анализ уязвимостей по ОУД4 — первый | C21: млн ₽ | D21: =Допущения!$E$58 -> 2.5
A22: 17 | B22: Повторная оценка релизов | C22: млн ₽ в год | D22: =Допущения!$E$59 -> 1
A23: 18 | B23: Внешняя юридическая экспертиза правил | C23: млн ₽ в год | D23: =Допущения!$E$60 -> 0.6
A24: 19 | B24: Инфраструктура на сотрудника | C24: млн ₽ в год | D24: =Допущения!$E$61 -> 0.15
A25: 20 | B25: Продажи: постоянная часть | C25: млн ₽ в год | D25: =Допущения!$E$62 -> 1
A26: 21 | B26: Продажи: на договор | C26: млн ₽ | D26: =Допущения!$E$63 -> 0.4
A27: 22 | B27: Административные: постоянная часть | C27: млн ₽ в год | D27: =Допущения!$E$64 -> 1.2
A28: 23 | B28: Административные: на сотрудника | C28: млн ₽ в год | D28: =Допущения!$E$65 -> 0.1
A29: 24 | B29: Оборудование на нового сотрудника | C29: млн ₽ | D29: =Допущения!$E$66 -> 0.25
A30: 25 | B30: Регистрация, аккредитация, реестр ПО | C30: млн ₽ | D30: =Допущения!$E$67 -> 0.3
A31: 26 | B31: Рост прочих затрат | C31: доля в год | D31: =Допущения!$E$68 -> 0.05
A32: 27 | B32: Резерв | C32: доля затрат | D32: =Допущения!$E$69 -> 0.1
A33: 28 | B33: Налог на прибыль | C33: доля | D33: =Допущения!$E$71 -> 0.05
A34: 29 | B34: Перенос убытка: доля прибыли | C34: доля | D34: =Допущения!$E$72 -> 0.5
A35: 30 | B35: Срок оплаты банками | C35: дней | D35: =Допущения!$E$73 -> 90
A36: 31 | B36: Ставка дисконтирования | C36: доля | D36: =Допущения!$E$74 -> 0.3
A37: 32 | B37: Рост после 2031 года | C37: доля в год | D37: =Допущения!$E$75 -> 0.04
A38: 33 | B38: Запас к финансированию | C38: доля | D38: =Допущения!$E$76 -> 0.2
A39: 34 | B39: Клиентов у банка уровня 1, кроме ВТБ | C39: млн | D39: =Рынок!$E$30 -> 0.49090909 | L39: лист «Рынок»
A40: 35 | B40: Клиентов у банка уровня 2 | C40: млн | D40: =Рынок!$E$31 -> 0.028125 | L40: лист «Рынок»
A41: 36 | B41: Оклад: Основатели: продукт и продажи, архитектура правил | C41: тыс. ₽ в месяц | D41: =План!$D$18 -> 200 | L41: лист «План»
A42: 37 | B42: Оклад: Разработчики | C42: тыс. ₽ в месяц | D42: =План!$D$19 -> 280 | L42: лист «План»
A43: 38 | B43: Оклад: Юрист-аналитик правил | C43: тыс. ₽ в месяц | D43: =План!$D$20 -> 230 | L43: лист «План»
A44: 39 | B44: Оклад: Инженеры внедрения и поддержки | C44: тыс. ₽ в месяц | D44: =План!$D$21 -> 220 | L44: лист «План»
A45: 40 | B45: Оклад: Инженер качества и ИБ | C45: тыс. ₽ в месяц | D45: =План!$D$22 -> 250 | L45: лист «План»
A46: 41 | B46: Оклад: Менеджер по работе с банками | C46: тыс. ₽ в месяц | D46: =План!$D$23 -> 220 | L46: лист «План»
A47: 42 | B47: Новые банки уровня 1 (кроме ВТБ) | C47: банков | E47: =План!E16 -> 0 | F47: =План!F16 -> 0 | G47: =План!G16 -> 0 | H47: =План!H16 -> 1 | I47: =План!I16 -> 0 | J47: =План!J16 -> 1 | K47: =SUM(F47:J47) -> 2 | L47: лист «План»
A48: 43 | B48: Новые банки уровня 2 | C48: банков | E48: =План!E17 -> 0 | F48: =План!F17 -> 0 | G48: =План!G17 -> 1 | H48: =План!H17 -> 2 | I48: =План!I17 -> 2 | J48: =План!J17 -> 3 | K48: =SUM(F48:J48) -> 8 | L48: лист «План»
A49: 44 | B49: Численность: Основатели: продукт и продажи, архитектура правил | C49: ставок | E49: =План!E18 -> 2 | F49: =План!F18 -> 2 | G49: =План!G18 -> 2 | H49: =План!H18 -> 2 | I49: =План!I18 -> 2 | J49: =План!J18 -> 2 | L49: лист «План»
A50: 45 | B50: Численность: Разработчики | C50: ставок | E50: =План!E19 -> 0 | F50: =План!F19 -> 1 | G50: =План!G19 -> 1 | H50: =План!H19 -> 1 | I50: =План!I19 -> 2 | J50: =План!J19 -> 2 | L50: лист «План»
A51: 46 | B51: Численность: Юрист-аналитик правил | C51: ставок | E51: =План!E20 -> 0 | F51: =План!F20 -> 1 | G51: =План!G20 -> 1 | H51: =План!H20 -> 1 | I51: =План!I20 -> 1 | J51: =План!J20 -> 1 | L51: лист «План»
A52: 47 | B52: Численность: Инженеры внедрения и поддержки | C52: ставок | E52: =План!E21 -> 0 | F52: =План!F21 -> 0 | G52: =План!G21 -> 1 | H52: =План!H21 -> 1 | I52: =План!I21 -> 1 | J52: =План!J21 -> 1 | L52: лист «План»
A53: 48 | B53: Численность: Инженер качества и ИБ | C53: ставок | E53: =План!E22 -> 0 | F53: =План!F22 -> 0 | G53: =План!G22 -> 0 | H53: =План!H22 -> 1 | I53: =План!I22 -> 1 | J53: =План!J22 -> 1 | L53: лист «План»
A54: 49 | B54: Численность: Менеджер по работе с банками | C54: ставок | E54: =План!E23 -> 0 | F54: =План!F23 -> 0 | G54: =План!G23 -> 0 | H54: =План!H23 -> 0 | I54: =План!I23 -> 0 | J54: =План!J23 -> 1 | L54: лист «План»
A55: 1. Время
A56: 50 | B56: Год | E56: =Допущения!$D$3 -> 2026 | F56: =E56+1 -> 2027 | G56: =F56+1 -> 2028 | H56: =G56+1 -> 2029 | I56: =H56+1 -> 2030 | J56: =I56+1 -> 2031 | L56: предыдущий + 1
A57: 51 | B57: Индекс цен к 2027 году | C57: раз | F57: =(1+$D$13)^(F$56-$E$56-1) -> 1 | G57: =(1+$D$13)^(G$56-$E$56-1) -> 1.05 | H57: =(1+$D$13)^(H$56-$E$56-1) -> 1.1025 | I57: =(1+$D$13)^(I$56-$E$56-1) -> 1.157625 | J57: =(1+$D$13)^(J$56-$E$56-1) -> 1.2155063 | L57: (1 + индексация) ^ (год − 2027)
A58: 52 | B58: Индекс прочих затрат к 2027 году | C58: раз | F58: =(1+$D$31)^(F$56-$E$56-1) -> 1 | G58: =(1+$D$31)^(G$56-$E$56-1) -> 1.05 | H58: =(1+$D$31)^(H$56-$E$56-1) -> 1.1025 | I58: =(1+$D$31)^(I$56-$E$56-1) -> 1.157625 | J58: =(1+$D$31)^(J$56-$E$56-1) -> 1.2155063 | L58: то же для затрат
A59: 53 | B59: Индекс окладов к 2027 году | C59: раз | F59: =(1+$D$15)^(F$56-$E$56-1) -> 1 | G59: =(1+$D$15)^(G$56-$E$56-1) -> 1.07 | H59: =(1+$D$15)^(H$56-$E$56-1) -> 1.1449 | I59: =(1+$D$15)^(I$56-$E$56-1) -> 1.225043 | J59: =(1+$D$15)^(J$56-$E$56-1) -> 1.310796 | L59: то же для окладов
A60: 54 | B60: Предельная база взносов | C60: млн ₽ в год | F60: =$D$19*(1+$D$20)^(F$56-$E$56) -> 3.21732 | G60: =$D$19*(1+$D$20)^(G$56-$E$56) -> 3.4747056 | H60: =$D$19*(1+$D$20)^(H$56-$E$56) -> 3.752682 | I60: =$D$19*(1+$D$20)^(I$56-$E$56) -> 4.0528966 | J60: =$D$19*(1+$D$20)^(J$56-$E$56) -> 4.3771283 | L60: база 2026 × (1 + рост) ^ (год − 2026)
A61: 2. Договоры
A62: 55 | B62: Договор с ВТБ (1 — в этом году) | C62: банков | F62: =IF(F$56=$D$6,1,0) -> 1 | G62: =IF(G$56=$D$6,1,0) -> 0 | H62: =IF(H$56=$D$6,1,0) -> 0 | I62: =IF(I$56=$D$6,1,0) -> 0 | J62: =IF(J$56=$D$6,1,0) -> 0 | L62: год договора с ВТБ
A63: 56 | B63: Новые банки уровня 1, с ВТБ | C63: банков | E63: =0 -> 0 | F63: =F62+F47 -> 1 | G63: =G62+G47 -> 0 | H63: =H62+H47 -> 1 | I63: =I62+I47 -> 0 | J63: =J62+J47 -> 1 | K63: =SUM(F63:J63) -> 3 | L63: ВТБ + другие
A64: 57 | B64: Банки уровня 1 с договором, на конец года | C64: банков | E64: =0 -> 0 | F64: =E64+F63 -> 1 | G64: =F64+G63 -> 1 | H64: =G64+H63 -> 2 | I64: =H64+I63 -> 2 | J64: =I64+J63 -> 3 | L64: накопленным итогом
A65: 58 | B65: Банки уровня 2 с договором, на конец года | C65: банков | E65: =0 -> 0 | F65: =E65+F48 -> 0 | G65: =F65+G48 -> 1 | H65: =G65+H48 -> 3 | I65: =H65+I48 -> 5 | J65: =I65+J48 -> 8 | L65: накопленным итогом
A66: 59 | B66: Банков с договором, на конец года | C66: банков | E66: =0 -> 0 | F66: =F64+F65 -> 1 | G66: =G64+G65 -> 2 | H66: =H64+H65 -> 5 | I66: =I64+I65 -> 7 | J66: =J64+J65 -> 11 | L66: уровень 1 + уровень 2
A67: 60 | B67: Новых договоров за год | C67: банков | F67: =F63+F48 -> 1 | G67: =G63+G48 -> 1 | H67: =H63+H48 -> 3 | I67: =I63+I48 -> 2 | J67: =J63+J48 -> 4 | K67: =SUM(F67:J67) -> 11
A68: 3. Выручка, млн ₽ без НДС
A69: 61 | B69: Подписка ВТБ | C69: млн ₽ | F69: =IF(F$56>$D$6,($D$8+$D$7*$D$9)*(1+$D$14)^(F$56-$D$6-1)*F57,0) -> 0 | G69: =IF(G$56>$D$6,($D$8+$D$7*$D$9)*(1+$D$14)^(G$56-$D$6-1)*G57,0) -> 15.75 | H69: =IF(H$56>$D$6,($D$8+$D$7*$D$9)*(1+$D$14)^(H$56-$D$6-1)*H57,0) -> 19.018125 | I69: =IF(I$56>$D$6,($D$8+$D$7*$D$9)*(1+$D$14)^(I$56-$D$6-1)*I57,0) -> 22.964386 | J69: =IF(J$56>$D$6,($D$8+$D$7*$D$9)*(1+$D$14)^(J$56-$D$6-1)*J57,0) -> 27.729496 | K69: =SUM(F69:J69) -> 85.462007 | L69: со следующего года после договора; растёт с новыми операциями; индексируется
A70: 62 | B70: Подписка других банков уровня 1 | C70: млн ₽ | F70: =($D$8+$D$39*$D$9)*F57*SUMPRODUCT($E$47:E$47,(1+$D$14)^(F$56-$E$56:E$56-1)) -> 0 | G70: =($D$8+$D$39*$D$9)*G57*SUMPRODUCT($E$47:F$47,(1+$D$14)^(G$56-$E$56:F$56-1)) -> 0 | H70: =($D$8+$D$39*$D$9)*H57*SUMPRODUCT($E$47:G$47,(1+$D$14)^(H$56-$E$56:G$56-1)) -> 0 | I70: =($D$8+$D$39*$D$9)*I57*SUMPRODUCT($E$47:H$47,(1+$D$14)^(I$56-$E$56:H$56-1)) -> 9.7871932 | J70: =($D$8+$D$39*$D$9)*J57*SUMPRODUCT($E$47:I$47,(1+$D$14)^(J$56-$E$56:I$56-1)) -> 11.818036 | K70: =SUM(F70:J70) -> 21.605229 | L70: по годам договоров: подписка × (1 + рост) ^ (лет после первого года) × индекс
A71: 63 | B71: Подписка банков уровня 2 | C71: млн ₽ | F71: =($D$10+$D$40*$D$9)*F57*SUMPRODUCT($E$48:E$48,(1+$D$14)^(F$56-$E$56:E$56-1)) -> 0 | G71: =($D$10+$D$40*$D$9)*G57*SUMPRODUCT($E$48:F$48,(1+$D$14)^(G$56-$E$56:F$56-1)) -> 0 | H71: =($D$10+$D$40*$D$9)*H57*SUMPRODUCT($E$48:G$48,(1+$D$14)^(H$56-$E$56:G$56-1)) -> 1.8087891 | I71: =($D$10+$D$40*$D$9)*I57*SUMPRODUCT($E$48:H$48,(1+$D$14)^(I$56-$E$56:H$56-1)) -> 5.9825698 | J71: =($D$10+$D$40*$D$9)*J57*SUMPRODUCT($E$48:I$48,(1+$D$14)^(J$56-$E$56:I$56-1)) -> 11.212333 | K71: =SUM(F71:J71) -> 19.003692 | L71: то же для уровня 2
A72: 64 | B72: Внедрение | C72: млн ₽ | F72: =(F63*$D$11+F48*$D$12)*F57 -> 8 | G72: =(G63*$D$11+G48*$D$12)*G57 -> 2.1 | H72: =(H63*$D$11+H48*$D$12)*H57 -> 13.23 | I72: =(I63*$D$11+I48*$D$12)*I57 -> 4.6305 | J72: =(J63*$D$11+J48*$D$12)*J57 -> 17.017087 | K72: =SUM(F72:J72) -> 44.977587 | L72: новые договоры × плата за внедрение × индекс
A73: 65 | B73: Подписка всего | C73: млн ₽ | F73: =F69+F70+F71 -> 0 | G73: =G69+G70+G71 -> 15.75 | H73: =H69+H70+H71 -> 20.826914 | I73: =I69+I70+I71 -> 38.734149 | J73: =J69+J70+J71 -> 50.759865 | K73: =SUM(F73:J73) -> 126.07093
A74: 66 | B74: Выручка | C74: млн ₽ | F74: =F73+F72 -> 8 | G74: =G73+G72 -> 17.85 | H74: =H73+H72 -> 34.056914 | I74: =I73+I72 -> 43.364649 | J74: =J73+J72 -> 67.776952 | K74: =SUM(F74:J74) -> 171.04852 | L74: подписка + внедрение
A75: 67 | B75: Годовая подписка на конец года (ARR) | C75: млн ₽ в год | F75: =IF(F$56>=$D$6,($D$8+$D$7*$D$9)*(1+$D$14)^(F$56-$D$6)*F57,0)+($D$8+$D$39*$D$9)*F57*SUMPRODUCT($E$47:F$47,(1+$D$14)^(F$56-$E$56:F$56))+($D$10+$D$40*$D$9)*F57*SUMPRODUCT($E$48:F$48,(1+$D$14)^(F$56-$E$56:F$56)) -> 15 | G75: =IF(G$56>=$D$6,($D$8+$D$7*$D$9)*(1+$D$14)^(G$56-$D$6)*G57,0)+($D$8+$D$39*$D$9)*G57*SUMPRODUCT($E$47:G$47,(1+$D$14)^(G$56-$E$56:G$56))+($D$10+$D$40*$D$9)*G57*SUMPRODUCT($E$48:G$48,(1+$D$14)^(G$56-$E$56:G$56)) -> 19.835156 | H75: =IF(H$56>=$D$6,($D$8+$D$7*$D$9)*(1+$D$14)^(H$56-$D$6)*H57,0)+($D$8+$D$39*$D$9)*H57*SUMPRODUCT($E$47:H$47,(1+$D$14)^(H$56-$E$56:H$56))+($D$10+$D$40*$D$9)*H57*SUMPRODUCT($E$48:H$48,(1+$D$14)^(H$56-$E$56:H$56)) -> 36.889666 | I75: =IF(I$56>=$D$6,($D$8+$D$7*$D$9)*(1+$D$14)^(I$56-$D$6)*I57,0)+($D$8+$D$39*$D$9)*I57*SUMPRODUCT($E$47:I$47,(1+$D$14)^(I$56-$E$56:I$56))+($D$10+$D$40*$D$9)*I57*SUMPRODUCT($E$48:I$48,(1+$D$14)^(I$56-$E$56:I$56)) -> 48.342728 | J75: =IF(J$56>=$D$6,($D$8+$D$7*$D$9)*(1+$D$14)^(J$56-$D$6)*J57,0)+($D$8+$D$39*$D$9)*J57*SUMPRODUCT($E$47:J$47,(1+$D$14)^(J$56-$E$56:J$56))+($D$10+$D$40*$D$9)*J57*SUMPRODUCT($E$48:J$48,(1+$D$14)^(J$56-$E$56:J$56)) -> 74.632967 | L75: подписка всех банков с договором в ценах года
A76: 4. Затраты, млн ₽
A77: 68 | B77: Численность команды | C77: ставок | E77: =E49+E50+E51+E52+E53+E54 -> 2 | F77: =F49+F50+F51+F52+F53+F54 -> 4 | G77: =G49+G50+G51+G52+G53+G54 -> 5 | H77: =H49+H50+H51+H52+H53+H54 -> 6 | I77: =I49+I50+I51+I52+I53+I54 -> 7 | J77: =J49+J50+J51+J52+J53+J54 -> 8 | L77: сумма по ролям
A78: 69 | B78: Новые сотрудники | C78: ставок | F78: =MAX(0,F77-E77) -> 2 | G78: =MAX(0,G77-F77) -> 1 | H78: =MAX(0,H77-G77) -> 1 | I78: =MAX(0,I77-H77) -> 1 | J78: =MAX(0,J77-I77) -> 1 | L78: прирост численности
A79: 70 | B79: Годовой оклад на ставку: Основатели: продукт и продажи, архитектура правил | C79: млн ₽ | F79: =$D$41*12/1000*F59 -> 2.4 | G79: =$D$41*12/1000*G59 -> 2.568 | H79: =$D$41*12/1000*H59 -> 2.74776 | I79: =$D$41*12/1000*I59 -> 2.9401032 | J79: =$D$41*12/1000*J59 -> 3.1459104 | L79: оклад × 12 × индекс
A80: 71 | B80: Годовой оклад на ставку: Разработчики | C80: млн ₽ | F80: =$D$42*12/1000*F59 -> 3.36 | G80: =$D$42*12/1000*G59 -> 3.5952 | H80: =$D$42*12/1000*H59 -> 3.846864 | I80: =$D$42*12/1000*I59 -> 4.1161445 | J80: =$D$42*12/1000*J59 -> 4.4042746 | L80: оклад × 12 × индекс
A81: 72 | B81: Годовой оклад на ставку: Юрист-аналитик правил | C81: млн ₽ | F81: =$D$43*12/1000*F59 -> 2.76 | G81: =$D$43*12/1000*G59 -> 2.9532 | H81: =$D$43*12/1000*H59 -> 3.159924 | I81: =$D$43*12/1000*I59 -> 3.3811187 | J81: =$D$43*12/1000*J59 -> 3.617797 | L81: оклад × 12 × индекс
A82: 73 | B82: Годовой оклад на ставку: Инженеры внедрения и поддержки | C82: млн ₽ | F82: =$D$44*12/1000*F59 -> 2.64 | G82: =$D$44*12/1000*G59 -> 2.8248 | H82: =$D$44*12/1000*H59 -> 3.022536 | I82: =$D$44*12/1000*I59 -> 3.2341135 | J82: =$D$44*12/1000*J59 -> 3.4605015 | L82: оклад × 12 × индекс
A83: 74 | B83: Годовой оклад на ставку: Инженер качества и ИБ | C83: млн ₽ | F83: =$D$45*12/1000*F59 -> 3 | G83: =$D$45*12/1000*G59 -> 3.21 | H83: =$D$45*12/1000*H59 -> 3.4347 | I83: =$D$45*12/1000*I59 -> 3.675129 | J83: =$D$45*12/1000*J59 -> 3.932388 | L83: оклад × 12 × индекс
A84: 75 | B84: Годовой оклад на ставку: Менеджер по работе с банками | C84: млн ₽ | F84: =$D$46*12/1000*F59 -> 2.64 | G84: =$D$46*12/1000*G59 -> 2.8248 | H84: =$D$46*12/1000*H59 -> 3.022536 | I84: =$D$46*12/1000*I59 -> 3.2341135 | J84: =$D$46*12/1000*J59 -> 3.4605015 | L84: оклад × 12 × индекс
A85: 76 | B85: Фонд оплаты труда: Основатели: продукт и продажи, архитектура правил | C85: млн ₽ | F85: =F49*F79 -> 4.8 | G85: =G49*G79 -> 5.136 | H85: =H49*H79 -> 5.49552 | I85: =I49*I79 -> 5.8802064 | J85: =J49*J79 -> 6.2918208 | K85: =SUM(F85:J85) -> 27.603547 | L85: ставки × годовой оклад
A86: 77 | B86: Фонд оплаты труда: Разработчики | C86: млн ₽ | F86: =F50*F80 -> 3.36 | G86: =G50*G80 -> 3.5952 | H86: =H50*H80 -> 3.846864 | I86: =I50*I80 -> 8.232289 | J86: =J50*J80 -> 8.8085492 | K86: =SUM(F86:J86) -> 27.842902 | L86: ставки × годовой оклад
A87: 78 | B87: Фонд оплаты труда: Юрист-аналитик правил | C87: млн ₽ | F87: =F51*F81 -> 2.76 | G87: =G51*G81 -> 2.9532 | H87: =H51*H81 -> 3.159924 | I87: =I51*I81 -> 3.3811187 | J87: =J51*J81 -> 3.617797 | K87: =SUM(F87:J87) -> 15.87204 | L87: ставки × годовой оклад
A88: 79 | B88: Фонд оплаты труда: Инженеры внедрения и поддержки | C88: млн ₽ | F88: =F52*F82 -> 0 | G88: =G52*G82 -> 2.8248 | H88: =H52*H82 -> 3.022536 | I88: =I52*I82 -> 3.2341135 | J88: =J52*J82 -> 3.4605015 | K88: =SUM(F88:J88) -> 12.541951 | L88: ставки × годовой оклад
A89: 80 | B89: Фонд оплаты труда: Инженер качества и ИБ | C89: млн ₽ | F89: =F53*F83 -> 0 | G89: =G53*G83 -> 0 | H89: =H53*H83 -> 3.4347 | I89: =I53*I83 -> 3.675129 | J89: =J53*J83 -> 3.932388 | K89: =SUM(F89:J89) -> 11.042217 | L89: ставки × годовой оклад
A90: 81 | B90: Фонд оплаты труда: Менеджер по работе с банками | C90: млн ₽ | F90: =F54*F84 -> 0 | G90: =G54*G84 -> 0 | H90: =H54*H84 -> 0 | I90: =I54*I84 -> 0 | J90: =J54*J84 -> 3.4605015 | K90: =SUM(F90:J90) -> 3.4605015 | L90: ставки × годовой оклад
A91: 82 | B91: Фонд оплаты труда | C91: млн ₽ | F91: =F85+F86+F87+F88+F89+F90 -> 10.92 | G91: =G85+G86+G87+G88+G89+G90 -> 14.5092 | H91: =H85+H86+H87+H88+H89+H90 -> 18.959544 | I91: =I85+I86+I87+I88+I89+I90 -> 24.402857 | J91: =J85+J86+J87+J88+J89+J90 -> 29.571558 | K91: =SUM(F91:J91) -> 98.363159
A92: 83 | B92: Страховые взносы | C92: млн ₽ | F92: =F49*(MIN(F79,F60)*$D$16+MAX(0,F79-F60)*$D$17+F79*$D$18)+F50*(MIN(F80,F60)*$D$16+MAX(0,F80-F60)*$D$17+F80*$D$18)+F51*(MIN(F81,F60)*$D$16+MAX(0,F81-F60)*$D$17+F81*$D$18)+F52*(MIN(F82,F60)*$D$16+MAX(0,F82-F60)*$D$17+F82*$D$18)+F53*(MIN(F83,F60)*$D$16+MAX(0,F83-F60)*$D$17+F83*$D$18)+F54*(MIN(F84,F60)*$D$16+MAX(0,F84-F60)*$D$17+F84*$D$18) -> 1.6492817 | G92: =G49*(MIN(G79,G60)*$D$16+MAX(0,G79-G60)*$D$17+G79*$D$18)+G50*(MIN(G80,G60)*$D$16+MAX(0,G80-G60)*$D$17+G80*$D$18)+G51*(MIN(G81,G60)*$D$16+MAX(0,G81-G60)*$D$17+G81*$D$18)+G52*(MIN(G82,G60)*$D$16+MAX(0,G82-G60)*$D$17+G82*$D$18)+G53*(MIN(G83,G60)*$D$16+MAX(0,G83-G60)*$D$17+G83*$D$18)+G54*(MIN(G84,G60)*$D$16+MAX(0,G84-G60)*$D$17+G84*$D$18) -> 2.1964818 | H92: =H49*(MIN(H79,H60)*$D$16+MAX(0,H79-H60)*$D$17+H79*$D$18)+H50*(MIN(H80,H60)*$D$16+MAX(0,H80-H60)*$D$17+H80*$D$18)+H51*(MIN(H81,H60)*$D$16+MAX(0,H81-H60)*$D$17+H81*$D$18)+H52*(MIN(H82,H60)*$D$16+MAX(0,H82-H60)*$D$17+H82*$D$18)+H53*(MIN(H83,H60)*$D$16+MAX(0,H83-H60)*$D$17+H83*$D$18)+H54*(MIN(H84,H60)*$D$16+MAX(0,H84-H60)*$D$17+H84*$D$18) -> 2.8748812 | I92: =I49*(MIN(I79,I60)*$D$16+MAX(0,I79-I60)*$D$17+I79*$D$18)+I50*(MIN(I80,I60)*$D$16+MAX(0,I80-I60)*$D$17+I80*$D$18)+I51*(MIN(I81,I60)*$D$16+MAX(0,I81-I60)*$D$17+I81*$D$18)+I52*(MIN(I82,I60)*$D$16+MAX(0,I82-I60)*$D$17+I82*$D$18)+I53*(MIN(I83,I60)*$D$16+MAX(0,I83-I60)*$D$17+I83*$D$18)+I54*(MIN(I84,I60)*$D$16+MAX(0,I84-I60)*$D$17+I84*$D$18) -> 3.6998735 | J92: =J49*(MIN(J79,J60)*$D$16+MAX(0,J79-J60)*$D$17+J79*$D$18)+J50*(MIN(J80,J60)*$D$16+MAX(0,J80-J60)*$D$17+J80*$D$18)+J51*(MIN(J81,J60)*$D$16+MAX(0,J81-J60)*$D$17+J81*$D$18)+J52*(MIN(J82,J60)*$D$16+MAX(0,J82-J60)*$D$17+J82*$D$18)+J53*(MIN(J83,J60)*$D$16+MAX(0,J83-J60)*$D$17+J83*$D$18)+J54*(MIN(J84,J60)*$D$16+MAX(0,J84-J60)*$D$17+J84*$D$18) -> 4.4908592 | K92: =SUM(F92:J92) -> 14.911377 | L92: по каждой роли: в пределах базы × льготный тариф + сверх базы × 7,6 % + травматизм
A93: 84 | B93: Первый договор (1 — в этом году) | F93: =IF(AND(F66>0,E66=0),1,0) -> 1 | G93: =IF(AND(G66>0,F66=0),1,0) -> 0 | H93: =IF(AND(H66>0,G66=0),1,0) -> 0 | I93: =IF(AND(I66>0,H66=0),1,0) -> 0 | J93: =IF(AND(J66>0,I66=0),1,0) -> 0
A94: 85 | B94: Оценка ИБ (анализ уязвимостей) | C94: млн ₽ | F94: =(F93*$D$21+IF(E66>0,1,0)*$D$22)*F58 -> 2.5 | G94: =(G93*$D$21+IF(F66>0,1,0)*$D$22)*G58 -> 1.05 | H94: =(H93*$D$21+IF(G66>0,1,0)*$D$22)*H58 -> 1.1025 | I94: =(I93*$D$21+IF(H66>0,1,0)*$D$22)*I58 -> 1.157625 | J94: =(J93*$D$21+IF(I66>0,1,0)*$D$22)*J58 -> 1.2155063 | K94: =SUM(F94:J94) -> 7.0256312 | L94: первая — в год первого договора, дальше — ежегодно
A95: 86 | B95: Внешняя юридическая экспертиза правил | C95: млн ₽ | F95: =$D$23*F58 -> 0.6 | G95: =$D$23*G58 -> 0.63 | H95: =$D$23*H58 -> 0.6615 | I95: =$D$23*I58 -> 0.694575 | J95: =$D$23*J58 -> 0.72930375 | K95: =SUM(F95:J95) -> 3.3153787
A96: 87 | B96: Инфраструктура и инструменты | C96: млн ₽ | F96: =$D$24*F77*F58 -> 0.6 | G96: =$D$24*G77*G58 -> 0.7875 | H96: =$D$24*H77*H58 -> 0.99225 | I96: =$D$24*I77*I58 -> 1.2155063 | J96: =$D$24*J77*J58 -> 1.4586075 | K96: =SUM(F96:J96) -> 5.0538637 | L96: на сотрудника
A97: 88 | B97: Продажи и маркетинг | C97: млн ₽ | F97: =($D$25+$D$26*F67)*F58 -> 1.4 | G97: =($D$25+$D$26*G67)*G58 -> 1.47 | H97: =($D$25+$D$26*H67)*H58 -> 2.4255 | I97: =($D$25+$D$26*I67)*I58 -> 2.083725 | J97: =($D$25+$D$26*J67)*J58 -> 3.1603163 | K97: =SUM(F97:J97) -> 10.539541 | L97: постоянная часть + на договор
A98: 89 | B98: Административные | C98: млн ₽ | F98: =($D$27+$D$28*F77)*F58 -> 1.6 | G98: =($D$27+$D$28*G77)*G58 -> 1.785 | H98: =($D$27+$D$28*H77)*H58 -> 1.9845 | I98: =($D$27+$D$28*I77)*I58 -> 2.1994875 | J98: =($D$27+$D$28*J77)*J58 -> 2.4310125 | K98: =SUM(F98:J98) -> 10 | L98: постоянная часть + на сотрудника
A99: 90 | B99: Оборудование | C99: млн ₽ | F99: =$D$29*F78*F58 -> 0.5 | G99: =$D$29*G78*G58 -> 0.2625 | H99: =$D$29*H78*H58 -> 0.275625 | I99: =$D$29*I78*I58 -> 0.28940625 | J99: =$D$29*J78*J58 -> 0.30387656 | K99: =SUM(F99:J99) -> 1.6314078 | L99: на нового сотрудника
A100: 91 | B100: Регистрация, аккредитация, реестр ПО | C100: млн ₽ | F100: =IF(F$56=$F$56,$D$30,0) -> 0.3 | G100: =IF(G$56=$F$56,$D$30,0) -> 0 | H100: =IF(H$56=$F$56,$D$30,0) -> 0 | I100: =IF(I$56=$F$56,$D$30,0) -> 0 | J100: =IF(J$56=$F$56,$D$30,0) -> 0 | K100: =SUM(F100:J100) -> 0.3 | L100: только 2027 год
A101: 92 | B101: Затраты до резерва | C101: млн ₽ | F101: =F91+F92+F94+F95+F96+F97+F98+F99+F100 -> 20.069282 | G101: =G91+G92+G94+G95+G96+G97+G98+G99+G100 -> 22.690682 | H101: =H91+H92+H94+H95+H96+H97+H98+H99+H100 -> 29.2763 | I101: =I91+I92+I94+I95+I96+I97+I98+I99+I100 -> 35.743055 | J101: =J91+J92+J94+J95+J96+J97+J98+J99+J100 -> 43.36104 | K101: =SUM(F101:J101) -> 151.14036
...

Sheet Оптимистичный
A1: Расчёт: оптимистичный сценарий
A2: Входы — зелёные ссылки на «Допущения», «План» и «Рынок»; в строке одна формула для всех лет; млн ₽ без НДС
A4: № | B4: Показатель | C4: Единица | D4: Константа | E4: 2026 | F4: 2027 | G4: 2028 | H4: 2029 | I4: 2030 | J4: 2031 | K4: Итого 2027–2031 | L4: Как считается
A5: Входные данные (ссылки на «Допущения», «План», «Рынок»)
A6: 1 | B6: Год договора с ВТБ | C6: год | D6: =Допущения!$F$49 -> 2027
A7: 2 | B7: Клиенты-бизнесы ВТБ | C7: млн | D7: =Допущения!$F$7 -> 1.8
A8: 3 | B8: Подписка уровня 1: постоянная часть | C8: млн ₽ в год | D8: =Допущения!$F$42 -> 8
A9: 4 | B9: Плата за активного клиента-бизнес | C9: ₽ в год | D9: =Допущения!$F$43 -> 7
A10: 5 | B10: Подписка уровня 2: постоянная часть | C10: млн ₽ в год | D10: =Допущения!$F$44 -> 2
A11: 6 | B11: Внедрение, уровень 1 | C11: млн ₽ | D11: =Допущения!$F$45 -> 10
A12: 7 | B12: Внедрение, уровень 2 | C12: млн ₽ | D12: =Допущения!$F$46 -> 2.5
A13: 8 | B13: Индексация цен | C13: доля в год | D13: =Допущения!$F$47 -> 0.06
A14: 9 | B14: Рост подписки за счёт новых операций | C14: доля в год | D14: =Допущения!$F$48 -> 0.25
A15: 10 | B15: Рост окладов | C15: доля в год | D15: =Допущения!$F$51 -> 0.07
A16: 11 | B16: Взносы в пределах базы | C16: доля | D16: =Допущения!$F$52 -> 0.15
A17: 12 | B17: Взносы сверх базы | C17: доля | D17: =Допущения!$F$53 -> 0.076
A18: 13 | B18: Взнос на травматизм | C18: доля | D18: =Допущения!$F$54 -> 0.002
A19: 14 | B19: Предельная база взносов 2026 | C19: млн ₽ в год | D19: =Допущения!$F$55 -> 2.979
A20: 15 | B20: Рост базы | C20: доля в год | D20: =Допущения!$F$56 -> 0.08
A21: 16 | B21: Анализ уязвимостей по ОУД4 — первый | C21: млн ₽ | D21: =Допущения!$F$58 -> 2.5
A22: 17 | B22: Повторная оценка релизов | C22: млн ₽ в год | D22: =Допущения!$F$59 -> 1
A23: 18 | B23: Внешняя юридическая экспертиза правил | C23: млн ₽ в год | D23: =Допущения!$F$60 -> 0.8
A24: 19 | B24: Инфраструктура на сотрудника | C24: млн ₽ в год | D24: =Допущения!$F$61 -> 0.18
A25: 20 | B25: Продажи: постоянная часть | C25: млн ₽ в год | D25: =Допущения!$F$62 -> 1.5
A26: 21 | B26: Продажи: на договор | C26: млн ₽ | D26: =Допущения!$F$63 -> 0.5
A27: 22 | B27: Административные: постоянная часть | C27: млн ₽ в год | D27: =Допущения!$F$64 -> 1.5
A28: 23 | B28: Административные: на сотрудника | C28: млн ₽ в год | D28: =Допущения!$F$65 -> 0.12
A29: 24 | B29: Оборудование на нового сотрудника | C29: млн ₽ | D29: =Допущения!$F$66 -> 0.25
A30: 25 | B30: Регистрация, аккредитация, реестр ПО | C30: млн ₽ | D30: =Допущения!$F$67 -> 0.3
A31: 26 | B31: Рост прочих затрат | C31: доля в год | D31: =Допущения!$F$68 -> 0.05
A32: 27 | B32: Резерв | C32: доля затрат | D32: =Допущения!$F$69 -> 0.1
A33: 28 | B33: Налог на прибыль | C33: доля | D33: =Допущения!$F$71 -> 0.05
A34: 29 | B34: Перенос убытка: доля прибыли | C34: доля | D34: =Допущения!$F$72 -> 0.5
A35: 30 | B35: Срок оплаты банками | C35: дней | D35: =Допущения!$F$73 -> 60
A36: 31 | B36: Ставка дисконтирования | C36: доля | D36: =Допущения!$F$74 -> 0.3
A37: 32 | B37: Рост после 2031 года | C37: доля в год | D37: =Допущения!$F$75 -> 0.04
A38: 33 | B38: Запас к финансированию | C38: доля | D38: =Допущения!$F$76 -> 0.2
A39: 34 | B39: Клиентов у банка уровня 1, кроме ВТБ | C39: млн | D39: =Рынок!$F$30 -> 0.49090909 | L39: лист «Рынок»
A40: 35 | B40: Клиентов у банка уровня 2 | C40: млн | D40: =Рынок!$F$31 -> 0.028125 | L40: лист «Рынок»
A41: 36 | B41: Оклад: Основатели: продукт и продажи, архитектура правил | C41: тыс. ₽ в месяц | D41: =План!$D$28 -> 200 | L41: лист «План»
A42: 37 | B42: Оклад: Разработчики | C42: тыс. ₽ в месяц | D42: =План!$D$29 -> 280 | L42: лист «План»
A43: 38 | B43: Оклад: Юрист-аналитик правил | C43: тыс. ₽ в месяц | D43: =План!$D$30 -> 230 | L43: лист «План»
A44: 39 | B44: Оклад: Инженеры внедрения и поддержки | C44: тыс. ₽ в месяц | D44: =План!$D$31 -> 220 | L44: лист «План»
A45: 40 | B45: Оклад: Инженер качества и ИБ | C45: тыс. ₽ в месяц | D45: =План!$D$32 -> 250 | L45: лист «План»
A46: 41 | B46: Оклад: Менеджер по работе с банками | C46: тыс. ₽ в месяц | D46: =План!$D$33 -> 220 | L46: лист «План»
A47: 42 | B47: Новые банки уровня 1 (кроме ВТБ) | C47: банков | E47: =План!E26 -> 0 | F47: =План!F26 -> 0 | G47: =План!G26 -> 0 | H47: =План!H26 -> 1 | I47: =План!I26 -> 1 | J47: =План!J26 -> 1 | K47: =SUM(F47:J47) -> 3 | L47: лист «План»
A48: 43 | B48: Новые банки уровня 2 | C48: банков | E48: =План!E27 -> 0 | F48: =План!F27 -> 0 | G48: =План!G27 -> 2 | H48: =План!H27 -> 3 | I48: =План!I27 -> 4 | J48: =План!J27 -> 5 | K48: =SUM(F48:J48) -> 14 | L48: лист «План»
A49: 44 | B49: Численность: Основатели: продукт и продажи, архитектура правил | C49: ставок | E49: =План!E28 -> 2 | F49: =План!F28 -> 2 | G49: =План!G28 -> 2 | H49: =План!H28 -> 2 | I49: =План!I28 -> 2 | J49: =План!J28 -> 2 | L49: лист «План»
A50: 45 | B50: Численность: Разработчики | C50: ставок | E50: =План!E29 -> 0 | F50: =План!F29 -> 1 | G50: =План!G29 -> 2 | H50: =План!H29 -> 3 | I50: =План!I29 -> 3 | J50: =План!J29 -> 4 | L50: лист «План»
A51: 46 | B51: Численность: Юрист-аналитик правил | C51: ставок | E51: =План!E30 -> 0 | F51: =План!F30 -> 1 | G51: =План!G30 -> 1 | H51: =План!H30 -> 1 | I51: =План!I30 -> 2 | J51: =План!J30 -> 2 | L51: лист «План»
A52: 47 | B52: Численность: Инженеры внедрения и поддержки | C52: ставок | E52: =План!E31 -> 0 | F52: =План!F31 -> 0 | G52: =План!G31 -> 1 | H52: =План!H31 -> 2 | I52: =План!I31 -> 3 | J52: =План!J31 -> 3 | L52: лист «План»
A53: 48 | B53: Численность: Инженер качества и ИБ | C53: ставок | E53: =План!E32 -> 0 | F53: =План!F32 -> 0 | G53: =План!G32 -> 1 | H53: =План!H32 -> 1 | I53: =План!I32 -> 1 | J53: =План!J32 -> 2 | L53: лист «План»
A54: 49 | B54: Численность: Менеджер по работе с банками | C54: ставок | E54: =План!E33 -> 0 | F54: =План!F33 -> 0 | G54: =План!G33 -> 0 | H54: =План!H33 -> 1 | I54: =План!I33 -> 1 | J54: =План!J33 -> 2 | L54: лист «План»
A55: 1. Время
A56: 50 | B56: Год | E56: =Допущения!$D$3 -> 2026 | F56: =E56+1 -> 2027 | G56: =F56+1 -> 2028 | H56: =G56+1 -> 2029 | I56: =H56+1 -> 2030 | J56: =I56+1 -> 2031 | L56: предыдущий + 1
A57: 51 | B57: Индекс цен к 2027 году | C57: раз | F57: =(1+$D$13)^(F$56-$E$56-1) -> 1 | G57: =(1+$D$13)^(G$56-$E$56-1) -> 1.06 | H57: =(1+$D$13)^(H$56-$E$56-1) -> 1.1236 | I57: =(1+$D$13)^(I$56-$E$56-1) -> 1.191016 | J57: =(1+$D$13)^(J$56-$E$56-1) -> 1.262477 | L57: (1 + индексация) ^ (год − 2027)
A58: 52 | B58: Индекс прочих затрат к 2027 году | C58: раз | F58: =(1+$D$31)^(F$56-$E$56-1) -> 1 | G58: =(1+$D$31)^(G$56-$E$56-1) -> 1.05 | H58: =(1+$D$31)^(H$56-$E$56-1) -> 1.1025 | I58: =(1+$D$31)^(I$56-$E$56-1) -> 1.157625 | J58: =(1+$D$31)^(J$56-$E$56-1) -> 1.2155063 | L58: то же для затрат
A59: 53 | B59: Индекс окладов к 2027 году | C59: раз | F59: =(1+$D$15)^(F$56-$E$56-1) -> 1 | G59: =(1+$D$15)^(G$56-$E$56-1) -> 1.07 | H59: =(1+$D$15)^(H$56-$E$56-1) -> 1.1449 | I59: =(1+$D$15)^(I$56-$E$56-1) -> 1.225043 | J59: =(1+$D$15)^(J$56-$E$56-1) -> 1.310796 | L59: то же для окладов
A60: 54 | B60: Предельная база взносов | C60: млн ₽ в год | F60: =$D$19*(1+$D$20)^(F$56-$E$56) -> 3.21732 | G60: =$D$19*(1+$D$20)^(G$56-$E$56) -> 3.4747056 | H60: =$D$19*(1+$D$20)^(H$56-$E$56) -> 3.752682 | I60: =$D$19*(1+$D$20)^(I$56-$E$56) -> 4.0528966 | J60: =$D$19*(1+$D$20)^(J$56-$E$56) -> 4.3771283 | L60: база 2026 × (1 + рост) ^ (год − 2026)
A61: 2. Договоры
A62: 55 | B62: Договор с ВТБ (1 — в этом году) | C62: банков | F62: =IF(F$56=$D$6,1,0) -> 1 | G62: =IF(G$56=$D$6,1,0) -> 0 | H62: =IF(H$56=$D$6,1,0) -> 0 | I62: =IF(I$56=$D$6,1,0) -> 0 | J62: =IF(J$56=$D$6,1,0) -> 0 | L62: год договора с ВТБ
A63: 56 | B63: Новые банки уровня 1, с ВТБ | C63: банков | E63: =0 -> 0 | F63: =F62+F47 -> 1 | G63: =G62+G47 -> 0 | H63: =H62+H47 -> 1 | I63: =I62+I47 -> 1 | J63: =J62+J47 -> 1 | K63: =SUM(F63:J63) -> 4 | L63: ВТБ + другие
A64: 57 | B64: Банки уровня 1 с договором, на конец года | C64: банков | E64: =0 -> 0 | F64: =E64+F63 -> 1 | G64: =F64+G63 -> 1 | H64: =G64+H63 -> 2 | I64: =H64+I63 -> 3 | J64: =I64+J63 -> 4 | L64: накопленным итогом
A65: 58 | B65: Банки уровня 2 с договором, на конец года | C65: банков | E65: =0 -> 0 | F65: =E65+F48 -> 0 | G65: =F65+G48 -> 2 | H65: =G65+H48 -> 5 | I65: =H65+I48 -> 9 | J65: =I65+J48 -> 14 | L65: накопленным итогом
A66: 59 | B66: Банков с договором, на конец года | C66: банков | E66: =0 -> 0 | F66: =F64+F65 -> 1 | G66: =G64+G65 -> 3 | H66: =H64+H65 -> 7 | I66: =I64+I65 -> 12 | J66: =J64+J65 -> 18 | L66: уровень 1 + уровень 2
A67: 60 | B67: Новых договоров за год | C67: банков | F67: =F63+F48 -> 1 | G67: =G63+G48 -> 2 | H67: =H63+H48 -> 4 | I67: =I63+I48 -> 5 | J67: =J63+J48 -> 6 | K67: =SUM(F67:J67) -> 18
A68: 3. Выручка, млн ₽ без НДС
A69: 61 | B69: Подписка ВТБ | C69: млн ₽ | F69: =IF(F$56>$D$6,($D$8+$D$7*$D$9)*(1+$D$14)^(F$56-$D$6-1)*F57,0) -> 0 | G69: =IF(G$56>$D$6,($D$8+$D$7*$D$9)*(1+$D$14)^(G$56-$D$6-1)*G57,0) -> 21.836 | H69: =IF(H$56>$D$6,($D$8+$D$7*$D$9)*(1+$D$14)^(H$56-$D$6-1)*H57,0) -> 28.9327 | I69: =IF(I$56>$D$6,($D$8+$D$7*$D$9)*(1+$D$14)^(I$56-$D$6-1)*I57,0) -> 38.335828 | J69: =IF(J$56>$D$6,($D$8+$D$7*$D$9)*(1+$D$14)^(J$56-$D$6-1)*J57,0) -> 50.794971 | K69: =SUM(F69:J69) -> 139.8995 | L69: со следующего года после договора; растёт с новыми операциями; индексируется
A70: 62 | B70: Подписка других банков уровня 1 | C70: млн ₽ | F70: =($D$8+$D$39*$D$9)*F57*SUMPRODUCT($E$47:E$47,(1+$D$14)^(F$56-$E$56:E$56-1)) -> 0 | G70: =($D$8+$D$39*$D$9)*G57*SUMPRODUCT($E$47:F$47,(1+$D$14)^(G$56-$E$56:F$56-1)) -> 0 | H70: =($D$8+$D$39*$D$9)*H57*SUMPRODUCT($E$47:G$47,(1+$D$14)^(H$56-$E$56:G$56-1)) -> 0 | I70: =($D$8+$D$39*$D$9)*I57*SUMPRODUCT($E$47:H$47,(1+$D$14)^(I$56-$E$56:H$56-1)) -> 13.620892 | J70: =($D$8+$D$39*$D$9)*J57*SUMPRODUCT($E$47:I$47,(1+$D$14)^(J$56-$E$56:I$56-1)) -> 32.485828 | K70: =SUM(F70:J70) -> 46.10672 | L70: по годам договоров: подписка × (1 + рост) ^ (лет после первого года) × индекс
A71: 63 | B71: Подписка банков уровня 2 | C71: млн ₽ | F71: =($D$10+$D$40*$D$9)*F57*SUMPRODUCT($E$48:E$48,(1+$D$14)^(F$56-$E$56:E$56-1)) -> 0 | G71: =($D$10+$D$40*$D$9)*G57*SUMPRODUCT($E$48:F$48,(1+$D$14)^(G$56-$E$56:F$56-1)) -> 0 | H71: =($D$10+$D$40*$D$9)*H57*SUMPRODUCT($E$48:G$48,(1+$D$14)^(H$56-$E$56:G$56-1)) -> 4.9368175 | I71: =($D$10+$D$40*$D$9)*I57*SUMPRODUCT($E$48:H$48,(1+$D$14)^(I$56-$E$56:H$56-1)) -> 14.390823 | J71: =($D$10+$D$40*$D$9)*J57*SUMPRODUCT($E$48:I$48,(1+$D$14)^(J$56-$E$56:I$56-1)) -> 30.161857 | K71: =SUM(F71:J71) -> 49.489497 | L71: то же для уровня 2
A72: 64 | B72: Внедрение | C72: млн ₽ | F72: =(F63*$D$11+F48*$D$12)*F57 -> 10 | G72: =(G63*$D$11+G48*$D$12)*G57 -> 5.3 | H72: =(H63*$D$11+H48*$D$12)*H57 -> 19.663 | I72: =(I63*$D$11+I48*$D$12)*I57 -> 23.82032 | J72: =(J63*$D$11+J48*$D$12)*J57 -> 28.405732 | K72: =SUM(F72:J72) -> 87.189052 | L72: новые договоры × плата за внедрение × индекс
A73: 65 | B73: Подписка всего | C73: млн ₽ | F73: =F69+F70+F71 -> 0 | G73: =G69+G70+G71 -> 21.836 | H73: =H69+H70+H71 -> 33.869518 | I73: =I69+I70+I71 -> 66.347543 | J73: =J69+J70+J71 -> 113.44266 | K73: =SUM(F73:J73) -> 235.49572
A74: 66 | B74: Выручка | C74: млн ₽ | F74: =F73+F72 -> 10 | G74: =G73+G72 -> 27.136 | H74: =H73+H72 -> 53.532517 | I74: =I73+I72 -> 90.167863 | J74: =J73+J72 -> 141.84839 | K74: =SUM(F74:J74) -> 322.68477 | L74: подписка + внедрение
A75: 67 | B75: Годовая подписка на конец года (ARR) | C75: млн ₽ в год | F75: =IF(F$56>=$D$6,($D$8+$D$7*$D$9)*(1+$D$14)^(F$56-$D$6)*F57,0)+($D$8+$D$39*$D$9)*F57*SUMPRODUCT($E$47:F$47,(1+$D$14)^(F$56-$E$56:F$56))+($D$10+$D$40*$D$9)*F57*SUMPRODUCT($E$48:F$48,(1+$D$14)^(F$56-$E$56:F$56)) -> 20.6 | G75: =IF(G$56>=$D$6,($D$8+$D$7*$D$9)*(1+$D$14)^(G$56-$D$6)*G57,0)+($D$8+$D$39*$D$9)*G57*SUMPRODUCT($E$47:G$47,(1+$D$14)^(G$56-$E$56:G$56))+($D$10+$D$40*$D$9)*G57*SUMPRODUCT($E$48:G$48,(1+$D$14)^(G$56-$E$56:G$56)) -> 31.952375 | H75: =IF(H$56>=$D$6,($D$8+$D$7*$D$9)*(1+$D$14)^(H$56-$D$6)*H57,0)+($D$8+$D$39*$D$9)*H57*SUMPRODUCT($E$47:H$47,(1+$D$14)^(H$56-$E$56:H$56))+($D$10+$D$40*$D$9)*H57*SUMPRODUCT($E$48:H$48,(1+$D$14)^(H$56-$E$56:H$56)) -> 62.592021 | I75: =IF(I$56>=$D$6,($D$8+$D$7*$D$9)*(1+$D$14)^(I$56-$D$6)*I57,0)+($D$8+$D$39*$D$9)*I57*SUMPRODUCT($E$47:I$47,(1+$D$14)^(I$56-$E$56:I$56))+($D$10+$D$40*$D$9)*I57*SUMPRODUCT($E$48:I$48,(1+$D$14)^(I$56-$E$56:I$56)) -> 107.02137 | J75: =IF(J$56>=$D$6,($D$8+$D$7*$D$9)*(1+$D$14)^(J$56-$D$6)*J57,0)+($D$8+$D$39*$D$9)*J57*SUMPRODUCT($E$47:J$47,(1+$D$14)^(J$56-$E$56:J$56))+($D$10+$D$40*$D$9)*J57*SUMPRODUCT($E$48:J$48,(1+$D$14)^(J$56-$E$56:J$56)) -> 170.10899 | L75: подписка всех банков с договором в ценах года
A76: 4. Затраты, млн ₽
A77: 68 | B77: Численность команды | C77: ставок | E77: =E49+E50+E51+E52+E53+E54 -> 2 | F77: =F49+F50+F51+F52+F53+F54 -> 4 | G77: =G49+G50+G51+G52+G53+G54 -> 7 | H77: =H49+H50+H51+H52+H53+H54 -> 10 | I77: =I49+I50+I51+I52+I53+I54 -> 12 | J77: =J49+J50+J51+J52+J53+J54 -> 15 | L77: сумма по ролям
A78: 69 | B78: Новые сотрудники | C78: ставок | F78: =MAX(0,F77-E77) -> 2 | G78: =MAX(0,G77-F77) -> 3 | H78: =MAX(0,H77-G77) -> 3 | I78: =MAX(0,I77-H77) -> 2 | J78: =MAX(0,J77-I77) -> 3 | L78: прирост численности
A79: 70 | B79: Годовой оклад на ставку: Основатели: продукт и продажи, архитектура правил | C79: млн ₽ | F79: =$D$41*12/1000*F59 -> 2.4 | G79: =$D$41*12/1000*G59 -> 2.568 | H79: =$D$41*12/1000*H59 -> 2.74776 | I79: =$D$41*12/1000*I59 -> 2.9401032 | J79: =$D$41*12/1000*J59 -> 3.1459104 | L79: оклад × 12 × индекс
A80: 71 | B80: Годовой оклад на ставку: Разработчики | C80: млн ₽ | F80: =$D$42*12/1000*F59 -> 3.36 | G80: =$D$42*12/1000*G59 -> 3.5952 | H80: =$D$42*12/1000*H59 -> 3.846864 | I80: =$D$42*12/1000*I59 -> 4.1161445 | J80: =$D$42*12/1000*J59 -> 4.4042746 | L80: оклад × 12 × индекс
A81: 72 | B81: Годовой оклад на ставку: Юрист-аналитик правил | C81: млн ₽ | F81: =$D$43*12/1000*F59 -> 2.76 | G81: =$D$43*12/1000*G59 -> 2.9532 | H81: =$D$43*12/1000*H59 -> 3.159924 | I81: =$D$43*12/1000*I59 -> 3.3811187 | J81: =$D$43*12/1000*J59 -> 3.617797 | L81: оклад × 12 × индекс
A82: 73 | B82: Годовой оклад на ставку: Инженеры внедрения и поддержки | C82: млн ₽ | F82: =$D$44*12/1000*F59 -> 2.64 | G82: =$D$44*12/1000*G59 -> 2.8248 | H82: =$D$44*12/1000*H59 -> 3.022536 | I82: =$D$44*12/1000*I59 -> 3.2341135 | J82: =$D$44*12/1000*J59 -> 3.4605015 | L82: оклад × 12 × индекс
A83: 74 | B83: Годовой оклад на ставку: Инженер качества и ИБ | C83: млн ₽ | F83: =$D$45*12/1000*F59 -> 3 | G83: =$D$45*12/1000*G59 -> 3.21 | H83: =$D$45*12/1000*H59 -> 3.4347 | I83: =$D$45*12/1000*I59 -> 3.675129 | J83: =$D$45*12/1000*J59 -> 3.932388 | L83: оклад × 12 × индекс
A84: 75 | B84: Годовой оклад на ставку: Менеджер по работе с банками | C84: млн ₽ | F84: =$D$46*12/1000*F59 -> 2.64 | G84: =$D$46*12/1000*G59 -> 2.8248 | H84: =$D$46*12/1000*H59 -> 3.022536 | I84: =$D$46*12/1000*I59 -> 3.2341135 | J84: =$D$46*12/1000*J59 -> 3.4605015 | L84: оклад × 12 × индекс
A85: 76 | B85: Фонд оплаты труда: Основатели: продукт и продажи, архитектура правил | C85: млн ₽ | F85: =F49*F79 -> 4.8 | G85: =G49*G79 -> 5.136 | H85: =H49*H79 -> 5.49552 | I85: =I49*I79 -> 5.8802064 | J85: =J49*J79 -> 6.2918208 | K85: =SUM(F85:J85) -> 27.603547 | L85: ставки × годовой оклад
A86: 77 | B86: Фонд оплаты труда: Разработчики | C86: млн ₽ | F86: =F50*F80 -> 3.36 | G86: =G50*G80 -> 7.1904 | H86: =H50*H80 -> 11.540592 | I86: =I50*I80 -> 12.348433 | J86: =J50*J80 -> 17.617098 | K86: =SUM(F86:J86) -> 52.056524 | L86: ставки × годовой оклад
A87: 78 | B87: Фонд оплаты труда: Юрист-аналитик правил | C87: млн ₽ | F87: =F51*F81 -> 2.76 | G87: =G51*G81 -> 2.9532 | H87: =H51*H81 -> 3.159924 | I87: =I51*I81 -> 6.7622374 | J87: =J51*J81 -> 7.235594 | K87: =SUM(F87:J87) -> 22.870955 | L87: ставки × годовой оклад
A88: 79 | B88: Фонд оплаты труда: Инженеры внедрения и поддержки | C88: млн ₽ | F88: =F52*F82 -> 0 | G88: =G52*G82 -> 2.8248 | H88: =H52*H82 -> 6.045072 | I88: =I52*I82 -> 9.7023406 | J88: =J52*J82 -> 10.381504 | K88: =SUM(F88:J88) -> 28.953717 | L88: ставки × годовой оклад
A89: 80 | B89: Фонд оплаты труда: Инженер качества и ИБ | C89: млн ₽ | F89: =F53*F83 -> 0 | G89: =G53*G83 -> 3.21 | H89: =H53*H83 -> 3.4347 | I89: =I53*I83 -> 3.675129 | J89: =J53*J83 -> 7.8647761 | K89: =SUM(F89:J89) -> 18.184605 | L89: ставки × годовой оклад
A90: 81 | B90: Фонд оплаты труда: Менеджер по работе с банками | C90: млн ₽ | F90: =F54*F84 -> 0 | G90: =G54*G84 -> 0 | H90: =H54*H84 -> 3.022536 | I90: =I54*I84 -> 3.2341135 | J90: =J54*J84 -> 6.9210029 | K90: =SUM(F90:J90) -> 13.177652 | L90: ставки × годовой оклад
A91: 82 | B91: Фонд оплаты труда | C91: млн ₽ | F91: =F85+F86+F87+F88+F89+F90 -> 10.92 | G91: =G85+G86+G87+G88+G89+G90 -> 21.3144 | H91: =H85+H86+H87+H88+H89+H90 -> 32.698344 | I91: =I85+I86+I87+I88+I89+I90 -> 41.60246 | J91: =J85+J86+J87+J88+J89+J90 -> 56.311797 | K91: =SUM(F91:J91) -> 162.847
A92: 83 | B92: Страховые взносы | C92: млн ₽ | F92: =F49*(MIN(F79,F60)*$D$16+MAX(0,F79-F60)*$D$17+F79*$D$18)+F50*(MIN(F80,F60)*$D$16+MAX(0,F80-F60)*$D$17+F80*$D$18)+F51*(MIN(F81,F60)*$D$16+MAX(0,F81-F60)*$D$17+F81*$D$18)+F52*(MIN(F82,F60)*$D$16+MAX(0,F82-F60)*$D$17+F82*$D$18)+F53*(MIN(F83,F60)*$D$16+MAX(0,F83-F60)*$D$17+F83*$D$18)+F54*(MIN(F84,F60)*$D$16+MAX(0,F84-F60)*$D$17+F84*$D$18) -> 1.6492817 | G92: =G49*(MIN(G79,G60)*$D$16+MAX(0,G79-G60)*$D$17+G79*$D$18)+G50*(MIN(G80,G60)*$D$16+MAX(0,G80-G60)*$D$17+G80*$D$18)+G51*(MIN(G81,G60)*$D$16+MAX(0,G81-G60)*$D$17+G81*$D$18)+G52*(MIN(G82,G60)*$D$16+MAX(0,G82-G60)*$D$17+G82*$D$18)+G53*(MIN(G83,G60)*$D$16+MAX(0,G83-G60)*$D$17+G83*$D$18)+G54*(MIN(G84,G60)*$D$16+MAX(0,G84-G60)*$D$17+G84*$D$18) -> 3.2219556 | H92: =H49*(MIN(H79,H60)*$D$16+MAX(0,H79-H60)*$D$17+H79*$D$18)+H50*(MIN(H80,H60)*$D$16+MAX(0,H80-H60)*$D$17+H80*$D$18)+H51*(MIN(H81,H60)*$D$16+MAX(0,H81-H60)*$D$17+H81*$D$18)+H52*(MIN(H82,H60)*$D$16+MAX(0,H82-H60)*$D$17+H82*$D$18)+H53*(MIN(H83,H60)*$D$16+MAX(0,H83-H60)*$D$17+H83*$D$18)+H54*(MIN(H84,H60)*$D$16+MAX(0,H84-H60)*$D$17+H84*$D$18) -> 4.9492399 | I92: =I49*(MIN(I79,I60)*$D$16+MAX(0,I79-I60)*$D$17+I79*$D$18)+I50*(MIN(I80,I60)*$D$16+MAX(0,I80-I60)*$D$17+I80*$D$18)+I51*(MIN(I81,I60)*$D$16+MAX(0,I81-I60)*$D$17+I81*$D$18)+I52*(MIN(I82,I60)*$D$16+MAX(0,I82-I60)*$D$17+I82*$D$18)+I53*(MIN(I83,I60)*$D$16+MAX(0,I83-I60)*$D$17+I83*$D$18)+I54*(MIN(I84,I60)*$D$16+MAX(0,I84-I60)*$D$17+I84*$D$18) -> 6.3095329 | J92: =J49*(MIN(J79,J60)*$D$16+MAX(0,J79-J60)*$D$17+J79*$D$18)+J50*(MIN(J80,J60)*$D$16+MAX(0,J80-J60)*$D$17+J80*$D$18)+J51*(MIN(J81,J60)*$D$16+MAX(0,J81-J60)*$D$17+J81*$D$18)+J52*(MIN(J82,J60)*$D$16+MAX(0,J82-J60)*$D$17+J82*$D$18)+J53*(MIN(J83,J60)*$D$16+MAX(0,J83-J60)*$D$17+J83*$D$18)+J54*(MIN(J84,J60)*$D$16+MAX(0,J84-J60)*$D$17+J84*$D$18) -> 8.5513578 | K92: =SUM(F92:J92) -> 24.681368 | L92: по каждой роли: в пределах базы × льготный тариф + сверх базы × 7,6 % + травматизм
A93: 84 | B93: Первый договор (1 — в этом году) | F93: =IF(AND(F66>0,E66=0),1,0) -> 1 | G93: =IF(AND(G66>0,F66=0),1,0) -> 0 | H93: =IF(AND(H66>0,G66=0),1,0) -> 0 | I93: =IF(AND(I66>0,H66=0),1,0) -> 0 | J93: =IF(AND(J66>0,I66=0),1,0) -> 0
A94: 85 | B94: Оценка ИБ (анализ уязвимостей) | C94: млн ₽ | F94: =(F93*$D$21+IF(E66>0,1,0)*$D$22)*F58 -> 2.5 | G94: =(G93*$D$21+IF(F66>0,1,0)*$D$22)*G58 -> 1.05 | H94: =(H93*$D$21+IF(G66>0,1,0)*$D$22)*H58 -> 1.1025 | I94: =(I93*$D$21+IF(H66>0,1,0)*$D$22)*I58 -> 1.157625 | J94: =(J93*$D$21+IF(I66>0,1,0)*$D$22)*J58 -> 1.2155063 | K94: =SUM(F94:J94) -> 7.0256312 | L94: первая — в год первого договора, дальше — ежегодно
A95: 86 | B95: Внешняя юридическая экспертиза правил | C95: млн ₽ | F95: =$D$23*F58 -> 0.8 | G95: =$D$23*G58 -> 0.84 | H95: =$D$23*H58 -> 0.882 | I95: =$D$23*I58 -> 0.9261 | J95: =$D$23*J58 -> 0.972405 | K95: =SUM(F95:J95) -> 4.420505
A96: 87 | B96: Инфраструктура и инструменты | C96: млн ₽ | F96: =$D$24*F77*F58 -> 0.72 | G96: =$D$24*G77*G58 -> 1.323 | H96: =$D$24*H77*H58 -> 1.9845 | I96: =$D$24*I77*I58 -> 2.50047 | J96: =$D$24*J77*J58 -> 3.2818669 | K96: =SUM(F96:J96) -> 9.8098369 | L96: на сотрудника
A97: 88 | B97: Продажи и маркетинг | C97: млн ₽ | F97: =($D$25+$D$26*F67)*F58 -> 2 | G97: =($D$25+$D$26*G67)*G58 -> 2.625 | H97: =($D$25+$D$26*H67)*H58 -> 3.85875 | I97: =($D$25+$D$26*I67)*I58 -> 4.6305 | J97: =($D$25+$D$26*J67)*J58 -> 5.4697781 | K97: =SUM(F97:J97) -> 18.584028 | L97: постоянная часть + на договор
A98: 89 | B98: Административные | C98: млн ₽ | F98: =($D$27+$D$28*F77)*F58 -> 1.98 | G98: =($D$27+$D$28*G77)*G58 -> 2.457 | H98: =($D$27+$D$28*H77)*H58 -> 2.97675 | I98: =($D$27+$D$28*I77)*I58 -> 3.4034175 | J98: =($D$27+$D$28*J77)*J58 -> 4.0111706 | K98: =SUM(F98:J98) -> 14.828338 | L98: постоянная часть + на сотрудника
A99: 90 | B99: Оборудование | C99: млн ₽ | F99: =$D$29*F78*F58 -> 0.5 | G99: =$D$29*G78*G58 -> 0.7875 | H99: =$D$29*H78*H58 -> 0.826875 | I99: =$D$29*I78*I58 -> 0.5788125 | J99: =$D$29*J78*J58 -> 0.91162969 | K99: =SUM(F99:J99) -> 3.6048172 | L99: на нового сотрудника
A100: 91 | B100: Регистрация, аккредитация, реестр ПО | C100: млн ₽ | F100: =IF(F$56=$F$56,$D$30,0) -> 0.3 | G100: =IF(G$56=$F$56,$D$30,0) -> 0 | H100: =IF(H$56=$F$56,$D$30,0) -> 0 | I100: =IF(I$56=$F$56,$D$30,0) -> 0 | J100: =IF(J$56=$F$56,$D$30,0) -> 0 | K100: =SUM(F100:J100) -> 0.3 | L100: только 2027 год
A101: 92 | B101: Затраты до резерва | C101: млн ₽ | F101: =F91+F92+F94+F95+F96+F97+F98+F99+F100 -> 21.369282 | G101: =G91+G92+G94+G95+G96+G97+G98+G99+G100 -> 33.618856 | H101: =H91+H92+H94+H95+H96+H97+H98+H99+H100 -> 49.278959 | I101: =I91+I92+I94+I95+I96+I97+I98+I99+I100 -> 61.108918 | J101: =J91+J92+J94+J95+J96+J97+J98+J99+J100 -> 80.725511 | K101: =SUM(F101:J101) -> 246.10153
...

Sheet Чувствительность
A1: Чувствительность NPV базового сценария
A2: Каждое допущение меняется на ±20 %, остальные — как в базовом сценарии. Блоки расчёта ниже — та же структура, что на листе «Базовый»
A4: № | B4: Допущение | C4: Изменение | D4: NPV при −20 % | E4: NPV при +20 % | F4: Базовый NPV | G4: Размах
A5: 1 | B5: Цена подписки | C5: ±20 % | D5: =$D$290 -> -18.213264 | E5: =$D$429 -> 17.452316 | F5: =Базовый!$D$136 -> -0.14959473 | G5: =ABS(E5-D5) -> 35.665579
A6: 2 | B6: Число новых банков | C6: ±20 % | D6: =$D$568 -> -11.087652 | E6: =$D$707 -> 10.778634 | F6: =Базовый!$D$136 -> -0.14959473 | G6: =ABS(E6-D6) -> 21.866287
A7: 3 | B7: Рост подписки за счёт новых операций | C7: ±20 % | D7: =$D$846 -> -3.7113142 | E7: =$D$985 -> 3.5450611 | F7: =Базовый!$D$136 -> -0.14959473 | G7: =ABS(E7-D7) -> 7.2563753
A8: 4 | B8: Плата за внедрение | C8: ±20 % | D8: =$D$1124 -> -6.5416818 | E8: =$D$1263 -> 6.2334685 | F8: =Базовый!$D$136 -> -0.14959473 | G8: =ABS(E8-D8) -> 12.77515
A9: 5 | B9: Оклады команды | C9: ±20 % | D9: =$D$1402 -> 17.70952 | E9: =$D$1541 -> -18.179021 | F9: =Базовый!$D$136 -> -0.14959473 | G9: =ABS(E9-D9) -> 35.888541
A10: 6 | B10: Численность команды | C10: ±20 % | D10: =$D$1680 -> 19.2436 | E10: =$D$1819 -> -20.205538 | F10: =Базовый!$D$136 -> -0.14959473 | G10: =ABS(E10-D10) -> 39.449138
A11: 7 | B11: Прочие затраты | C11: ±20 % | D11: =$D$1958 -> 5.8850866 | E11: =$D$2097 -> -6.1842761 | F11: =Базовый!$D$136 -> -0.14959473 | G11: =ABS(E11-D11) -> 12.069363
A12: 8 | B12: Срок оплаты банками | C12: ±20 % | D12: =$D$2236 -> 2.5870315 | E12: =$D$2375 -> -2.886221 | F12: =Базовый!$D$136 -> -0.14959473 | G12: =ABS(E12-D12) -> 5.4732525
A13: 9 | B13: Ставка дисконтирования | C13: ±20 % | D13: =$D$2514 -> 9.0779508 | E13: =$D$2653 -> -4.9603535 | F13: =Базовый!$D$136 -> -0.14959473 | G13: =ABS(E13-D13) -> 14.038304
A14: 10 | B14: Договор с ВТБ на год позже | C14: +1 год | D14: =$D$2792 -> -15.249814 | F14: =Базовый!$D$136 -> -0.14959473 | G14: =ABS(D14-F14) -> 15.100219
A16: Строки с блоками расчёта свёрнуты: раскройте группу слева, чтобы увидеть формулы.
A18: Контроль: базовый сценарий без изменений
A19: № | B19: Показатель | C19: Единица | D19: Константа | E19: 2026 | F19: 2027 | G19: 2028 | H19: 2029 | I19: 2030 | J19: 2031 | K19: Итого 2027–2031 | L19: Как считается
A20: Входные данные (ссылки на «Допущения», «План», «Рынок»)
A21: 1 | B21: Год договора с ВТБ | C21: год | D21: =Допущения!$E$49 -> 2027
A22: 2 | B22: Клиенты-бизнесы ВТБ | C22: млн | D22: =Допущения!$E$7 -> 1.8
A23: 3 | B23: Подписка уровня 1: постоянная часть | C23: млн ₽ в год | D23: =Допущения!$E$42 -> 6
A24: 4 | B24: Плата за активного клиента-бизнес | C24: ₽ в год | D24: =Допущения!$E$43 -> 5
A25: 5 | B25: Подписка уровня 2: постоянная часть | C25: млн ₽ в год | D25: =Допущения!$E$44 -> 1.5
A26: 6 | B26: Внедрение, уровень 1 | C26: млн ₽ | D26: =Допущения!$E$45 -> 8
A27: 7 | B27: Внедрение, уровень 2 | C27: млн ₽ | D27: =Допущения!$E$46 -> 2
A28: 8 | B28: Индексация цен | C28: доля в год | D28: =Допущения!$E$47 -> 0.05
A29: 9 | B29: Рост подписки за счёт новых операций | C29: доля в год | D29: =Допущения!$E$48 -> 0.15
A30: 10 | B30: Рост окладов | C30: доля в год | D30: =Допущения!$E$51 -> 0.07
A31: 11 | B31: Взносы в пределах базы | C31: доля | D31: =Допущения!$E$52 -> 0.15
A32: 12 | B32: Взносы сверх базы | C32: доля | D32: =Допущения!$E$53 -> 0.076
A33: 13 | B33: Взнос на травматизм | C33: доля | D33: =Допущения!$E$54 -> 0.002
A34: 14 | B34: Предельная база взносов 2026 | C34: млн ₽ в год | D34: =Допущения!$E$55 -> 2.979
A35: 15 | B35: Рост базы | C35: доля в год | D35: =Допущения!$E$56 -> 0.08
A36: 16 | B36: Анализ уязвимостей по ОУД4 — первый | C36: млн ₽ | D36: =Допущения!$E$58 -> 2.5
A37: 17 | B37: Повторная оценка релизов | C37: млн ₽ в год | D37: =Допущения!$E$59 -> 1
A38: 18 | B38: Внешняя юридическая экспертиза правил | C38: млн ₽ в год | D38: =Допущения!$E$60 -> 0.6
A39: 19 | B39: Инфраструктура на сотрудника | C39: млн ₽ в год | D39: =Допущения!$E$61 -> 0.15
A40: 20 | B40: Продажи: постоянная часть | C40: млн ₽ в год | D40: =Допущения!$E$62 -> 1
A41: 21 | B41: Продажи: на договор | C41: млн ₽ | D41: =Допущения!$E$63 -> 0.4
A42: 22 | B42: Административные: постоянная часть | C42: млн ₽ в год | D42: =Допущения!$E$64 -> 1.2
A43: 23 | B43: Административные: на сотрудника | C43: млн ₽ в год | D43: =Допущения!$E$65 -> 0.1
A44: 24 | B44: Оборудование на нового сотрудника | C44: млн ₽ | D44: =Допущения!$E$66 -> 0.25
A45: 25 | B45: Регистрация, аккредитация, реестр ПО | C45: млн ₽ | D45: =Допущения!$E$67 -> 0.3
A46: 26 | B46: Рост прочих затрат | C46: доля в год | D46: =Допущения!$E$68 -> 0.05
A47: 27 | B47: Резерв | C47: доля затрат | D47: =Допущения!$E$69 -> 0.1
A48: 28 | B48: Налог на прибыль | C48: доля | D48: =Допущения!$E$71 -> 0.05
A49: 29 | B49: Перенос убытка: доля прибыли | C49: доля | D49: =Допущения!$E$72 -> 0.5
A50: 30 | B50: Срок оплаты банками | C50: дней | D50: =Допущения!$E$73 -> 90
A51: 31 | B51: Ставка дисконтирования | C51: доля | D51: =Допущения!$E$74 -> 0.3
A52: 32 | B52: Рост после 2031 года | C52: доля в год | D52: =Допущения!$E$75 -> 0.04
A53: 33 | B53: Запас к финансированию | C53: доля | D53: =Допущения!$E$76 -> 0.2
A54: 34 | B54: Клиентов у банка уровня 1, кроме ВТБ | C54: млн | D54: =Рынок!$E$30 -> 0.49090909 | L54: лист «Рынок»
A55: 35 | B55: Клиентов у банка уровня 2 | C55: млн | D55: =Рынок!$E$31 -> 0.028125 | L55: лист «Рынок»
A56: 36 | B56: Оклад: Основатели: продукт и продажи, архитектура правил | C56: тыс. ₽ в месяц | D56: =План!$D$18 -> 200 | L56: лист «План»
A57: 37 | B57: Оклад: Разработчики | C57: тыс. ₽ в месяц | D57: =План!$D$19 -> 280 | L57: лист «План»
A58: 38 | B58: Оклад: Юрист-аналитик правил | C58: тыс. ₽ в месяц | D58: =План!$D$20 -> 230 | L58: лист «План»
A59: 39 | B59: Оклад: Инженеры внедрения и поддержки | C59: тыс. ₽ в месяц | D59: =План!$D$21 -> 220 | L59: лист «План»
A60: 40 | B60: Оклад: Инженер качества и ИБ | C60: тыс. ₽ в месяц | D60: =План!$D$22 -> 250 | L60: лист «План»
A61: 41 | B61: Оклад: Менеджер по работе с банками | C61: тыс. ₽ в месяц | D61: =План!$D$23 -> 220 | L61: лист «План»
A62: 42 | B62: Новые банки уровня 1 (кроме ВТБ) | C62: банков | E62: =План!E16 -> 0 | F62: =План!F16 -> 0 | G62: =План!G16 -> 0 | H62: =План!H16 -> 1 | I62: =План!I16 -> 0 | J62: =План!J16 -> 1 | K62: =SUM(F62:J62) -> 2 | L62: лист «План»
A63: 43 | B63: Новые банки уровня 2 | C63: банков | E63: =План!E17 -> 0 | F63: =План!F17 -> 0 | G63: =План!G17 -> 1 | H63: =План!H17 -> 2 | I63: =План!I17 -> 2 | J63: =План!J17 -> 3 | K63: =SUM(F63:J63) -> 8 | L63: лист «План»
A64: 44 | B64: Численность: Основатели: продукт и продажи, архитектура правил | C64: ставок | E64: =План!E18 -> 2 | F64: =План!F18 -> 2 | G64: =План!G18 -> 2 | H64: =План!H18 -> 2 | I64: =План!I18 -> 2 | J64: =План!J18 -> 2 | L64: лист «План»
A65: 45 | B65: Численность: Разработчики | C65: ставок | E65: =План!E19 -> 0 | F65: =План!F19 -> 1 | G65: =План!G19 -> 1 | H65: =План!H19 -> 1 | I65: =План!I19 -> 2 | J65: =План!J19 -> 2 | L65: лист «План»
A66: 46 | B66: Численность: Юрист-аналитик правил | C66: ставок | E66: =План!E20 -> 0 | F66: =План!F20 -> 1 | G66: =План!G20 -> 1 | H66: =План!H20 -> 1 | I66: =План!I20 -> 1 | J66: =План!J20 -> 1 | L66: лист «План»
A67: 47 | B67: Численность: Инженеры внедрения и поддержки | C67: ставок | E67: =План!E21 -> 0 | F67: =План!F21 -> 0 | G67: =План!G21 -> 1 | H67: =План!H21 -> 1 | I67: =План!I21 -> 1 | J67: =План!J21 -> 1 | L67: лист «План»
A68: 48 | B68: Численность: Инженер качества и ИБ | C68: ставок | E68: =План!E22 -> 0 | F68: =План!F22 -> 0 | G68: =План!G22 -> 0 | H68: =План!H22 -> 1 | I68: =План!I22 -> 1 | J68: =План!J22 -> 1 | L68: лист «План»
A69: 49 | B69: Численность: Менеджер по работе с банками | C69: ставок | E69: =План!E23 -> 0 | F69: =План!F23 -> 0 | G69: =План!G23 -> 0 | H69: =План!H23 -> 0 | I69: =План!I23 -> 0 | J69: =План!J23 -> 1 | L69: лист «План»
A70: 1. Время
A71: 50 | B71: Год | E71: =Допущения!$D$3 -> 2026 | F71: =E71+1 -> 2027 | G71: =F71+1 -> 2028 | H71: =G71+1 -> 2029 | I71: =H71+1 -> 2030 | J71: =I71+1 -> 2031 | L71: предыдущий + 1
A72: 51 | B72: Индекс цен к 2027 году | C72: раз | F72: =(1+$D$28)^(F$71-$E$71-1) -> 1 | G72: =(1+$D$28)^(G$71-$E$71-1) -> 1.05 | H72: =(1+$D$28)^(H$71-$E$71-1) -> 1.1025 | I72: =(1+$D$28)^(I$71-$E$71-1) -> 1.157625 | J72: =(1+$D$28)^(J$71-$E$71-1) -> 1.2155063 | L72: (1 + индексация) ^ (год − 2027)
A73: 52 | B73: Индекс прочих затрат к 2027 году | C73: раз | F73: =(1+$D$46)^(F$71-$E$71-1) -> 1 | G73: =(1+$D$46)^(G$71-$E$71-1) -> 1.05 | H73: =(1+$D$46)^(H$71-$E$71-1) -> 1.1025 | I73: =(1+$D$46)^(I$71-$E$71-1) -> 1.157625 | J73: =(1+$D$46)^(J$71-$E$71-1) -> 1.2155063 | L73: то же для затрат
A74: 53 | B74: Индекс окладов к 2027 году | C74: раз | F74: =(1+$D$30)^(F$71-$E$71-1) -> 1 | G74: =(1+$D$30)^(G$71-$E$71-1) -> 1.07 | H74: =(1+$D$30)^(H$71-$E$71-1) -> 1.1449 | I74: =(1+$D$30)^(I$71-$E$71-1) -> 1.225043 | J74: =(1+$D$30)^(J$71-$E$71-1) -> 1.310796 | L74: то же для окладов
A75: 54 | B75: Предельная база взносов | C75: млн ₽ в год | F75: =$D$34*(1+$D$35)^(F$71-$E$71) -> 3.21732 | G75: =$D$34*(1+$D$35)^(G$71-$E$71) -> 3.4747056 | H75: =$D$34*(1+$D$35)^(H$71-$E$71) -> 3.752682 | I75: =$D$34*(1+$D$35)^(I$71-$E$71) -> 4.0528966 | J75: =$D$34*(1+$D$35)^(J$71-$E$71) -> 4.3771283 | L75: база 2026 × (1 + рост) ^ (год − 2026)
A76: 2. Договоры
A77: 55 | B77: Договор с ВТБ (1 — в этом году) | C77: банков | F77: =IF(F$71=$D$21,1,0) -> 1 | G77: =IF(G$71=$D$21,1,0) -> 0 | H77: =IF(H$71=$D$21,1,0) -> 0 | I77: =IF(I$71=$D$21,1,0) -> 0 | J77: =IF(J$71=$D$21,1,0) -> 0 | L77: год договора с ВТБ
A78: 56 | B78: Новые банки уровня 1, с ВТБ | C78: банков | E78: =0 -> 0 | F78: =F77+F62 -> 1 | G78: =G77+G62 -> 0 | H78: =H77+H62 -> 1 | I78: =I77+I62 -> 0 | J78: =J77+J62 -> 1 | K78: =SUM(F78:J78) -> 3 | L78: ВТБ + другие
A79: 57 | B79: Банки уровня 1 с договором, на конец года | C79: банков | E79: =0 -> 0 | F79: =E79+F78 -> 1 | G79: =F79+G78 -> 1 | H79: =G79+H78 -> 2 | I79: =H79+I78 -> 2 | J79: =I79+J78 -> 3 | L79: накопленным итогом
A80: 58 | B80: Банки уровня 2 с договором, на конец года | C80: банков | E80: =0 -> 0 | F80: =E80+F63 -> 0 | G80: =F80+G63 -> 1 | H80: =G80+H63 -> 3 | I80: =H80+I63 -> 5 | J80: =I80+J63 -> 8 | L80: накопленным итогом
A81: 59 | B81: Банков с договором, на конец года | C81: банков | E81: =0 -> 0 | F81: =F79+F80 -> 1 | G81: =G79+G80 -> 2 | H81: =H79+H80 -> 5 | I81: =I79+I80 -> 7 | J81: =J79+J80 -> 11 | L81: уровень 1 + уровень 2
A82: 60 | B82: Новых договоров за год | C82: банков | F82: =F78+F63 -> 1 | G82: =G78+G63 -> 1 | H82: =H78+H63 -> 3 | I82: =I78+I63 -> 2 | J82: =J78+J63 -> 4 | K82: =SUM(F82:J82) -> 11
A83: 3. Выручка, млн ₽ без НДС
A84: 61 | B84: Подписка ВТБ | C84: млн ₽ | F84: =IF(F$71>$D$21,($D$23+$D$22*$D$24)*(1+$D$29)^(F$71-$D$21-1)*F72,0) -> 0 | G84: =IF(G$71>$D$21,($D$23+$D$22*$D$24)*(1+$D$29)^(G$71-$D$21-1)*G72,0) -> 15.75 | H84: =IF(H$71>$D$21,($D$23+$D$22*$D$24)*(1+$D$29)^(H$71-$D$21-1)*H72,0) -> 19.018125 | I84: =IF(I$71>$D$21,($D$23+$D$22*$D$24)*(1+$D$29)^(I$71-$D$21-1)*I72,0) -> 22.964386 | J84: =IF(J$71>$D$21,($D$23+$D$22*$D$24)*(1+$D$29)^(J$71-$D$21-1)*J72,0) -> 27.729496 | K84: =SUM(F84:J84) -> 85.462007 | L84: со следующего года после договора; растёт с новыми операциями; индексируется
A85: 62 | B85: Подписка других банков уровня 1 | C85: млн ₽ | F85: =($D$23+$D$54*$D$24)*F72*SUMPRODUCT($E$62:E$62,(1+$D$29)^(F$71-$E$71:E$71-1)) -> 0 | G85: =($D$23+$D$54*$D$24)*G72*SUMPRODUCT($E$62:F$62,(1+$D$29)^(G$71-$E$71:F$71-1)) -> 0 | H85: =($D$23+$D$54*$D$24)*H72*SUMPRODUCT($E$62:G$62,(1+$D$29)^(H$71-$E$71:G$71-1)) -> 0 | I85: =($D$23+$D$54*$D$24)*I72*SUMPRODUCT($E$62:H$62,(1+$D$29)^(I$71-$E$71:H$71-1)) -> 9.7871932 | J85: =($D$23+$D$54*$D$24)*J72*SUMPRODUCT($E$62:I$62,(1+$D$29)^(J$71-$E$71:I$71-1)) -> 11.818036 | K85: =SUM(F85:J85) -> 21.605229 | L85: по годам договоров: подписка × (1 + рост) ^ (лет после первого года) × индекс
A86: 63 | B86: Подписка банков уровня 2 | C86: млн ₽ | F86: =($D$25+$D$55*$D$24)*F72*SUMPRODUCT($E$63:E$63,(1+$D$29)^(F$71-$E$71:E$71-1)) -> 0 | G86: =($D$25+$D$55*$D$24)*G72*SUMPRODUCT($E$63:F$63,(1+$D$29)^(G$71-$E$71:F$71-1)) -> 0 | H86: =($D$25+$D$55*$D$24)*H72*SUMPRODUCT($E$63:G$63,(1+$D$29)^(H$71-$E$71:G$71-1)) -> 1.8087891 | I86: =($D$25+$D$55*$D$24)*I72*SUMPRODUCT($E$63:H$63,(1+$D$29)^(I$71-$E$71:H$71-1)) -> 5.9825698 | J86: =($D$25+$D$55*$D$24)*J72*SUMPRODUCT($E$63:I$63,(1+$D$29)^(J$71-$E$71:I$71-1)) -> 11.212333 | K86: =SUM(F86:J86) -> 19.003692 | L86: то же для уровня 2
A87: 64 | B87: Внедрение | C87: млн ₽ | F87: =(F78*$D$26+F63*$D$27)*F72 -> 8 | G87: =(G78*$D$26+G63*$D$27)*G72 -> 2.1 | H87: =(H78*$D$26+H63*$D$27)*H72 -> 13.23 | I87: =(I78*$D$26+I63*$D$27)*I72 -> 4.6305 | J87: =(J78*$D$26+J63*$D$27)*J72 -> 17.017087 | K87: =SUM(F87:J87) -> 44.977587 | L87: новые договоры × плата за внедрение × индекс
A88: 65 | B88: Подписка всего | C88: млн ₽ | F88: =F84+F85+F86 -> 0 | G88: =G84+G85+G86 -> 15.75 | H88: =H84+H85+H86 -> 20.826914 | I88: =I84+I85+I86 -> 38.734149 | J88: =J84+J85+J86 -> 50.759865 | K88: =SUM(F88:J88) -> 126.07093
A89: 66 | B89: Выручка | C89: млн ₽ | F89: =F88+F87 -> 8 | G89: =G88+G87 -> 17.85 | H89: =H88+H87 -> 34.056914 | I89: =I88+I87 -> 43.364649 | J89: =J88+J87 -> 67.776952 | K89: =SUM(F89:J89) -> 171.04852 | L89: подписка + внедрение
A90: 67 | B90: Годовая подписка на конец года (ARR) | C90: млн ₽ в год | F90: =IF(F$71>=$D$21,($D$23+$D$22*$D$24)*(1+$D$29)^(F$71-$D$21)*F72,0)+($D$23+$D$54*$D$24)*F72*SUMPRODUCT($E$62:F$62,(1+$D$29)^(F$71-$E$71:F$71))+($D$25+$D$55*$D$24)*F72*SUMPRODUCT($E$63:F$63,(1+$D$29)^(F$71-$E$71:F$71)) -> 15 | G90: =IF(G$71>=$D$21,($D$23+$D$22*$D$24)*(1+$D$29)^(G$71-$D$21)*G72,0)+($D$23+$D$54*$D$24)*G72*SUMPRODUCT($E$62:G$62,(1+$D$29)^(G$71-$E$71:G$71))+($D$25+$D$55*$D$24)*G72*SUMPRODUCT($E$63:G$63,(1+$D$29)^(G$71-$E$71:G$71)) -> 19.835156 | H90: =IF(H$71>=$D$21,($D$23+$D$22*$D$24)*(1+$D$29)^(H$71-$D$21)*H72,0)+($D$23+$D$54*$D$24)*H72*SUMPRODUCT($E$62:H$62,(1+$D$29)^(H$71-$E$71:H$71))+($D$25+$D$55*$D$24)*H72*SUMPRODUCT($E$63:H$63,(1+$D$29)^(H$71-$E$71:H$71)) -> 36.889666 | I90: =IF(I$71>=$D$21,($D$23+$D$22*$D$24)*(1+$D$29)^(I$71-$D$21)*I72,0)+($D$23+$D$54*$D$24)*I72*SUMPRODUCT($E$62:I$62,(1+$D$29)^(I$71-$E$71:I$71))+($D$25+$D$55*$D$24)*I72*SUMPRODUCT($E$63:I$63,(1+$D$29)^(I$71-$E$71:I$71)) -> 48.342728 | J90: =IF(J$71>=$D$21,($D$23+$D$22*$D$24)*(1+$D$29)^(J$71-$D$21)*J72,0)+($D$23+$D$54*$D$24)*J72*SUMPRODUCT($E$62:J$62,(1+$D$29)^(J$71-$E$71:J$71))+($D$25+$D$55*$D$24)*J72*SUMPRODUCT($E$63:J$63,(1+$D$29)^(J$71-$E$71:J$71)) -> 74.632967 | L90: подписка всех банков с договором в ценах года
A91: 4. Затраты, млн ₽
A92: 68 | B92: Численность команды | C92: ставок | E92: =E64+E65+E66+E67+E68+E69 -> 2 | F92: =F64+F65+F66+F67+F68+F69 -> 4 | G92: =G64+G65+G66+G67+G68+G69 -> 5 | H92: =H64+H65+H66+H67+H68+H69 -> 6 | I92: =I64+I65+I66+I67+I68+I69 -> 7 | J92: =J64+J65+J66+J67+J68+J69 -> 8 | L92: сумма по ролям
A93: 69 | B93: Новые сотрудники | C93: ставок | F93: =MAX(0,F92-E92) -> 2 | G93: =MAX(0,G92-F92) -> 1 | H93: =MAX(0,H92-G92) -> 1 | I93: =MAX(0,I92-H92) -> 1 | J93: =MAX(0,J92-I92) -> 1 | L93: прирост численности
A94: 70 | B94: Годовой оклад на ставку: Основатели: продукт и продажи, архитектура правил | C94: млн ₽ | F94: =$D$56*12/1000*F74 -> 2.4 | G94: =$D$56*12/1000*G74 -> 2.568 | H94: =$D$56*12/1000*H74 -> 2.74776 | I94: =$D$56*12/1000*I74 -> 2.9401032 | J94: =$D$56*12/1000*J74 -> 3.1459104 | L94: оклад × 12 × индекс
A95: 71 | B95: Годовой оклад на ставку: Разработчики | C95: млн ₽ | F95: =$D$57*12/1000*F74 -> 3.36 | G95: =$D$57*12/1000*G74 -> 3.5952 | H95: =$D$57*12/1000*H74 -> 3.846864 | I95: =$D$57*12/1000*I74 -> 4.1161445 | J95: =$D$57*12/1000*J74 -> 4.4042746 | L95: оклад × 12 × индекс
A96: 72 | B96: Годовой оклад на ставку: Юрист-аналитик правил | C96: млн ₽ | F96: =$D$58*12/1000*F74 -> 2.76 | G96: =$D$58*12/1000*G74 -> 2.9532 | H96: =$D$58*12/1000*H74 -> 3.159924 | I96: =$D$58*12/1000*I74 -> 3.3811187 | J96: =$D$58*12/1000*J74 -> 3.617797 | L96: оклад × 12 × индекс
A97: 73 | B97: Годовой оклад на ставку: Инженеры внедрения и поддержки | C97: млн ₽ | F97: =$D$59*12/1000*F74 -> 2.64 | G97: =$D$59*12/1000*G74 -> 2.8248 | H97: =$D$59*12/1000*H74 -> 3.022536 | I97: =$D$59*12/1000*I74 -> 3.2341135 | J97: =$D$59*12/1000*J74 -> 3.4605015 | L97: оклад × 12 × индекс
A98: 74 | B98: Годовой оклад на ставку: Инженер качества и ИБ | C98: млн ₽ | F98: =$D$60*12/1000*F74 -> 3 | G98: =$D$60*12/1000*G74 -> 3.21 | H98: =$D$60*12/1000*H74 -> 3.4347 | I98: =$D$60*12/1000*I74 -> 3.675129 | J98: =$D$60*12/1000*J74 -> 3.932388 | L98: оклад × 12 × индекс
A99: 75 | B99: Годовой оклад на ставку: Менеджер по работе с банками | C99: млн ₽ | F99: =$D$61*12/1000*F74 -> 2.64 | G99: =$D$61*12/1000*G74 -> 2.8248 | H99: =$D$61*12/1000*H74 -> 3.022536 | I99: =$D$61*12/1000*I74 -> 3.2341135 | J99: =$D$61*12/1000*J74 -> 3.4605015 | L99: оклад × 12 × индекс
A100: 76 | B100: Фонд оплаты труда: Основатели: продукт и продажи, архитектура правил | C100: млн ₽ | F100: =F64*F94 -> 4.8 | G100: =G64*G94 -> 5.136 | H100: =H64*H94 -> 5.49552 | I100: =I64*I94 -> 5.8802064 | J100: =J64*J94 -> 6.2918208 | K100: =SUM(F100:J100) -> 27.603547 | L100: ставки × годовой оклад
A101: 77 | B101: Фонд оплаты труда: Разработчики | C101: млн ₽ | F101: =F65*F95 -> 3.36 | G101: =G65*G95 -> 3.5952 | H101: =H65*H95 -> 3.846864 | I101: =I65*I95 -> 8.232289 | J101: =J65*J95 -> 8.8085492 | K101: =SUM(F101:J101) -> 27.842902 | L101: ставки × годовой оклад
A102: 78 | B102: Фонд оплаты труда: Юрист-аналитик правил | C102: млн ₽ | F102: =F66*F96 -> 2.76 | G102: =G66*G96 -> 2.9532 | H102: =H66*H96 -> 3.159924 | I102: =I66*I96 -> 3.3811187 | J102: =J66*J96 -> 3.617797 | K102: =SUM(F102:J102) -> 15.87204 | L102: ставки × годовой оклад
A103: 79 | B103: Фонд оплаты труда: Инженеры внедрения и поддержки | C103: млн ₽ | F103: =F67*F97 -> 0 | G103: =G67*G97 -> 2.8248 | H103: =H67*H97 -> 3.022536 | I103: =I67*I97 -> 3.2341135 | J103: =J67*J97 -> 3.4605015 | K103: =SUM(F103:J103) -> 12.541951 | L103: ставки × годовой оклад
...

Sheet Проверки
A1: Проверки
A2: Целостность — должна быть «ОК» всегда; допущения — предупреждение, если цена или доля рынка выходят за рамки
A4: № | B4: Проверка | C4: Сценарий | D4: Ожидается | E4: Факт | F4: Статус | G4: Пояснение
A5: Целостность
A6: 1 | B6: Ставки совпадают с презентацией (C-15) | C6: Консервативный | D6: 33 | E6: ='Эффект для банка'!$D$36 -> 33 | F6: =IF(E6=D6,"ОК","ОШИБКА") -> ОК | G6: эталон — реестр утверждений
A7: 2 | B7: Ущерб совпадает с презентацией (C-16) | C7: Консервативный | D7: 34 | E7: ='Эффект для банка'!$D$44 -> 34 | F7: =IF(E7=D7,"ОК","ОШИБКА") -> ОК | G7: эталон — реестр утверждений
A8: 3 | B8: Ставки совпадают с презентацией (C-15) | C8: Базовый | D8: 75 | E8: ='Эффект для банка'!$E$36 -> 75 | F8: =IF(E8=D8,"ОК","ОШИБКА") -> ОК | G8: эталон — реестр утверждений
A9: 4 | B9: Ущерб совпадает с презентацией (C-16) | C9: Базовый | D9: 115 | E9: ='Эффект для банка'!$E$44 -> 115 | F9: =IF(E9=D9,"ОК","ОШИБКА") -> ОК | G9: эталон — реестр утверждений
A10: 5 | B10: Ставки совпадают с презентацией (C-15) | C10: Оптимистичный | D10: 167 | E10: ='Эффект для банка'!$F$36 -> 167 | F10: =IF(E10=D10,"ОК","ОШИБКА") -> ОК | G10: эталон — реестр утверждений
A11: 6 | B11: Ущерб совпадает с презентацией (C-16) | C11: Оптимистичный | D11: 229 | E11: ='Эффект для банка'!$F$44 -> 229 | F11: =IF(E11=D11,"ОК","ОШИБКА") -> ОК | G11: эталон — реестр утверждений
A12: 7 | B12: Выручка = подписка + внедрение | C12: Консервативный | D12: =Консервативный!K73+Консервативный!K72 -> 37.247677 | E12: =Консервативный!K74 -> 37.247677 | F12: =IF(ABS(E12-D12)<0.000001,"ОК","ОШИБКА") -> ОК | G12: итоги 2027–2031
A13: 8 | B13: Подписка = ВТБ + уровень 1 + уровень 2 | C13: Консервативный | D13: =Консервативный!K69+Консервативный!K70+Консервативный!K71 -> 25.943193 | E13: =Консервативный!K73 -> 25.943193 | F13: =IF(ABS(E13-D13)<0.000001,"ОК","ОШИБКА") -> ОК
A14: 9 | B14: Накопленный поток = сумма потоков | C14: Консервативный | D14: =Консервативный!K116 -> -65.103095 | E14: =Консервативный!J117 -> -65.103095 | F14: =IF(ABS(E14-D14)<0.000001,"ОК","ОШИБКА") -> ОК
A15: 10 | B15: Чистая прибыль = EBITDA − налог | C15: Консервативный | D15: =Консервативный!K105-Консервативный!K110 -> -61.175255 | E15: =Консервативный!K112 -> -61.175255 | F15: =IF(ABS(E15-D15)<0.000001,"ОК","ОШИБКА") -> ОК
A16: 11 | B16: Численность и договоры не отрицательные | C16: Консервативный | D16: 0 | E16: =MIN(Консервативный!E77:J77,Консервативный!F66:J66) -> 0 | F16: =IF(E16>=D16,"ОК","ОШИБКА") -> ОК
A17: 12 | B17: Банков с договором не больше, чем в SAM | C17: Консервативный | D17: =Рынок!$D$7+Рынок!$D$8 -> 60 | E17: =Консервативный!J66 -> 4 | F17: =IF(E17<=D17,"ОК","ОШИБКА") -> ОК
A18: 13 | B18: Выручка = подписка + внедрение | C18: Базовый | D18: =Базовый!K73+Базовый!K72 -> 171.04852 | E18: =Базовый!K74 -> 171.04852 | F18: =IF(ABS(E18-D18)<0.000001,"ОК","ОШИБКА") -> ОК | G18: итоги 2027–2031
A19: 14 | B19: Подписка = ВТБ + уровень 1 + уровень 2 | C19: Базовый | D19: =Базовый!K69+Базовый!K70+Базовый!K71 -> 126.07093 | E19: =Базовый!K73 -> 126.07093 | F19: =IF(ABS(E19-D19)<0.000001,"ОК","ОШИБКА") -> ОК
A20: 15 | B20: Накопленный поток = сумма потоков | C20: Базовый | D20: =Базовый!K116 -> -12.567507 | E20: =Базовый!J117 -> -12.567507 | F20: =IF(ABS(E20-D20)<0.000001,"ОК","ОШИБКА") -> ОК
A21: 16 | B21: Чистая прибыль = EBITDA − налог | C21: Базовый | D21: =Базовый!K105-Базовый!K110 -> 4.1446186 | E21: =Базовый!K112 -> 4.1446186 | F21: =IF(ABS(E21-D21)<0.000001,"ОК","ОШИБКА") -> ОК
A22: 17 | B22: Численность и договоры не отрицательные | C22: Базовый | D22: 0 | E22: =MIN(Базовый!E77:J77,Базовый!F66:J66) -> 1 | F22: =IF(E22>=D22,"ОК","ОШИБКА") -> ОК
A23: 18 | B23: Банков с договором не больше, чем в SAM | C23: Базовый | D23: =Рынок!$E$7+Рынок!$E$8 -> 60 | E23: =Базовый!J66 -> 11 | F23: =IF(E23<=D23,"ОК","ОШИБКА") -> ОК
A24: 19 | B24: Выручка = подписка + внедрение | C24: Оптимистичный | D24: =Оптимистичный!K73+Оптимистичный!K72 -> 322.68477 | E24: =Оптимистичный!K74 -> 322.68477 | F24: =IF(ABS(E24-D24)<0.000001,"ОК","ОШИБКА") -> ОК | G24: итоги 2027–2031
A25: 20 | B25: Подписка = ВТБ + уровень 1 + уровень 2 | C25: Оптимистичный | D25: =Оптимистичный!K69+Оптимистичный!K70+Оптимистичный!K71 -> 235.49572 | E25: =Оптимистичный!K73 -> 235.49572 | F25: =IF(ABS(E25-D25)<0.000001,"ОК","ОШИБКА") -> ОК
A26: 21 | B26: Накопленный поток = сумма потоков | C26: Оптимистичный | D26: =Оптимистичный!K116 -> 26.056892 | E26: =Оптимистичный!J117 -> 26.056892 | F26: =IF(ABS(E26-D26)<0.000001,"ОК","ОШИБКА") -> ОК
A27: 22 | B27: Чистая прибыль = EBITDA − налог | C27: Оптимистичный | D27: =Оптимистичный!K105-Оптимистичный!K110 -> 49.374435 | E27: =Оптимистичный!K112 -> 49.374435 | F27: =IF(ABS(E27-D27)<0.000001,"ОК","ОШИБКА") -> ОК
A28: 23 | B28: Численность и договоры не отрицательные | C28: Оптимистичный | D28: 0 | E28: =MIN(Оптимистичный!E77:J77,Оптимистичный!F66:J66) -> 1 | F28: =IF(E28>=D28,"ОК","ОШИБКА") -> ОК
A29: 24 | B29: Банков с договором не больше, чем в SAM | C29: Оптимистичный | D29: =Рынок!$F$7+Рынок!$F$8 -> 60 | E29: =Оптимистичный!J66 -> 18 | F29: =IF(E29<=D29,"ОК","ОШИБКА") -> ОК
A30: 25 | B30: Доли уровней в сумме 100 % | C30: Консервативный | D30: 1 | E30: =Рынок!$D$10+Рынок!$D$11+Рынок!$D$29/Рынок!$D$26 -> 1 | F30: =IF(ABS(E30-D30)<0.000001,"ОК","ОШИБКА") -> ОК
A31: 26 | B31: Банков уровня 3 не меньше нуля | C31: Консервативный | D31: 0 | E31: =Рынок!$D$25 -> 241 | F31: =IF(E31>=D31,"ОК","ОШИБКА") -> ОК
A32: 27 | B32: Доли уровней в сумме 100 % | C32: Базовый | D32: 1 | E32: =Рынок!$E$10+Рынок!$E$11+Рынок!$E$29/Рынок!$E$26 -> 1 | F32: =IF(ABS(E32-D32)<0.000001,"ОК","ОШИБКА") -> ОК
A33: 28 | B33: Банков уровня 3 не меньше нуля | C33: Базовый | D33: 0 | E33: =Рынок!$E$25 -> 241 | F33: =IF(E33>=D33,"ОК","ОШИБКА") -> ОК
A34: 29 | B34: Доли уровней в сумме 100 % | C34: Оптимистичный | D34: 1 | E34: =Рынок!$F$10+Рынок!$F$11+Рынок!$F$29/Рынок!$F$26 -> 1 | F34: =IF(ABS(E34-D34)<0.000001,"ОК","ОШИБКА") -> ОК
A35: 30 | B35: Банков уровня 3 не меньше нуля | C35: Оптимистичный | D35: 0 | E35: =Рынок!$F$25 -> 241 | F35: =IF(E35>=D35,"ОК","ОШИБКА") -> ОК
A36: 31 | B36: Блок чувствительности без изменений = лист «Базовый» | C36: Базовый | D36: =Базовый!$D$136 -> -0.14959473 | E36: =Чувствительность!$D$151 -> -0.14959473 | F36: =IF(ABS(E36-D36)<0.000001,"ОК","ОШИБКА") -> ОК | G36: блоки чувствительности считаются той же формулой
A37: Допущения о цене и рынке
A38: 32 | B38: Подписка не больше 15 % прямого эффекта банка (ёмкость) | C38: Консервативный | D38: 0.15 | E38: ='Эффект для банка'!$D$67 -> 0.11669107 | F38: =IF(E38<=D38,"ОК","ВНИМАНИЕ") -> ОК | G38: клиент оставляет себе не меньше 85 % эффекта
A39: 33 | B39: Купить дешевле, чем сделать самим | C39: Консервативный | D39: 1 | E39: ='Эффект для банка'!$D$71 -> 0.4640146 | F39: =IF(E39<D39,"ОК","ВНИМАНИЕ") -> ОК | G39: затраты в год за горизонт сравнения
A40: 34 | B40: SOM не больше 40 % SAM при полном охвате | C40: Консервативный | D40: 0.4 | E40: =Рынок!$D$45 -> 0.096624629 | F40: =IF(E40<=D40,"ОК","ВНИМАНИЕ") -> ОК | G40: доля сегмента за 5 лет
A41: 35 | B41: Подписка не больше 15 % прямого эффекта банка (ёмкость) | C41: Базовый | D41: 0.15 | E41: ='Эффект для банка'!$E$67 -> 0.091076672 | F41: =IF(E41<=D41,"ОК","ВНИМАНИЕ") -> ОК | G41: клиент оставляет себе не меньше 85 % эффекта
A42: 36 | B42: Купить дешевле, чем сделать самим | C42: Базовый | D42: 1 | E42: ='Эффект для банка'!$E$71 -> 0.77113553 | F42: =IF(E42<D42,"ОК","ВНИМАНИЕ") -> ОК | G42: затраты в год за горизонт сравнения
A43: 37 | B43: SOM не больше 40 % SAM при полном охвате | C43: Базовый | D43: 0.4 | E43: =Рынок!$E$45 -> 0.18798428 | F43: =IF(E43<=D43,"ОК","ВНИМАНИЕ") -> ОК | G43: доля сегмента за 5 лет
A44: 38 | B44: Подписка не больше 15 % прямого эффекта банка (ёмкость) | C44: Оптимистичный | D44: 0.15 | E44: ='Эффект для банка'!$F$67 -> 0.044442143 | F44: =IF(E44<=D44,"ОК","ВНИМАНИЕ") -> ОК | G44: клиент оставляет себе не меньше 85 % эффекта
A45: 39 | B45: Купить дешевле, чем сделать самим | C45: Оптимистичный | D45: 1 | E45: ='Эффект для банка'!$F$71 -> 0.94448529 | F45: =IF(E45<D45,"ОК","ВНИМАНИЕ") -> ОК | G45: затраты в год за горизонт сравнения
A46: 40 | B46: SOM не больше 40 % SAM при полном охвате | C46: Оптимистичный | D46: 0.4 | E46: =Рынок!$F$45 -> 0.21914007 | F46: =IF(E46<=D46,"ОК","ВНИМАНИЕ") -> ОК | G46: доля сегмента за 5 лет
B48: Ошибок целостности | E48: =IF(F6="ОК",0,1)+IF(F7="ОК",0,1)+IF(F8="ОК",0,1)+IF(F9="ОК",0,1)+IF(F10="ОК",0,1)+IF(F11="ОК",0,1)+IF(F12="ОК",0,1)+IF(F13="ОК",0,1)+IF(F14="ОК",0,1)+IF(F15="ОК",0,1)+IF(F16="ОК",0,1)+IF(F17="ОК",0,1)+IF(F18="ОК",0,1)+IF(F19="ОК",0,1)+IF(F20="ОК",0,1)+IF(F21="ОК",0,1)+IF(F22="ОК",0,1)+IF(F23="ОК",0,1)+IF(F24="ОК",0,1)+IF(F25="ОК",0,1)+IF(F26="ОК",0,1)+IF(F27="ОК",0,1)+IF(F28="ОК",0,1)+IF(F29="ОК",0,1)+IF(F30="ОК",0,1)+IF(F31="ОК",0,1)+IF(F32="ОК",0,1)+IF(F33="ОК",0,1)+IF(F34="ОК",0,1)+IF(F35="ОК",0,1)+IF(F36="ОК",0,1) -> 0
B49: Предупреждений о допущениях | E49: =IF(F38="ОК",0,1)+IF(F39="ОК",0,1)+IF(F40="ОК",0,1)+IF(F41="ОК",0,1)+IF(F42="ОК",0,1)+IF(F43="ОК",0,1)+IF(F44="ОК",0,1)+IF(F45="ОК",0,1)+IF(F46="ОК",0,1) -> 0
B50: Итог | F50: =IF(E48=0,"ОК","ОШИБКА") -> ОК

Sheet Источники
A1: Источники
A2: Строки M-xx и C-xx — в CLAIMS_REGISTRY.md репозитория; там же граница каждого утверждения
A4: Код | B4: Что подтверждает | C4: Источник | D4: Дата | E4: Статус | F4: Ссылка
A5: S01 | B5: Числа о продукте: правила, автотесты, корпус, задержка | C5: evidence.json, сборка 27.10.2026; команды — в CLAIMS_REGISTRY.md (C-01…C-17) | D5: 27.10.2026 | E5: репозиторий | F5: https://github.com/KonkovDV/Mandat/blob/main/evidence.json
A6: S02 | B6: Сценарии эффекта для ВТБ (ставки, ущерб) | C6: src/mandat/data/effect_scenarios.json; python scripts/effect_model.py --scenarios (C-15, C-16) | D6: 27.10.2026 | E6: репозиторий | F6: https://github.com/KonkovDV/Mandat/blob/main/docs/ECONOMICS.md
A7: S03 | B7: Операции без согласия у юрлиц, I кв. 2026: 818 операций, 573 млн ₽, возмещено 15,9 % по счетам | C7: Банк России, обзор отчётности об инцидентах ИБ при переводе денежных средств (M-07) | D7: 14.05.2026 | E7: первичный | F7: https://cbr.ru
A8: S04 | B8: II кв. 2026: у юрлиц похищено свыше 830 млн ₽, доля юрлиц в потерях 11,3 % | C8: Банк России, обзор за II кв. 2026, в пересказе Интерфакса и Smart-Lab (M-15) | D8: 04.08.2026 | E8: вторичный | F8: https://cbr.ru
A9: S05 | B9: ВТБ обслуживает около 1,8 млн предприятий и предпринимателей | C9: Пресс-релиз ВТБ к МСФО за I полугодие 2026 в пересказе altapress.ru и kp.ru (M-09) | D9: 07.2026 | E9: вторичный | F9: https://altapress.ru
A10: S06 | B10: В реестре ФНС более 5 млн МЧД | C10: ФНС, nalog.gov.ru (M-08) | D10: 27.07.2026 | E10: первичный | F10: https://www.nalog.gov.ru
A11: S07 | B11: Около 1,6 млн МЧД в реестре ФНС | C11: emchd.ru (M-10) | D11: 28.10.2024 | E11: вторичный | F11: https://emchd.ru
A12: S08 | B12: Реестр МСП на 10.07.2026: 6 612 445 субъектов, из них 2 022 689 юрлиц и 4 589 756 ИП | C12: ФНС, ежегодное обновление реестра, в пересказе «ОПОРЫ РОССИИ» и v2b.ru (M-20) | D12: 13.07.2026 | E12: вторичный | F12: https://www.v2b.ru/2026/07/13/reestr-msp-obnovilsya-kolichestvo-predprinimateley-dostiglo-6-6-mln/
A13: S09 | B13: Перечень системно значимых банков: 12 банков, около 80 % активов | C13: The Moscow Times, vbr.ru (M-21) | D13: 07.10.2026 | E13: вторичный | F13: https://www.vbr.ru/novosti/banki/2026/10/08/bank-rossii-ytverdil-perecen-sistemno-znacimih-bankov/
A14: S10 | B14: 301 банк на 01.07.2026 | C14: brobank.ru по данным Банка России (M-22) | D14: 07.2026 | E14: вторичный | F14: https://brobank.ru/skolko-bankov-na-segodnya/
A15: S11 | B15: Ключевая ставка 14 % | C15: Решение Банка России 23.10.2026 в пересказе СМИ (M-23) | D15: 23.10.2026 | E15: вторичный | F15: https://bankiros.ru
... A34: S30 | B34: Конкуренты и ниша: проверено и не проверено | C34: docs/COMPETITORS.md, проверено 13.10.2026 | D34: 13.10.2026 | E34: репозиторий | F34: https://github.com/KonkovDV/Mandat/blob/main/docs/COMPETITORS.md
